Workbook

Sheet Start
A1: Step | B1: Instructions
A2: Release | B2: TEST ONLY — SYNTHETIC INPUTS — NEVER RESEARCH DATA
A3: Coordinator | B3: Assign two different people to the two role files. Distribute only the corresponding file to each person. Roles are labels, not person IDs. This standalone file cannot verify the identity in another file.
A4: 1. Begin | B4: Save As a working copy in Excel. Enter your own reviewer ID (or identifying name) in Setup B2 and optional full name in B3. Setup B4 identifies this file's role; B5 is the cohort year.
A5: 2. Read | B5: Use Papers links to open each C_ sheet. Candidate-key links open embedded Evidence. Filter Candidates, Evidence, Links and Relations by key for full context. Click source labels in Links to open original PDFs. Keep the source-folder structure when using relative links.
A6: 3. Assess | B6: Choose D=retain, exclude, or discuss. Confirm or change the AI-suggested domain in E. Answer applicable H-L, using Codebook definitions. R holds optional English notes. Yellow = common/required; blue = optional; gray = inactive. M-Q are empty spacers.
A7: 4. Applicability | B7: For retain: statistical_results requires H and I; J is optional. report_internal_inconsistency and plan_material require K. protocol_report has no extra required judgment; L is optional. Exclude/discuss have no active H-L judgments.
A8: 5. Defaults | B8: Untouched H-L formulas display blank for a potentially applicable field while D is blank or retain; otherwise not_applicable. Choosing an answer replaces its formula. Blank means unanswered, with no inherited answer. Optional active fields may stay blank. Active fields cannot use not_applicable.
A9: 6. Changes | B9: Before changing a completed row, manually set F=no, make changes, review again, then mark primary_done. Excel formulas cannot reset an entered flag. Domain/disposition changes do not erase literal answers. CLEAR INACTIVE VALUES: delete stale inactive answers or set them to not_applicable; answer newly active required fields.
A10: 7. Finish each row | B10: After manual evidence review, set F=primary_done. G must show PRIMARY READY. Invalid pasted values are checked as well as dropdown choices. D and a valid E are required even for exclude/discuss. Completion alone does not establish scientific accuracy.
A11: 8. Inspect and deliver | B11: Inspect G and Checks; filter Decisions status for unfinished rows. When Checks shows PRIMARY READY, save the completed workbook and deliver this file. Review, calculations and delivery use Excel alone. Keep normal Excel backup copies; never regenerate a completed review file.
A12: Uncertainty | B12: Discuss is a completed independent response when otherwise valid. It records unresolved scientific uncertainty and initiates no shared workflow. Checks displays discuss totals separately; completing data entry does not resolve uncertainty.
... A17: Validation status | B17: Construction static and formula-engine checks are documented in the accompanying VALIDATION.md. Interactive desktop Excel smoke testing and visual rendering are pending. Excel recalculates on opening.

Sheet Setup
A1: Field | B1: Value
A2: reviewerId / identifying name | B2: TEST_REVIEWER
A3: reviewerName (optional) | B3: TEST ONLY
A4: reviewerRole | B4: R_A
A5: year | B5: 2025

Sheet Checks
A1: Check | B1: Result
A2: Reviewer role | B2: =Setup!B4 -> R_A
A3: Candidates | B3: 131
A4: Primary ready rows | B4: =COUNTIF(Decisions!G2:G132,"PRIMARY READY") -> 131
A5: Unfinished rows | B5: =B3-B4 -> 0
A6: Discuss / unresolved rows | B6: =COUNTIF(Decisions!K2:K132,"discuss") -> 0
A7: Workflow status | B7: =IF(B4=B3,"PRIMARY READY","ACTION NEEDED") -> PRIMARY READY
A8: Interpretation | B8: Completion means independent entry is finished. Discuss remains unresolved; affected paper outcome counts are withheld.
A9: Next action | B9: Filter Decisions status; return to C_ inputs. When primary-ready, save and deliver this file.
A10: Ready discuss rows | B10: =COUNTIFS(Decisions!G2:G132,"PRIMARY READY",Decisions!K2:K132,"discuss") -> 0

Sheet Papers
A1: Paper | B1: Review worksheet | C1: Candidates
A2: jama.2024.24764 | B2: C_jama.2024.24764 | C2: 8
A3: jama.2024.27643 | B3: C_jama.2024.27643 | C3: 8
A4: jama.2025.11178 | B4: C_jama.2025.11178 | C4: 37
A5: jama.2025.15185 | B5: C_jama.2025.15185 | C5: 12
A6: jama.2025.15440 | B6: C_jama.2025.15440 | C6: 2
A7: jama.2025.16450 | B7: C_jama.2025.16450 | C7: 10
A8: jama.2025.19563 | B8: C_jama.2025.19563 | C8: 7
A9: jama.2025.19843 | B9: C_jama.2025.19843 | C9: 1
A10: jama.2025.20765 | B10: C_jama.2025.20765 | C10: 13
A11: jama.2025.24175 | B11: C_jama.2025.24175 | C11: 14
A12: jama.2025.4390 | B12: C_jama.2025.4390 | C12: 3
A13: jama.2025.7583 | B13: C_jama.2025.7583 | C13: 3
... A16: jama.2025.9663 | B16: C_jama.2025.9663 | C16: 3

Sheet C_jama.2024.24764
A1: Candidate key | B1: Candidate title | C1: Source location | D1: Disposition | E1: Review domain (AI suggestion; editable) | F1: Complete | G1: Validation hint | H1: Statistcal_or_numerical issue | I1: Substantiveness | J1: Downstream impact | K1: Report-internal or planning-material inconsistency | L1: Protocol interpretation | R1: Notes (optional)
A2: 2025::jama.2024.24764::C001 | B2: Smoking percentages use a different denominator from the printed smoking totals | C2: jama_atherton_2025_oi_240145_1741627844.85412.pdf — PDF p. 5, Table 1 | D2: retain | E2: statistical_results | F2: primary_done | G2: =IFERROR(IF(LEN(TRIM(CLEAN(SUBSTITUTE(Setup!$B$2,CHAR(160)," "))))=0,"CHECK REVIEWER ID",IF(OR(A2="",(COUNTIF('C_jama.2024.24764'!$A$2:$A$9,A2)+COUNTIF('C_jama.2024.27643'!$A$2:$A$9,A2)+COUNTIF('C_jama.2025.11178'!$A$2:$A$38,A2)+COUNTIF('C_jama.2025.15185'!$A$2:$A$13,A2)+COUNTIF('C_jama.2025.15440'!$A$2:$A$3,A2)+COUNTIF('C_jama.2025.16450'!$A$2:$A$11,A2)+COUNTIF('C_jama.2025.19563'!$A$2:$A$8,A2)+COUNTIF('C_jama.2025.19843'!$A$2:$A$2,A2)+COUNTIF('C_jama.2025.20765'!$A$2:$A$14,A2)+COUNTIF('C_jama.2025.24175'!$A$2:$A$15,A2)+COUNTIF('C_jama.2025.4390'!$A$2:$A$4,A2)+COUNTIF('C_jama.2025.7583'!$A$2:$A$4,A2)+COUNTIF('C_jama.2025.7710'!$A$2:$A$5,A2)+COUNTIF('C_jama.2025.9110'!$A$2:$A$7,A2)+COUNTIF('C_jama.2025.9663'!$A$2:$A$4,A2))<>1,COUNTIFS(Candidates!$G$2:$G$132,A2,Candidates!$K$2:$K$132,"jama.2024.24764")<>1),"CHECK KEY",IF(OR(AND(NOT(AND(D2="retain",E2="statistical_results")),H2<>"",H2<>"not_applicable"),AND(NOT(AND(D2="retain",E2="statistical_results")),I2<>"",I2<>"not_applicable"),AND(NOT(AND(D2="retain",E2="statistical_results")),J2<>"",J2<>"not_applicable"),AND(NOT(AND(D2="retain",OR(E2="report_internal_inconsistency",E2="plan_material"))),K2<>"",K2<>"not_applicable"),AND(NOT(AND(D2="retain",E2="protocol_report")),L2<>"",L2<>"not_applicable")),"CLEAR INACTIVE VALUES",IF(OR(NOT(OR(D2="retain",D2="exclude",D2="discuss")),NOT(OR(E2="statistical_results",E2="report_internal_inconsistency",E2="plan_material",E2="protocol_report")),AND(AND(D2="retain",E2="statistical_results"),NOT(OR(H2="confirmed_issue",H2="probable_issue",H2="not_issue",H2="indeterminate"))),AND(AND(D2="retain",E2="statistical_results"),NOT(OR(I2="substantive",I2="minor_presentation",I2="indeterminate"))),AND(AND(D2="retain",E2="statistical_results"),J2<>"",NOT(OR(J2="direct",J2="possible",J2="unlikely",J2="unknown"))),AND(AND(D2="retain",OR(E2="report_internal_inconsistency",E2="plan_material")),NOT(OR(K2="substantive_inconsistency",K2="minor_presentation",K2="non_inconsistency",K2="indeterminate"))),AND(AND(D2="retain",E2="protocol_report"),L2<>"",NOT(OR(L2="substantive_difference",L2="minor_presentation",L2="version_timing",L2="non_inconsistency",L2="indeterminate")))),"CHECK FIELDS",IF(AND(F2<>"",NOT(OR(F2="no",F2="primary_done"))),"CHECK COMPLETE",IF(F2="primary_done","PRIMARY READY","PRIMARY DRAFT")))))),"CHECK INPUT / KEY") -> PRIMARY READY | H2: confirmed_issue | I2: substantive | R2: TEST 2025::jama.2024.24764::C001
A3: 2025::jama.2024.24764::C002 | B3: Operating-surgeon level totals exceed participant denominators without a multi-response qualifier | C3: jama_atherton_2025_oi_240145_1741627844.85412.pdf — PDF p. 7, Table 2 | D3: retain | E3: statistical_results | F3: primary_done | G3: =IFERROR(IF(LEN(TRIM(CLEAN(SUBSTITUTE(Setup!$B$2,CHAR(160)," "))))=0,"CHECK REVIEWER ID",IF(OR(A3="",(COUNTIF('C_jama.2024.24764'!$A$2:$A$9,A3)+COUNTIF('C_jama.2024.27643'!$A$2:$A$9,A3)+COUNTIF('C_jama.2025.11178'!$A$2:$A$38,A3)+COUNTIF('C_jama.2025.15185'!$A$2:$A$13,A3)+COUNTIF('C_jama.2025.15440'!$A$2:$A$3,A3)+COUNTIF('C_jama.2025.16450'!$A$2:$A$11,A3)+COUNTIF('C_jama.2025.19563'!$A$2:$A$8,A3)+COUNTIF('C_jama.2025.19843'!$A$2:$A$2,A3)+COUNTIF('C_jama.2025.20765'!$A$2:$A$14,A3)+COUNTIF('C_jama.2025.24175'!$A$2:$A$15,A3)+COUNTIF('C_jama.2025.4390'!$A$2:$A$4,A3)+COUNTIF('C_jama.2025.7583'!$A$2:$A$4,A3)+COUNTIF('C_jama.2025.7710'!$A$2:$A$5,A3)+COUNTIF('C_jama.2025.9110'!$A$2:$A$7,A3)+COUNTIF('C_jama.2025.9663'!$A$2:$A$4,A3))<>1,COUNTIFS(Candidates!$G$2:$G$132,A3,Candidates!$K$2:$K$132,"jama.2024.24764")<>1),"CHECK KEY",IF(OR(AND(NOT(AND(D3="retain",E3="statistical_results")),H3<>"",H3<>"not_applicable"),AND(NOT(AND(D3="retain",E3="statistical_results")),I3<>"",I3<>"not_applicable"),AND(NOT(AND(D3="retain",E3="statistical_results")),J3<>"",J3<>"not_applicable"),AND(NOT(AND(D3="retain",OR(E3="report_internal_inconsistency",E3="plan_material"))),K3<>"",K3<>"not_applicable"),AND(NOT(AND(D3="retain",E3="protocol_report")),L3<>"",L3<>"not_applicable")),"CLEAR INACTIVE VALUES",IF(OR(NOT(OR(D3="retain",D3="exclude",D3="discuss")),NOT(OR(E3="statistical_results",E3="report_internal_inconsistency",E3="plan_material",E3="protocol_report")),AND(AND(D3="retain",E3="statistical_results"),NOT(OR(H3="confirmed_issue",H3="probable_issue",H3="not_issue",H3="indeterminate"))),AND(AND(D3="retain",E3="statistical_results"),NOT(OR(I3="substantive",I3="minor_presentation",I3="indeterminate"))),AND(AND(D3="retain",E3="statistical_results"),J3<>"",NOT(OR(J3="direct",J3="possible",J3="unlikely",J3="unknown"))),AND(AND(D3="retain",OR(E3="report_internal_inconsistency",E3="plan_material")),NOT(OR(K3="substantive_inconsistency",K3="minor_presentation",K3="non_inconsistency",K3="indeterminate"))),AND(AND(D3="retain",E3="protocol_report"),L3<>"",NOT(OR(L3="substantive_difference",L3="minor_presentation",L3="version_timing",L3="non_inconsistency",L3="indeterminate")))),"CHECK FIELDS",IF(AND(F3<>"",NOT(OR(F3="no",F3="primary_done"))),"CHECK COMPLETE",IF(F3="primary_done","PRIMARY READY","PRIMARY DRAFT")))))),"CHECK INPUT / KEY") -> PRIMARY READY | H3: confirmed_issue | I3: substantive | R3: TEST 2025::jama.2024.24764::C002
A4: 2025::jama.2024.24764::C003 | B4: Fascia-closing surgeon level totals exceed participant denominators without a multi-response qualifier | C4: jama_atherton_2025_oi_240145_1741627844.85412.pdf — PDF p. 7, Table 2 continuation | D4: retain | E4: statistical_results | F4: primary_done | G4: =IFERROR(IF(LEN(TRIM(CLEAN(SUBSTITUTE(Setup!$B$2,CHAR(160)," "))))=0,"CHECK REVIEWER ID",IF(OR(A4="",(COUNTIF('C_jama.2024.24764'!$A$2:$A$9,A4)+COUNTIF('C_jama.2024.27643'!$A$2:$A$9,A4)+COUNTIF('C_jama.2025.11178'!$A$2:$A$38,A4)+COUNTIF('C_jama.2025.15185'!$A$2:$A$13,A4)+COUNTIF('C_jama.2025.15440'!$A$2:$A$3,A4)+COUNTIF('C_jama.2025.16450'!$A$2:$A$11,A4)+COUNTIF('C_jama.2025.19563'!$A$2:$A$8,A4)+COUNTIF('C_jama.2025.19843'!$A$2:$A$2,A4)+COUNTIF('C_jama.2025.20765'!$A$2:$A$14,A4)+COUNTIF('C_jama.2025.24175'!$A$2:$A$15,A4)+COUNTIF('C_jama.2025.4390'!$A$2:$A$4,A4)+COUNTIF('C_jama.2025.7583'!$A$2:$A$4,A4)+COUNTIF('C_jama.2025.7710'!$A$2:$A$5,A4)+COUNTIF('C_jama.2025.9110'!$A$2:$A$7,A4)+COUNTIF('C_jama.2025.9663'!$A$2:$A$4,A4))<>1,COUNTIFS(Candidates!$G$2:$G$132,A4,Candidates!$K$2:$K$132,"jama.2024.24764")<>1),"CHECK KEY",IF(OR(AND(NOT(AND(D4="retain",E4="statistical_results")),H4<>"",H4<>"not_applicable"),AND(NOT(AND(D4="retain",E4="statistical_results")),I4<>"",I4<>"not_applicable"),AND(NOT(AND(D4="retain",E4="statistical_results")),J4<>"",J4<>"not_applicable"),AND(NOT(AND(D4="retain",OR(E4="report_internal_inconsistency",E4="plan_material"))),K4<>"",K4<>"not_applicable"),AND(NOT(AND(D4="retain",E4="protocol_report")),L4<>"",L4<>"not_applicable")),"CLEAR INACTIVE VALUES",IF(OR(NOT(OR(D4="retain",D4="exclude",D4="discuss")),NOT(OR(E4="statistical_results",E4="report_internal_inconsistency",E4="plan_material",E4="protocol_report")),AND(AND(D4="retain",E4="statistical_results"),NOT(OR(H4="confirmed_issue",H4="probable_issue",H4="not_issue",H4="indeterminate"))),AND(AND(D4="retain",E4="statistical_results"),NOT(OR(I4="substantive",I4="minor_presentation",I4="indeterminate"))),AND(AND(D4="retain",E4="statistical_results"),J4<>"",NOT(OR(J4="direct",J4="possible",J4="unlikely",J4="unknown"))),AND(AND(D4="retain",OR(E4="report_internal_inconsistency",E4="plan_material")),NOT(OR(K4="substantive_inconsistency",K4="minor_presentation",K4="non_inconsistency",K4="indeterminate"))),AND(AND(D4="retain",E4="protocol_report"),L4<>"",NOT(OR(L4="substantive_difference",L4="minor_presentation",L4="version_timing",L4="non_inconsistency",L4="indeterminate")))),"CHECK FIELDS",IF(AND(F4<>"",NOT(OR(F4="no",F4="primary_done"))),"CHECK COMPLETE",IF(F4="primary_done","PRIMARY READY","PRIMARY DRAFT")))))),"CHECK INPUT / KEY") -> PRIMARY READY | H4: confirmed_issue | I4: substantive | R4: TEST 2025::jama.2024.24764::C003
A5: 2025::jama.2024.24764::C004 | B5: Skin-closing surgeon level totals exceed participant denominators without a multi-response qualifier | C5: jama_atherton_2025_oi_240145_1741627844.85412.pdf — PDF p. 7, Table 2 continuation | D5: retain | E5: statistical_results | F5: primary_done | G5: =IFERROR(IF(LEN(TRIM(CLEAN(SUBSTITUTE(Setup!$B$2,CHAR(160)," "))))=0,"CHECK REVIEWER ID",IF(OR(A5="",(COUNTIF('C_jama.2024.24764'!$A$2:$A$9,A5)+COUNTIF('C_jama.2024.27643'!$A$2:$A$9,A5)+COUNTIF('C_jama.2025.11178'!$A$2:$A$38,A5)+COUNTIF('C_jama.2025.15185'!$A$2:$A$13,A5)+COUNTIF('C_jama.2025.15440'!$A$2:$A$3,A5)+COUNTIF('C_jama.2025.16450'!$A$2:$A$11,A5)+COUNTIF('C_jama.2025.19563'!$A$2:$A$8,A5)+COUNTIF('C_jama.2025.19843'!$A$2:$A$2,A5)+COUNTIF('C_jama.2025.20765'!$A$2:$A$14,A5)+COUNTIF('C_jama.2025.24175'!$A$2:$A$15,A5)+COUNTIF('C_jama.2025.4390'!$A$2:$A$4,A5)+COUNTIF('C_jama.2025.7583'!$A$2:$A$4,A5)+COUNTIF('C_jama.2025.7710'!$A$2:$A$5,A5)+COUNTIF('C_jama.2025.9110'!$A$2:$A$7,A5)+COUNTIF('C_jama.2025.9663'!$A$2:$A$4,A5))<>1,COUNTIFS(Candidates!$G$2:$G$132,A5,Candidates!$K$2:$K$132,"jama.2024.24764")<>1),"CHECK KEY",IF(OR(AND(NOT(AND(D5="retain",E5="statistical_results")),H5<>"",H5<>"not_applicable"),AND(NOT(AND(D5="retain",E5="statistical_results")),I5<>"",I5<>"not_applicable"),AND(NOT(AND(D5="retain",E5="statistical_results")),J5<>"",J5<>"not_applicable"),AND(NOT(AND(D5="retain",OR(E5="report_internal_inconsistency",E5="plan_material"))),K5<>"",K5<>"not_applicable"),AND(NOT(AND(D5="retain",E5="protocol_report")),L5<>"",L5<>"not_applicable")),"CLEAR INACTIVE VALUES",IF(OR(NOT(OR(D5="retain",D5="exclude",D5="discuss")),NOT(OR(E5="statistical_results",E5="report_internal_inconsistency",E5="plan_material",E5="protocol_report")),AND(AND(D5="retain",E5="statistical_results"),NOT(OR(H5="confirmed_issue",H5="probable_issue",H5="not_issue",H5="indeterminate"))),AND(AND(D5="retain",E5="statistical_results"),NOT(OR(I5="substantive",I5="minor_presentation",I5="indeterminate"))),AND(AND(D5="retain",E5="statistical_results"),J5<>"",NOT(OR(J5="direct",J5="possible",J5="unlikely",J5="unknown"))),AND(AND(D5="retain",OR(E5="report_internal_inconsistency",E5="plan_material")),NOT(OR(K5="substantive_inconsistency",K5="minor_presentation",K5="non_inconsistency",K5="indeterminate"))),AND(AND(D5="retain",E5="protocol_report"),L5<>"",NOT(OR(L5="substantive_difference",L5="minor_presentation",L5="version_timing",L5="non_inconsistency",L5="indeterminate")))),"CHECK FIELDS",IF(AND(F5<>"",NOT(OR(F5="no",F5="primary_done"))),"CHECK COMPLETE",IF(F5="primary_done","PRIMARY READY","PRIMARY DRAFT")))))),"CHECK INPUT / KEY") -> PRIMARY READY | H5: confirmed_issue | I5: substantive | R5: TEST 2025::jama.2024.24764::C004
A6: 2025::jama.2024.24764::C005 | B6: Control-arm mortality differs between participant flow and 30-day safety reporting | C6: jama_atherton_2025_oi_240145_1741627844.85412.pdf — PDF p. 3, Figure 1; PDF p. 6, safety narrative; PDF p. 8, Table 3 | D6: retain | E6: report_internal_inconsistency | F6: primary_done | G6: =IFERROR(IF(LEN(TRIM(CLEAN(SUBSTITUTE(Setup!$B$2,CHAR(160)," "))))=0,"CHECK REVIEWER ID",IF(OR(A6="",(COUNTIF('C_jama.2024.24764'!$A$2:$A$9,A6)+COUNTIF('C_jama.2024.27643'!$A$2:$A$9,A6)+COUNTIF('C_jama.2025.11178'!$A$2:$A$38,A6)+COUNTIF('C_jama.2025.15185'!$A$2:$A$13,A6)+COUNTIF('C_jama.2025.15440'!$A$2:$A$3,A6)+COUNTIF('C_jama.2025.16450'!$A$2:$A$11,A6)+COUNTIF('C_jama.2025.19563'!$A$2:$A$8,A6)+COUNTIF('C_jama.2025.19843'!$A$2:$A$2,A6)+COUNTIF('C_jama.2025.20765'!$A$2:$A$14,A6)+COUNTIF('C_jama.2025.24175'!$A$2:$A$15,A6)+COUNTIF('C_jama.2025.4390'!$A$2:$A$4,A6)+COUNTIF('C_jama.2025.7583'!$A$2:$A$4,A6)+COUNTIF('C_jama.2025.7710'!$A$2:$A$5,A6)+COUNTIF('C_jama.2025.9110'!$A$2:$A$7,A6)+COUNTIF('C_jama.2025.9663'!$A$2:$A$4,A6))<>1,COUNTIFS(Candidates!$G$2:$G$132,A6,Candidates!$K$2:$K$132,"jama.2024.24764")<>1),"CHECK KEY",IF(OR(AND(NOT(AND(D6="retain",E6="statistical_results")),H6<>"",H6<>"not_applicable"),AND(NOT(AND(D6="retain",E6="statistical_results")),I6<>"",I6<>"not_applicable"),AND(NOT(AND(D6="retain",E6="statistical_results")),J6<>"",J6<>"not_applicable"),AND(NOT(AND(D6="retain",OR(E6="report_internal_inconsistency",E6="plan_material"))),K6<>"",K6<>"not_applicable"),AND(NOT(AND(D6="retain",E6="protocol_report")),L6<>"",L6<>"not_applicable")),"CLEAR INACTIVE VALUES",IF(OR(NOT(OR(D6="retain",D6="exclude",D6="discuss")),NOT(OR(E6="statistical_results",E6="report_internal_inconsistency",E6="plan_material",E6="protocol_report")),AND(AND(D6="retain",E6="statistical_results"),NOT(OR(H6="confirmed_issue",H6="probable_issue",H6="not_issue",H6="indeterminate"))),AND(AND(D6="retain",E6="statistical_results"),NOT(OR(I6="substantive",I6="minor_presentation",I6="indeterminate"))),AND(AND(D6="retain",E6="statistical_results"),J6<>"",NOT(OR(J6="direct",J6="possible",J6="unlikely",J6="unknown"))),AND(AND(D6="retain",OR(E6="report_internal_inconsistency",E6="plan_material")),NOT(OR(K6="substantive_inconsistency",K6="minor_presentation",K6="non_inconsistency",K6="indeterminate"))),AND(AND(D6="retain",E6="protocol_report"),L6<>"",NOT(OR(L6="substantive_difference",L6="minor_presentation",L6="version_timing",L6="non_inconsistency",L6="indeterminate")))),"CHECK FIELDS",IF(AND(F6<>"",NOT(OR(F6="no",F6="primary_done"))),"CHECK COMPLETE",IF(F6="primary_done","PRIMARY READY","PRIMARY DRAFT")))))),"CHECK INPUT / KEY") -> PRIMARY READY | K6: substantive_inconsistency | R6: TEST 2025::jama.2024.24764::C005
A7: 2025::jama.2024.24764::C006 | B7: Longitudinal quality-of-life covariance specification differs between SAP and final article | C7: joi240145supp1_prod_1741627844.87412.pdf — PDF p. 26, SAP; jama_atherton_2025_oi_240145_1741627844.85412.pdf — PDF p. 4, Statistical Analysis | D7: retain | E7: protocol_report | F7: primary_done | G7: =IFERROR(IF(LEN(TRIM(CLEAN(SUBSTITUTE(Setup!$B$2,CHAR(160)," "))))=0,"CHECK REVIEWER ID",IF(OR(A7="",(COUNTIF('C_jama.2024.24764'!$A$2:$A$9,A7)+COUNTIF('C_jama.2024.27643'!$A$2:$A$9,A7)+COUNTIF('C_jama.2025.11178'!$A$2:$A$38,A7)+COUNTIF('C_jama.2025.15185'!$A$2:$A$13,A7)+COUNTIF('C_jama.2025.15440'!$A$2:$A$3,A7)+COUNTIF('C_jama.2025.16450'!$A$2:$A$11,A7)+COUNTIF('C_jama.2025.19563'!$A$2:$A$8,A7)+COUNTIF('C_jama.2025.19843'!$A$2:$A$2,A7)+COUNTIF('C_jama.2025.20765'!$A$2:$A$14,A7)+COUNTIF('C_jama.2025.24175'!$A$2:$A$15,A7)+COUNTIF('C_jama.2025.4390'!$A$2:$A$4,A7)+COUNTIF('C_jama.2025.7583'!$A$2:$A$4,A7)+COUNTIF('C_jama.2025.7710'!$A$2:$A$5,A7)+COUNTIF('C_jama.2025.9110'!$A$2:$A$7,A7)+COUNTIF('C_jama.2025.9663'!$A$2:$A$4,A7))<>1,COUNTIFS(Candidates!$G$2:$G$132,A7,Candidates!$K$2:$K$132,"jama.2024.24764")<>1),"CHECK KEY",IF(OR(AND(NOT(AND(D7="retain",E7="statistical_results")),H7<>"",H7<>"not_applicable"),AND(NOT(AND(D7="retain",E7="statistical_results")),I7<>"",I7<>"not_applicable"),AND(NOT(AND(D7="retain",E7="statistical_results")),J7<>"",J7<>"not_applicable"),AND(NOT(AND(D7="retain",OR(E7="report_internal_inconsistency",E7="plan_material"))),K7<>"",K7<>"not_applicable"),AND(NOT(AND(D7="retain",E7="protocol_report")),L7<>"",L7<>"not_applicable")),"CLEAR INACTIVE VALUES",IF(OR(NOT(OR(D7="retain",D7="exclude",D7="discuss")),NOT(OR(E7="statistical_results",E7="report_internal_inconsistency",E7="plan_material",E7="protocol_report")),AND(AND(D7="retain",E7="statistical_results"),NOT(OR(H7="confirmed_issue",H7="probable_issue",H7="not_issue",H7="indeterminate"))),AND(AND(D7="retain",E7="statistical_results"),NOT(OR(I7="substantive",I7="minor_presentation",I7="indeterminate"))),AND(AND(D7="retain",E7="statistical_results"),J7<>"",NOT(OR(J7="direct",J7="possible",J7="unlikely",J7="unknown"))),AND(AND(D7="retain",OR(E7="report_internal_inconsistency",E7="plan_material")),NOT(OR(K7="substantive_inconsistency",K7="minor_presentation",K7="non_inconsistency",K7="indeterminate"))),AND(AND(D7="retain",E7="protocol_report"),L7<>"",NOT(OR(L7="substantive_difference",L7="minor_presentation",L7="version_timing",L7="non_inconsistency",L7="indeterminate")))),"CHECK FIELDS",IF(AND(F7<>"",NOT(OR(F7="no",F7="primary_done"))),"CHECK COMPLETE",IF(F7="primary_done","PRIMARY READY","PRIMARY DRAFT")))))),"CHECK INPUT / KEY") -> PRIMARY READY | R7: TEST 2025::jama.2024.24764::C006
A8: 2025::jama.2024.24764::C007 | B8: Length-of-stay effect measure and model differ between SAP/protocol and final article | C8: joi240145supp1_prod_1741627844.87412.pdf — PDF p. 25, SAP; joi240145supp4_prod_1741627844.90412.pdf — PDF p. 39, protocol; jama_atherton_2025_oi_240145_1741627844.85412.pdf — PDF p. 4; PDF p. 8, Table 3 | D8: retain | E8: protocol_report | F8: primary_done | G8: =IFERROR(IF(LEN(TRIM(CLEAN(SUBSTITUTE(Setup!$B$2,CHAR(160)," "))))=0,"CHECK REVIEWER ID",IF(OR(A8="",(COUNTIF('C_jama.2024.24764'!$A$2:$A$9,A8)+COUNTIF('C_jama.2024.27643'!$A$2:$A$9,A8)+COUNTIF('C_jama.2025.11178'!$A$2:$A$38,A8)+COUNTIF('C_jama.2025.15185'!$A$2:$A$13,A8)+COUNTIF('C_jama.2025.15440'!$A$2:$A$3,A8)+COUNTIF('C_jama.2025.16450'!$A$2:$A$11,A8)+COUNTIF('C_jama.2025.19563'!$A$2:$A$8,A8)+COUNTIF('C_jama.2025.19843'!$A$2:$A$2,A8)+COUNTIF('C_jama.2025.20765'!$A$2:$A$14,A8)+COUNTIF('C_jama.2025.24175'!$A$2:$A$15,A8)+COUNTIF('C_jama.2025.4390'!$A$2:$A$4,A8)+COUNTIF('C_jama.2025.7583'!$A$2:$A$4,A8)+COUNTIF('C_jama.2025.7710'!$A$2:$A$5,A8)+COUNTIF('C_jama.2025.9110'!$A$2:$A$7,A8)+COUNTIF('C_jama.2025.9663'!$A$2:$A$4,A8))<>1,COUNTIFS(Candidates!$G$2:$G$132,A8,Candidates!$K$2:$K$132,"jama.2024.24764")<>1),"CHECK KEY",IF(OR(AND(NOT(AND(D8="retain",E8="statistical_results")),H8<>"",H8<>"not_applicable"),AND(NOT(AND(D8="retain",E8="statistical_results")),I8<>"",I8<>"not_applicable"),AND(NOT(AND(D8="retain",E8="statistical_results")),J8<>"",J8<>"not_applicable"),AND(NOT(AND(D8="retain",OR(E8="report_internal_inconsistency",E8="plan_material"))),K8<>"",K8<>"not_applicable"),AND(NOT(AND(D8="retain",E8="protocol_report")),L8<>"",L8<>"not_applicable")),"CLEAR INACTIVE VALUES",IF(OR(NOT(OR(D8="retain",D8="exclude",D8="discuss")),NOT(OR(E8="statistical_results",E8="report_internal_inconsistency",E8="plan_material",E8="protocol_report")),AND(AND(D8="retain",E8="statistical_results"),NOT(OR(H8="confirmed_issue",H8="probable_issue",H8="not_issue",H8="indeterminate"))),AND(AND(D8="retain",E8="statistical_results"),NOT(OR(I8="substantive",I8="minor_presentation",I8="indeterminate"))),AND(AND(D8="retain",E8="statistical_results"),J8<>"",NOT(OR(J8="direct",J8="possible",J8="unlikely",J8="unknown"))),AND(AND(D8="retain",OR(E8="report_internal_inconsistency",E8="plan_material")),NOT(OR(K8="substantive_inconsistency",K8="minor_presentation",K8="non_inconsistency",K8="indeterminate"))),AND(AND(D8="retain",E8="protocol_report"),L8<>"",NOT(OR(L8="substantive_difference",L8="minor_presentation",L8="version_timing",L8="non_inconsistency",L8="indeterminate")))),"CHECK FIELDS",IF(AND(F8<>"",NOT(OR(F8="no",F8="primary_done"))),"CHECK COMPLETE",IF(F8="primary_done","PRIMARY READY","PRIMARY DRAFT")))))),"CHECK INPUT / KEY") -> PRIMARY READY | R8: TEST 2025::jama.2024.24764::C007
A9: 2025::jama.2024.24764::C008 | B9: Australia-inclusive length-of-stay result differs from the stated UK-only analysis population | C9: joi240145supp1_prod_1741627844.87412.pdf — PDF p. 18, SAP endpoint; PDF p. 25, SAP population; joi240145supp4_prod_1741627844.90412.pdf — PDF p. 24, protocol; jama_atherton_2025_oi_240145_1741627844.85412.pdf — PDF p. 1, abstract; PDF p. 8, Table 3 | D9: retain | E9: protocol_report | F9: primary_done | G9: =IFERROR(IF(LEN(TRIM(CLEAN(SUBSTITUTE(Setup!$B$2,CHAR(160)," "))))=0,"CHECK REVIEWER ID",IF(OR(A9="",(COUNTIF('C_jama.2024.24764'!$A$2:$A$9,A9)+COUNTIF('C_jama.2024.27643'!$A$2:$A$9,A9)+COUNTIF('C_jama.2025.11178'!$A$2:$A$38,A9)+COUNTIF('C_jama.2025.15185'!$A$2:$A$13,A9)+COUNTIF('C_jama.2025.15440'!$A$2:$A$3,A9)+COUNTIF('C_jama.2025.16450'!$A$2:$A$11,A9)+COUNTIF('C_jama.2025.19563'!$A$2:$A$8,A9)+COUNTIF('C_jama.2025.19843'!$A$2:$A$2,A9)+COUNTIF('C_jama.2025.20765'!$A$2:$A$14,A9)+COUNTIF('C_jama.2025.24175'!$A$2:$A$15,A9)+COUNTIF('C_jama.2025.4390'!$A$2:$A$4,A9)+COUNTIF('C_jama.2025.7583'!$A$2:$A$4,A9)+COUNTIF('C_jama.2025.7710'!$A$2:$A$5,A9)+COUNTIF('C_jama.2025.9110'!$A$2:$A$7,A9)+COUNTIF('C_jama.2025.9663'!$A$2:$A$4,A9))<>1,COUNTIFS(Candidates!$G$2:$G$132,A9,Candidates!$K$2:$K$132,"jama.2024.24764")<>1),"CHECK KEY",IF(OR(AND(NOT(AND(D9="retain",E9="statistical_results")),H9<>"",H9<>"not_applicable"),AND(NOT(AND(D9="retain",E9="statistical_results")),I9<>"",I9<>"not_applicable"),AND(NOT(AND(D9="retain",E9="statistical_results")),J9<>"",J9<>"not_applicable"),AND(NOT(AND(D9="retain",OR(E9="report_internal_inconsistency",E9="plan_material"))),K9<>"",K9<>"not_applicable"),AND(NOT(AND(D9="retain",E9="protocol_report")),L9<>"",L9<>"not_applicable")),"CLEAR INACTIVE VALUES",IF(OR(NOT(OR(D9="retain",D9="exclude",D9="discuss")),NOT(OR(E9="statistical_results",E9="report_internal_inconsistency",E9="plan_material",E9="protocol_report")),AND(AND(D9="retain",E9="statistical_results"),NOT(OR(H9="confirmed_issue",H9="probable_issue",H9="not_issue",H9="indeterminate"))),AND(AND(D9="retain",E9="statistical_results"),NOT(OR(I9="substantive",I9="minor_presentation",I9="indeterminate"))),AND(AND(D9="retain",E9="statistical_results"),J9<>"",NOT(OR(J9="direct",J9="possible",J9="unlikely",J9="unknown"))),AND(AND(D9="retain",OR(E9="report_internal_inconsistency",E9="plan_material")),NOT(OR(K9="substantive_inconsistency",K9="minor_presentation",K9="non_inconsistency",K9="indeterminate"))),AND(AND(D9="retain",E9="protocol_report"),L9<>"",NOT(OR(L9="substantive_difference",L9="minor_presentation",L9="version_timing",L9="non_inconsistency",L9="indeterminate")))),"CHECK FIELDS",IF(AND(F9<>"",NOT(OR(F9="no",F9="primary_done"))),"CHECK COMPLETE",IF(F9="primary_done","PRIMARY READY","PRIMARY DRAFT")))))),"CHECK INPUT / KEY") -> PRIMARY READY | R9: TEST 2025::jama.2024.24764::C008

Sheet C_jama.2024.27643
A1: Candidate key | B1: Candidate title | C1: Source location | D1: Disposition | E1: Review domain (AI suggestion; editable) | F1: Complete | G1: Validation hint | H1: Statistcal_or_numerical issue | I1: Substantiveness | J1: Downstream impact | K1: Report-internal or planning-material inconsistency | L1: Protocol interpretation | R1: Notes (optional)
A2: 2025::jama.2024.27643::C001 | B2: Shared-placebo race missingness does not reconcile with the printed denominator | C2: jama_berry_2025_oi_240158_1742927563.7361.pdf — Table 1 and footnote b, PDF p. 6 | D2: retain | E2: statistical_results | F2: primary_done | G2: =IFERROR(IF(LEN(TRIM(CLEAN(SUBSTITUTE(Setup!$B$2,CHAR(160)," "))))=0,"CHECK REVIEWER ID",IF(OR(A2="",(COUNTIF('C_jama.2024.24764'!$A$2:$A$9,A2)+COUNTIF('C_jama.2024.27643'!$A$2:$A$9,A2)+COUNTIF('C_jama.2025.11178'!$A$2:$A$38,A2)+COUNTIF('C_jama.2025.15185'!$A$2:$A$13,A2)+COUNTIF('C_jama.2025.15440'!$A$2:$A$3,A2)+COUNTIF('C_jama.2025.16450'!$A$2:$A$11,A2)+COUNTIF('C_jama.2025.19563'!$A$2:$A$8,A2)+COUNTIF('C_jama.2025.19843'!$A$2:$A$2,A2)+COUNTIF('C_jama.2025.20765'!$A$2:$A$14,A2)+COUNTIF('C_jama.2025.24175'!$A$2:$A$15,A2)+COUNTIF('C_jama.2025.4390'!$A$2:$A$4,A2)+COUNTIF('C_jama.2025.7583'!$A$2:$A$4,A2)+COUNTIF('C_jama.2025.7710'!$A$2:$A$5,A2)+COUNTIF('C_jama.2025.9110'!$A$2:$A$7,A2)+COUNTIF('C_jama.2025.9663'!$A$2:$A$4,A2))<>1,COUNTIFS(Candidates!$G$2:$G$132,A2,Candidates!$K$2:$K$132,"jama.2024.27643")<>1),"CHECK KEY",IF(OR(AND(NOT(AND(D2="retain",E2="statistical_results")),H2<>"",H2<>"not_applicable"),AND(NOT(AND(D2="retain",E2="statistical_results")),I2<>"",I2<>"not_applicable"),AND(NOT(AND(D2="retain",E2="statistical_results")),J2<>"",J2<>"not_applicable"),AND(NOT(AND(D2="retain",OR(E2="report_internal_inconsistency",E2="plan_material"))),K2<>"",K2<>"not_applicable"),AND(NOT(AND(D2="retain",E2="protocol_report")),L2<>"",L2<>"not_applicable")),"CLEAR INACTIVE VALUES",IF(OR(NOT(OR(D2="retain",D2="exclude",D2="discuss")),NOT(OR(E2="statistical_results",E2="report_internal_inconsistency",E2="plan_material",E2="protocol_report")),AND(AND(D2="retain",E2="statistical_results"),NOT(OR(H2="confirmed_issue",H2="probable_issue",H2="not_issue",H2="indeterminate"))),AND(AND(D2="retain",E2="statistical_results"),NOT(OR(I2="substantive",I2="minor_presentation",I2="indeterminate"))),AND(AND(D2="retain",E2="statistical_results"),J2<>"",NOT(OR(J2="direct",J2="possible",J2="unlikely",J2="unknown"))),AND(AND(D2="retain",OR(E2="report_internal_inconsistency",E2="plan_material")),NOT(OR(K2="substantive_inconsistency",K2="minor_presentation",K2="non_inconsistency",K2="indeterminate"))),AND(AND(D2="retain",E2="protocol_report"),L2<>"",NOT(OR(L2="substantive_difference",L2="minor_presentation",L2="version_timing",L2="non_inconsistency",L2="indeterminate")))),"CHECK FIELDS",IF(AND(F2<>"",NOT(OR(F2="no",F2="primary_done"))),"CHECK COMPLETE",IF(F2="primary_done","PRIMARY READY","PRIMARY DRAFT")))))),"CHECK INPUT / KEY") -> PRIMARY READY | H2: confirmed_issue | I2: substantive | R2: TEST 2025::jama.2024.27643::C001
A3: 2025::jama.2024.27643::C002 | B3: SVC values have incompatible monthly-rate and 24-week-change labels | C3: jama_berry_2025_oi_240158_1742927563.7361.pdf — Secondary Efficacy Outcomes, PDF p. 4; joi240158supp3_prod_1742927563.7911.pdf — eTable 3A, PDF p. 16 | D3: retain | E3: report_internal_inconsistency | F3: primary_done | G3: =IFERROR(IF(LEN(TRIM(CLEAN(SUBSTITUTE(Setup!$B$2,CHAR(160)," "))))=0,"CHECK REVIEWER ID",IF(OR(A3="",(COUNTIF('C_jama.2024.24764'!$A$2:$A$9,A3)+COUNTIF('C_jama.2024.27643'!$A$2:$A$9,A3)+COUNTIF('C_jama.2025.11178'!$A$2:$A$38,A3)+COUNTIF('C_jama.2025.15185'!$A$2:$A$13,A3)+COUNTIF('C_jama.2025.15440'!$A$2:$A$3,A3)+COUNTIF('C_jama.2025.16450'!$A$2:$A$11,A3)+COUNTIF('C_jama.2025.19563'!$A$2:$A$8,A3)+COUNTIF('C_jama.2025.19843'!$A$2:$A$2,A3)+COUNTIF('C_jama.2025.20765'!$A$2:$A$14,A3)+COUNTIF('C_jama.2025.24175'!$A$2:$A$15,A3)+COUNTIF('C_jama.2025.4390'!$A$2:$A$4,A3)+COUNTIF('C_jama.2025.7583'!$A$2:$A$4,A3)+COUNTIF('C_jama.2025.7710'!$A$2:$A$5,A3)+COUNTIF('C_jama.2025.9110'!$A$2:$A$7,A3)+COUNTIF('C_jama.2025.9663'!$A$2:$A$4,A3))<>1,COUNTIFS(Candidates!$G$2:$G$132,A3,Candidates!$K$2:$K$132,"jama.2024.27643")<>1),"CHECK KEY",IF(OR(AND(NOT(AND(D3="retain",E3="statistical_results")),H3<>"",H3<>"not_applicable"),AND(NOT(AND(D3="retain",E3="statistical_results")),I3<>"",I3<>"not_applicable"),AND(NOT(AND(D3="retain",E3="statistical_results")),J3<>"",J3<>"not_applicable"),AND(NOT(AND(D3="retain",OR(E3="report_internal_inconsistency",E3="plan_material"))),K3<>"",K3<>"not_applicable"),AND(NOT(AND(D3="retain",E3="protocol_report")),L3<>"",L3<>"not_applicable")),"CLEAR INACTIVE VALUES",IF(OR(NOT(OR(D3="retain",D3="exclude",D3="discuss")),NOT(OR(E3="statistical_results",E3="report_internal_inconsistency",E3="plan_material",E3="protocol_report")),AND(AND(D3="retain",E3="statistical_results"),NOT(OR(H3="confirmed_issue",H3="probable_issue",H3="not_issue",H3="indeterminate"))),AND(AND(D3="retain",E3="statistical_results"),NOT(OR(I3="substantive",I3="minor_presentation",I3="indeterminate"))),AND(AND(D3="retain",E3="statistical_results"),J3<>"",NOT(OR(J3="direct",J3="possible",J3="unlikely",J3="unknown"))),AND(AND(D3="retain",OR(E3="report_internal_inconsistency",E3="plan_material")),NOT(OR(K3="substantive_inconsistency",K3="minor_presentation",K3="non_inconsistency",K3="indeterminate"))),AND(AND(D3="retain",E3="protocol_report"),L3<>"",NOT(OR(L3="substantive_difference",L3="minor_presentation",L3="version_timing",L3="non_inconsistency",L3="indeterminate")))),"CHECK FIELDS",IF(AND(F3<>"",NOT(OR(F3="no",F3="primary_done"))),"CHECK COMPLETE",IF(F3="primary_done","PRIMARY READY","PRIMARY DRAFT")))))),"CHECK INPUT / KEY") -> PRIMARY READY | K3: substantive_inconsistency | R3: TEST 2025::jama.2024.27643::C002
A4: 2025::jama.2024.27643::C003 | B4: Shared-placebo ALSFRS-R credible-interval endpoints differ for the cited primary model | C4: jama_berry_2025_oi_240158_1742927563.7361.pdf — Primary Efficacy Outcome, PDF p. 4; joi240158supp3_prod_1742927563.7911.pdf — eTable 2, PDF p. 15 | D4: retain | E4: report_internal_inconsistency | F4: primary_done | G4: =IFERROR(IF(LEN(TRIM(CLEAN(SUBSTITUTE(Setup!$B$2,CHAR(160)," "))))=0,"CHECK REVIEWER ID",IF(OR(A4="",(COUNTIF('C_jama.2024.24764'!$A$2:$A$9,A4)+COUNTIF('C_jama.2024.27643'!$A$2:$A$9,A4)+COUNTIF('C_jama.2025.11178'!$A$2:$A$38,A4)+COUNTIF('C_jama.2025.15185'!$A$2:$A$13,A4)+COUNTIF('C_jama.2025.15440'!$A$2:$A$3,A4)+COUNTIF('C_jama.2025.16450'!$A$2:$A$11,A4)+COUNTIF('C_jama.2025.19563'!$A$2:$A$8,A4)+COUNTIF('C_jama.2025.19843'!$A$2:$A$2,A4)+COUNTIF('C_jama.2025.20765'!$A$2:$A$14,A4)+COUNTIF('C_jama.2025.24175'!$A$2:$A$15,A4)+COUNTIF('C_jama.2025.4390'!$A$2:$A$4,A4)+COUNTIF('C_jama.2025.7583'!$A$2:$A$4,A4)+COUNTIF('C_jama.2025.7710'!$A$2:$A$5,A4)+COUNTIF('C_jama.2025.9110'!$A$2:$A$7,A4)+COUNTIF('C_jama.2025.9663'!$A$2:$A$4,A4))<>1,COUNTIFS(Candidates!$G$2:$G$132,A4,Candidates!$K$2:$K$132,"jama.2024.27643")<>1),"CHECK KEY",IF(OR(AND(NOT(AND(D4="retain",E4="statistical_results")),H4<>"",H4<>"not_applicable"),AND(NOT(AND(D4="retain",E4="statistical_results")),I4<>"",I4<>"not_applicable"),AND(NOT(AND(D4="retain",E4="statistical_results")),J4<>"",J4<>"not_applicable"),AND(NOT(AND(D4="retain",OR(E4="report_internal_inconsistency",E4="plan_material"))),K4<>"",K4<>"not_applicable"),AND(NOT(AND(D4="retain",E4="protocol_report")),L4<>"",L4<>"not_applicable")),"CLEAR INACTIVE VALUES",IF(OR(NOT(OR(D4="retain",D4="exclude",D4="discuss")),NOT(OR(E4="statistical_results",E4="report_internal_inconsistency",E4="plan_material",E4="protocol_report")),AND(AND(D4="retain",E4="statistical_results"),NOT(OR(H4="confirmed_issue",H4="probable_issue",H4="not_issue",H4="indeterminate"))),AND(AND(D4="retain",E4="statistical_results"),NOT(OR(I4="substantive",I4="minor_presentation",I4="indeterminate"))),AND(AND(D4="retain",E4="statistical_results"),J4<>"",NOT(OR(J4="direct",J4="possible",J4="unlikely",J4="unknown"))),AND(AND(D4="retain",OR(E4="report_internal_inconsistency",E4="plan_material")),NOT(OR(K4="substantive_inconsistency",K4="minor_presentation",K4="non_inconsistency",K4="indeterminate"))),AND(AND(D4="retain",E4="protocol_report"),L4<>"",NOT(OR(L4="substantive_difference",L4="minor_presentation",L4="version_timing",L4="non_inconsistency",L4="indeterminate")))),"CHECK FIELDS",IF(AND(F4<>"",NOT(OR(F4="no",F4="primary_done"))),"CHECK COMPLETE",IF(F4="primary_done","PRIMARY READY","PRIMARY DRAFT")))))),"CHECK INPUT / KEY") -> PRIMARY READY | K4: substantive_inconsistency | R4: TEST 2025::jama.2024.27643::C003
A5: 2025::jama.2024.27643::C004 | B5: Pooled-active ALSFRS-R credible-interval endpoints differ for the cited primary model | C5: jama_berry_2025_oi_240158_1742927563.7361.pdf — Primary Efficacy Outcome, PDF p. 4; joi240158supp3_prod_1742927563.7911.pdf — eTable 2, PDF p. 15 | D5: retain | E5: report_internal_inconsistency | F5: primary_done | G5: =IFERROR(IF(LEN(TRIM(CLEAN(SUBSTITUTE(Setup!$B$2,CHAR(160)," "))))=0,"CHECK REVIEWER ID",IF(OR(A5="",(COUNTIF('C_jama.2024.24764'!$A$2:$A$9,A5)+COUNTIF('C_jama.2024.27643'!$A$2:$A$9,A5)+COUNTIF('C_jama.2025.11178'!$A$2:$A$38,A5)+COUNTIF('C_jama.2025.15185'!$A$2:$A$13,A5)+COUNTIF('C_jama.2025.15440'!$A$2:$A$3,A5)+COUNTIF('C_jama.2025.16450'!$A$2:$A$11,A5)+COUNTIF('C_jama.2025.19563'!$A$2:$A$8,A5)+COUNTIF('C_jama.2025.19843'!$A$2:$A$2,A5)+COUNTIF('C_jama.2025.20765'!$A$2:$A$14,A5)+COUNTIF('C_jama.2025.24175'!$A$2:$A$15,A5)+COUNTIF('C_jama.2025.4390'!$A$2:$A$4,A5)+COUNTIF('C_jama.2025.7583'!$A$2:$A$4,A5)+COUNTIF('C_jama.2025.7710'!$A$2:$A$5,A5)+COUNTIF('C_jama.2025.9110'!$A$2:$A$7,A5)+COUNTIF('C_jama.2025.9663'!$A$2:$A$4,A5))<>1,COUNTIFS(Candidates!$G$2:$G$132,A5,Candidates!$K$2:$K$132,"jama.2024.27643")<>1),"CHECK KEY",IF(OR(AND(NOT(AND(D5="retain",E5="statistical_results")),H5<>"",H5<>"not_applicable"),AND(NOT(AND(D5="retain",E5="statistical_results")),I5<>"",I5<>"not_applicable"),AND(NOT(AND(D5="retain",E5="statistical_results")),J5<>"",J5<>"not_applicable"),AND(NOT(AND(D5="retain",OR(E5="report_internal_inconsistency",E5="plan_material"))),K5<>"",K5<>"not_applicable"),AND(NOT(AND(D5="retain",E5="protocol_report")),L5<>"",L5<>"not_applicable")),"CLEAR INACTIVE VALUES",IF(OR(NOT(OR(D5="retain",D5="exclude",D5="discuss")),NOT(OR(E5="statistical_results",E5="report_internal_inconsistency",E5="plan_material",E5="protocol_report")),AND(AND(D5="retain",E5="statistical_results"),NOT(OR(H5="confirmed_issue",H5="probable_issue",H5="not_issue",H5="indeterminate"))),AND(AND(D5="retain",E5="statistical_results"),NOT(OR(I5="substantive",I5="minor_presentation",I5="indeterminate"))),AND(AND(D5="retain",E5="statistical_results"),J5<>"",NOT(OR(J5="direct",J5="possible",J5="unlikely",J5="unknown"))),AND(AND(D5="retain",OR(E5="report_internal_inconsistency",E5="plan_material")),NOT(OR(K5="substantive_inconsistency",K5="minor_presentation",K5="non_inconsistency",K5="indeterminate"))),AND(AND(D5="retain",E5="protocol_report"),L5<>"",NOT(OR(L5="substantive_difference",L5="minor_presentation",L5="version_timing",L5="non_inconsistency",L5="indeterminate")))),"CHECK FIELDS",IF(AND(F5<>"",NOT(OR(F5="no",F5="primary_done"))),"CHECK COMPLETE",IF(F5="primary_done","PRIMARY READY","PRIMARY DRAFT")))))),"CHECK INPUT / KEY") -> PRIMARY READY | K5: substantive_inconsistency | R5: TEST 2025::jama.2024.27643::C004
A6: 2025::jama.2024.27643::C005 | B6: Bayesian mortality event rates differ between article text and cited eTable 2 | C6: jama_berry_2025_oi_240158_1742927563.7361.pdf — Primary Efficacy Outcome, PDF p. 4; joi240158supp3_prod_1742927563.7911.pdf — eTable 2, PDF p. 15 | D6: retain | E6: report_internal_inconsistency | F6: primary_done | G6: =IFERROR(IF(LEN(TRIM(CLEAN(SUBSTITUTE(Setup!$B$2,CHAR(160)," "))))=0,"CHECK REVIEWER ID",IF(OR(A6="",(COUNTIF('C_jama.2024.24764'!$A$2:$A$9,A6)+COUNTIF('C_jama.2024.27643'!$A$2:$A$9,A6)+COUNTIF('C_jama.2025.11178'!$A$2:$A$38,A6)+COUNTIF('C_jama.2025.15185'!$A$2:$A$13,A6)+COUNTIF('C_jama.2025.15440'!$A$2:$A$3,A6)+COUNTIF('C_jama.2025.16450'!$A$2:$A$11,A6)+COUNTIF('C_jama.2025.19563'!$A$2:$A$8,A6)+COUNTIF('C_jama.2025.19843'!$A$2:$A$2,A6)+COUNTIF('C_jama.2025.20765'!$A$2:$A$14,A6)+COUNTIF('C_jama.2025.24175'!$A$2:$A$15,A6)+COUNTIF('C_jama.2025.4390'!$A$2:$A$4,A6)+COUNTIF('C_jama.2025.7583'!$A$2:$A$4,A6)+COUNTIF('C_jama.2025.7710'!$A$2:$A$5,A6)+COUNTIF('C_jama.2025.9110'!$A$2:$A$7,A6)+COUNTIF('C_jama.2025.9663'!$A$2:$A$4,A6))<>1,COUNTIFS(Candidates!$G$2:$G$132,A6,Candidates!$K$2:$K$132,"jama.2024.27643")<>1),"CHECK KEY",IF(OR(AND(NOT(AND(D6="retain",E6="statistical_results")),H6<>"",H6<>"not_applicable"),AND(NOT(AND(D6="retain",E6="statistical_results")),I6<>"",I6<>"not_applicable"),AND(NOT(AND(D6="retain",E6="statistical_results")),J6<>"",J6<>"not_applicable"),AND(NOT(AND(D6="retain",OR(E6="report_internal_inconsistency",E6="plan_material"))),K6<>"",K6<>"not_applicable"),AND(NOT(AND(D6="retain",E6="protocol_report")),L6<>"",L6<>"not_applicable")),"CLEAR INACTIVE VALUES",IF(OR(NOT(OR(D6="retain",D6="exclude",D6="discuss")),NOT(OR(E6="statistical_results",E6="report_internal_inconsistency",E6="plan_material",E6="protocol_report")),AND(AND(D6="retain",E6="statistical_results"),NOT(OR(H6="confirmed_issue",H6="probable_issue",H6="not_issue",H6="indeterminate"))),AND(AND(D6="retain",E6="statistical_results"),NOT(OR(I6="substantive",I6="minor_presentation",I6="indeterminate"))),AND(AND(D6="retain",E6="statistical_results"),J6<>"",NOT(OR(J6="direct",J6="possible",J6="unlikely",J6="unknown"))),AND(AND(D6="retain",OR(E6="report_internal_inconsistency",E6="plan_material")),NOT(OR(K6="substantive_inconsistency",K6="minor_presentation",K6="non_inconsistency",K6="indeterminate"))),AND(AND(D6="retain",E6="protocol_report"),L6<>"",NOT(OR(L6="substantive_difference",L6="minor_presentation",L6="version_timing",L6="non_inconsistency",L6="indeterminate")))),"CHECK FIELDS",IF(AND(F6<>"",NOT(OR(F6="no",F6="primary_done"))),"CHECK COMPLETE",IF(F6="primary_done","PRIMARY READY","PRIMARY DRAFT")))))),"CHECK INPUT / KEY") -> PRIMARY READY | K6: substantive_inconsistency | R6: TEST 2025::jama.2024.27643::C005
A7: 2025::jama.2024.27643::C006 | B7: Plasma NfL confidence intervals differ across Figure 3, narrative, and eTable 3B | C7: jama_berry_2025_oi_240158_1742927563.7361.pdf — Figure 3 and Biomarker Analyses, PDF p. 8; joi240158supp3_prod_1742927563.7911.pdf — eTable 3B, PDF p. 17 | D7: retain | E7: report_internal_inconsistency | F7: primary_done | G7: =IFERROR(IF(LEN(TRIM(CLEAN(SUBSTITUTE(Setup!$B$2,CHAR(160)," "))))=0,"CHECK REVIEWER ID",IF(OR(A7="",(COUNTIF('C_jama.2024.24764'!$A$2:$A$9,A7)+COUNTIF('C_jama.2024.27643'!$A$2:$A$9,A7)+COUNTIF('C_jama.2025.11178'!$A$2:$A$38,A7)+COUNTIF('C_jama.2025.15185'!$A$2:$A$13,A7)+COUNTIF('C_jama.2025.15440'!$A$2:$A$3,A7)+COUNTIF('C_jama.2025.16450'!$A$2:$A$11,A7)+COUNTIF('C_jama.2025.19563'!$A$2:$A$8,A7)+COUNTIF('C_jama.2025.19843'!$A$2:$A$2,A7)+COUNTIF('C_jama.2025.20765'!$A$2:$A$14,A7)+COUNTIF('C_jama.2025.24175'!$A$2:$A$15,A7)+COUNTIF('C_jama.2025.4390'!$A$2:$A$4,A7)+COUNTIF('C_jama.2025.7583'!$A$2:$A$4,A7)+COUNTIF('C_jama.2025.7710'!$A$2:$A$5,A7)+COUNTIF('C_jama.2025.9110'!$A$2:$A$7,A7)+COUNTIF('C_jama.2025.9663'!$A$2:$A$4,A7))<>1,COUNTIFS(Candidates!$G$2:$G$132,A7,Candidates!$K$2:$K$132,"jama.2024.27643")<>1),"CHECK KEY",IF(OR(AND(NOT(AND(D7="retain",E7="statistical_results")),H7<>"",H7<>"not_applicable"),AND(NOT(AND(D7="retain",E7="statistical_results")),I7<>"",I7<>"not_applicable"),AND(NOT(AND(D7="retain",E7="statistical_results")),J7<>"",J7<>"not_applicable"),AND(NOT(AND(D7="retain",OR(E7="report_internal_inconsistency",E7="plan_material"))),K7<>"",K7<>"not_applicable"),AND(NOT(AND(D7="retain",E7="protocol_report")),L7<>"",L7<>"not_applicable")),"CLEAR INACTIVE VALUES",IF(OR(NOT(OR(D7="retain",D7="exclude",D7="discuss")),NOT(OR(E7="statistical_results",E7="report_internal_inconsistency",E7="plan_material",E7="protocol_report")),AND(AND(D7="retain",E7="statistical_results"),NOT(OR(H7="confirmed_issue",H7="probable_issue",H7="not_issue",H7="indeterminate"))),AND(AND(D7="retain",E7="statistical_results"),NOT(OR(I7="substantive",I7="minor_presentation",I7="indeterminate"))),AND(AND(D7="retain",E7="statistical_results"),J7<>"",NOT(OR(J7="direct",J7="possible",J7="unlikely",J7="unknown"))),AND(AND(D7="retain",OR(E7="report_internal_inconsistency",E7="plan_material")),NOT(OR(K7="substantive_inconsistency",K7="minor_presentation",K7="non_inconsistency",K7="indeterminate"))),AND(AND(D7="retain",E7="protocol_report"),L7<>"",NOT(OR(L7="substantive_difference",L7="minor_presentation",L7="version_timing",L7="non_inconsistency",L7="indeterminate")))),"CHECK FIELDS",IF(AND(F7<>"",NOT(OR(F7="no",F7="primary_done"))),"CHECK COMPLETE",IF(F7="primary_done","PRIMARY READY","PRIMARY DRAFT")))))),"CHECK INPUT / KEY") -> PRIMARY READY | K7: substantive_inconsistency | R7: TEST 2025::jama.2024.27643::C006
A8: 2025::jama.2024.27643::C007 | B8: Serum NfL regimen-only values and contrast differ across displays | C8: jama_berry_2025_oi_240158_1742927563.7361.pdf — Figure 3 and Biomarker Analyses, PDF p. 8; joi240158supp3_prod_1742927563.7911.pdf — eTable 3B, PDF p. 17 | D8: retain | E8: report_internal_inconsistency | F8: primary_done | G8: =IFERROR(IF(LEN(TRIM(CLEAN(SUBSTITUTE(Setup!$B$2,CHAR(160)," "))))=0,"CHECK REVIEWER ID",IF(OR(A8="",(COUNTIF('C_jama.2024.24764'!$A$2:$A$9,A8)+COUNTIF('C_jama.2024.27643'!$A$2:$A$9,A8)+COUNTIF('C_jama.2025.11178'!$A$2:$A$38,A8)+COUNTIF('C_jama.2025.15185'!$A$2:$A$13,A8)+COUNTIF('C_jama.2025.15440'!$A$2:$A$3,A8)+COUNTIF('C_jama.2025.16450'!$A$2:$A$11,A8)+COUNTIF('C_jama.2025.19563'!$A$2:$A$8,A8)+COUNTIF('C_jama.2025.19843'!$A$2:$A$2,A8)+COUNTIF('C_jama.2025.20765'!$A$2:$A$14,A8)+COUNTIF('C_jama.2025.24175'!$A$2:$A$15,A8)+COUNTIF('C_jama.2025.4390'!$A$2:$A$4,A8)+COUNTIF('C_jama.2025.7583'!$A$2:$A$4,A8)+COUNTIF('C_jama.2025.7710'!$A$2:$A$5,A8)+COUNTIF('C_jama.2025.9110'!$A$2:$A$7,A8)+COUNTIF('C_jama.2025.9663'!$A$2:$A$4,A8))<>1,COUNTIFS(Candidates!$G$2:$G$132,A8,Candidates!$K$2:$K$132,"jama.2024.27643")<>1),"CHECK KEY",IF(OR(AND(NOT(AND(D8="retain",E8="statistical_results")),H8<>"",H8<>"not_applicable"),AND(NOT(AND(D8="retain",E8="statistical_results")),I8<>"",I8<>"not_applicable"),AND(NOT(AND(D8="retain",E8="statistical_results")),J8<>"",J8<>"not_applicable"),AND(NOT(AND(D8="retain",OR(E8="report_internal_inconsistency",E8="plan_material"))),K8<>"",K8<>"not_applicable"),AND(NOT(AND(D8="retain",E8="protocol_report")),L8<>"",L8<>"not_applicable")),"CLEAR INACTIVE VALUES",IF(OR(NOT(OR(D8="retain",D8="exclude",D8="discuss")),NOT(OR(E8="statistical_results",E8="report_internal_inconsistency",E8="plan_material",E8="protocol_report")),AND(AND(D8="retain",E8="statistical_results"),NOT(OR(H8="confirmed_issue",H8="probable_issue",H8="not_issue",H8="indeterminate"))),AND(AND(D8="retain",E8="statistical_results"),NOT(OR(I8="substantive",I8="minor_presentation",I8="indeterminate"))),AND(AND(D8="retain",E8="statistical_results"),J8<>"",NOT(OR(J8="direct",J8="possible",J8="unlikely",J8="unknown"))),AND(AND(D8="retain",OR(E8="report_internal_inconsistency",E8="plan_material")),NOT(OR(K8="substantive_inconsistency",K8="minor_presentation",K8="non_inconsistency",K8="indeterminate"))),AND(AND(D8="retain",E8="protocol_report"),L8<>"",NOT(OR(L8="substantive_difference",L8="minor_presentation",L8="version_timing",L8="non_inconsistency",L8="indeterminate")))),"CHECK FIELDS",IF(AND(F8<>"",NOT(OR(F8="no",F8="primary_done"))),"CHECK COMPLETE",IF(F8="primary_done","PRIMARY READY","PRIMARY DRAFT")))))),"CHECK INPUT / KEY") -> PRIMARY READY | K8: substantive_inconsistency | R8: TEST 2025::jama.2024.27643::C007
A9: 2025::jama.2024.27643::C008 | B9: Discussion total of 13 events conflicts with the 14 events displayed in Table 2 | C9: jama_berry_2025_oi_240158_1742927563.7361.pdf — Table 2, PDF p. 7; jama_berry_2025_oi_240158_1742927563.7361.pdf — Discussion, PDF p. 9 | D9: retain | E9: statistical_results | F9: primary_done | G9: =IFERROR(IF(LEN(TRIM(CLEAN(SUBSTITUTE(Setup!$B$2,CHAR(160)," "))))=0,"CHECK REVIEWER ID",IF(OR(A9="",(COUNTIF('C_jama.2024.24764'!$A$2:$A$9,A9)+COUNTIF('C_jama.2024.27643'!$A$2:$A$9,A9)+COUNTIF('C_jama.2025.11178'!$A$2:$A$38,A9)+COUNTIF('C_jama.2025.15185'!$A$2:$A$13,A9)+COUNTIF('C_jama.2025.15440'!$A$2:$A$3,A9)+COUNTIF('C_jama.2025.16450'!$A$2:$A$11,A9)+COUNTIF('C_jama.2025.19563'!$A$2:$A$8,A9)+COUNTIF('C_jama.2025.19843'!$A$2:$A$2,A9)+COUNTIF('C_jama.2025.20765'!$A$2:$A$14,A9)+COUNTIF('C_jama.2025.24175'!$A$2:$A$15,A9)+COUNTIF('C_jama.2025.4390'!$A$2:$A$4,A9)+COUNTIF('C_jama.2025.7583'!$A$2:$A$4,A9)+COUNTIF('C_jama.2025.7710'!$A$2:$A$5,A9)+COUNTIF('C_jama.2025.9110'!$A$2:$A$7,A9)+COUNTIF('C_jama.2025.9663'!$A$2:$A$4,A9))<>1,COUNTIFS(Candidates!$G$2:$G$132,A9,Candidates!$K$2:$K$132,"jama.2024.27643")<>1),"CHECK KEY",IF(OR(AND(NOT(AND(D9="retain",E9="statistical_results")),H9<>"",H9<>"not_applicable"),AND(NOT(AND(D9="retain",E9="statistical_results")),I9<>"",I9<>"not_applicable"),AND(NOT(AND(D9="retain",E9="statistical_results")),J9<>"",J9<>"not_applicable"),AND(NOT(AND(D9="retain",OR(E9="report_internal_inconsistency",E9="plan_material"))),K9<>"",K9<>"not_applicable"),AND(NOT(AND(D9="retain",E9="protocol_report")),L9<>"",L9<>"not_applicable")),"CLEAR INACTIVE VALUES",IF(OR(NOT(OR(D9="retain",D9="exclude",D9="discuss")),NOT(OR(E9="statistical_results",E9="report_internal_inconsistency",E9="plan_material",E9="protocol_report")),AND(AND(D9="retain",E9="statistical_results"),NOT(OR(H9="confirmed_issue",H9="probable_issue",H9="not_issue",H9="indeterminate"))),AND(AND(D9="retain",E9="statistical_results"),NOT(OR(I9="substantive",I9="minor_presentation",I9="indeterminate"))),AND(AND(D9="retain",E9="statistical_results"),J9<>"",NOT(OR(J9="direct",J9="possible",J9="unlikely",J9="unknown"))),AND(AND(D9="retain",OR(E9="report_internal_inconsistency",E9="plan_material")),NOT(OR(K9="substantive_inconsistency",K9="minor_presentation",K9="non_inconsistency",K9="indeterminate"))),AND(AND(D9="retain",E9="protocol_report"),L9<>"",NOT(OR(L9="substantive_difference",L9="minor_presentation",L9="version_timing",L9="non_inconsistency",L9="indeterminate")))),"CHECK FIELDS",IF(AND(F9<>"",NOT(OR(F9="no",F9="primary_done"))),"CHECK COMPLETE",IF(F9="primary_done","PRIMARY READY","PRIMARY DRAFT")))))),"CHECK INPUT / KEY") -> PRIMARY READY | H9: confirmed_issue | I9: substantive | R9: TEST 2025::jama.2024.27643::C008

Sheet C_jama.2025.11178
A1: Candidate key | B1: Candidate title | C1: Source location | D1: Disposition | E1: Review domain (AI suggestion; editable) | F1: Complete | G1: Validation hint | H1: Statistcal_or_numerical issue | I1: Substantiveness | J1: Downstream impact | K1: Report-internal or planning-material inconsistency | L1: Protocol interpretation | R1: Notes (optional)
A2: 2025::jama.2025.11178::C001 | B2: Conditional Figure 1 further-ineligibility component subtotal gap | C2: main article — PDF p. 5, Figure 1, “4481 Ineligible.” | D2: retain | E2: statistical_results | F2: primary_done | G2: =IFERROR(IF(LEN(TRIM(CLEAN(SUBSTITUTE(Setup!$B$2,CHAR(160)," "))))=0,"CHECK REVIEWER ID",IF(OR(A2="",(COUNTIF('C_jama.2024.24764'!$A$2:$A$9,A2)+COUNTIF('C_jama.2024.27643'!$A$2:$A$9,A2)+COUNTIF('C_jama.2025.11178'!$A$2:$A$38,A2)+COUNTIF('C_jama.2025.15185'!$A$2:$A$13,A2)+COUNTIF('C_jama.2025.15440'!$A$2:$A$3,A2)+COUNTIF('C_jama.2025.16450'!$A$2:$A$11,A2)+COUNTIF('C_jama.2025.19563'!$A$2:$A$8,A2)+COUNTIF('C_jama.2025.19843'!$A$2:$A$2,A2)+COUNTIF('C_jama.2025.20765'!$A$2:$A$14,A2)+COUNTIF('C_jama.2025.24175'!$A$2:$A$15,A2)+COUNTIF('C_jama.2025.4390'!$A$2:$A$4,A2)+COUNTIF('C_jama.2025.7583'!$A$2:$A$4,A2)+COUNTIF('C_jama.2025.7710'!$A$2:$A$5,A2)+COUNTIF('C_jama.2025.9110'!$A$2:$A$7,A2)+COUNTIF('C_jama.2025.9663'!$A$2:$A$4,A2))<>1,COUNTIFS(Candidates!$G$2:$G$132,A2,Candidates!$K$2:$K$132,"jama.2025.11178")<>1),"CHECK KEY",IF(OR(AND(NOT(AND(D2="retain",E2="statistical_results")),H2<>"",H2<>"not_applicable"),AND(NOT(AND(D2="retain",E2="statistical_results")),I2<>"",I2<>"not_applicable"),AND(NOT(AND(D2="retain",E2="statistical_results")),J2<>"",J2<>"not_applicable"),AND(NOT(AND(D2="retain",OR(E2="report_internal_inconsistency",E2="plan_material"))),K2<>"",K2<>"not_applicable"),AND(NOT(AND(D2="retain",E2="protocol_report")),L2<>"",L2<>"not_applicable")),"CLEAR INACTIVE VALUES",IF(OR(NOT(OR(D2="retain",D2="exclude",D2="discuss")),NOT(OR(E2="statistical_results",E2="report_internal_inconsistency",E2="plan_material",E2="protocol_report")),AND(AND(D2="retain",E2="statistical_results"),NOT(OR(H2="confirmed_issue",H2="probable_issue",H2="not_issue",H2="indeterminate"))),AND(AND(D2="retain",E2="statistical_results"),NOT(OR(I2="substantive",I2="minor_presentation",I2="indeterminate"))),AND(AND(D2="retain",E2="statistical_results"),J2<>"",NOT(OR(J2="direct",J2="possible",J2="unlikely",J2="unknown"))),AND(AND(D2="retain",OR(E2="report_internal_inconsistency",E2="plan_material")),NOT(OR(K2="substantive_inconsistency",K2="minor_presentation",K2="non_inconsistency",K2="indeterminate"))),AND(AND(D2="retain",E2="protocol_report"),L2<>"",NOT(OR(L2="substantive_difference",L2="minor_presentation",L2="version_timing",L2="non_inconsistency",L2="indeterminate")))),"CHECK FIELDS",IF(AND(F2<>"",NOT(OR(F2="no",F2="primary_done"))),"CHECK COMPLETE",IF(F2="primary_done","PRIMARY READY","PRIMARY DRAFT")))))),"CHECK INPUT / KEY") -> PRIMARY READY | H2: confirmed_issue | I2: substantive | R2: TEST 2025::jama.2025.11178::C001
A3: 2025::jama.2025.11178::C002 | B3: Overall eTable 1 follow-up-pattern partition | C3: results supplement — PDF p. 7, eTable 1, Overall column. | D3: retain | E3: statistical_results | F3: primary_done | G3: =IFERROR(IF(LEN(TRIM(CLEAN(SUBSTITUTE(Setup!$B$2,CHAR(160)," "))))=0,"CHECK REVIEWER ID",IF(OR(A3="",(COUNTIF('C_jama.2024.24764'!$A$2:$A$9,A3)+COUNTIF('C_jama.2024.27643'!$A$2:$A$9,A3)+COUNTIF('C_jama.2025.11178'!$A$2:$A$38,A3)+COUNTIF('C_jama.2025.15185'!$A$2:$A$13,A3)+COUNTIF('C_jama.2025.15440'!$A$2:$A$3,A3)+COUNTIF('C_jama.2025.16450'!$A$2:$A$11,A3)+COUNTIF('C_jama.2025.19563'!$A$2:$A$8,A3)+COUNTIF('C_jama.2025.19843'!$A$2:$A$2,A3)+COUNTIF('C_jama.2025.20765'!$A$2:$A$14,A3)+COUNTIF('C_jama.2025.24175'!$A$2:$A$15,A3)+COUNTIF('C_jama.2025.4390'!$A$2:$A$4,A3)+COUNTIF('C_jama.2025.7583'!$A$2:$A$4,A3)+COUNTIF('C_jama.2025.7710'!$A$2:$A$5,A3)+COUNTIF('C_jama.2025.9110'!$A$2:$A$7,A3)+COUNTIF('C_jama.2025.9663'!$A$2:$A$4,A3))<>1,COUNTIFS(Candidates!$G$2:$G$132,A3,Candidates!$K$2:$K$132,"jama.2025.11178")<>1),"CHECK KEY",IF(OR(AND(NOT(AND(D3="retain",E3="statistical_results")),H3<>"",H3<>"not_applicable"),AND(NOT(AND(D3="retain",E3="statistical_results")),I3<>"",I3<>"not_applicable"),AND(NOT(AND(D3="retain",E3="statistical_results")),J3<>"",J3<>"not_applicable"),AND(NOT(AND(D3="retain",OR(E3="report_internal_inconsistency",E3="plan_material"))),K3<>"",K3<>"not_applicable"),AND(NOT(AND(D3="retain",E3="protocol_report")),L3<>"",L3<>"not_applicable")),"CLEAR INACTIVE VALUES",IF(OR(NOT(OR(D3="retain",D3="exclude",D3="discuss")),NOT(OR(E3="statistical_results",E3="report_internal_inconsistency",E3="plan_material",E3="protocol_report")),AND(AND(D3="retain",E3="statistical_results"),NOT(OR(H3="confirmed_issue",H3="probable_issue",H3="not_issue",H3="indeterminate"))),AND(AND(D3="retain",E3="statistical_results"),NOT(OR(I3="substantive",I3="minor_presentation",I3="indeterminate"))),AND(AND(D3="retain",E3="statistical_results"),J3<>"",NOT(OR(J3="direct",J3="possible",J3="unlikely",J3="unknown"))),AND(AND(D3="retain",OR(E3="report_internal_inconsistency",E3="plan_material")),NOT(OR(K3="substantive_inconsistency",K3="minor_presentation",K3="non_inconsistency",K3="indeterminate"))),AND(AND(D3="retain",E3="protocol_report"),L3<>"",NOT(OR(L3="substantive_difference",L3="minor_presentation",L3="version_timing",L3="non_inconsistency",L3="indeterminate")))),"CHECK FIELDS",IF(AND(F3<>"",NOT(OR(F3="no",F3="primary_done"))),"CHECK COMPLETE",IF(F3="primary_done","PRIMARY READY","PRIMARY DRAFT")))))),"CHECK INPUT / KEY") -> PRIMARY READY | H3: confirmed_issue | I3: substantive | R3: TEST 2025::jama.2025.11178::C002
A4: 2025::jama.2025.11178::C003 | B4: painTRAINER eTable 1 follow-up-pattern partition | C4: results supplement — PDF p. 7, eTable 1, painTRAINER column. | D4: retain | E4: statistical_results | F4: primary_done | G4: =IFERROR(IF(LEN(TRIM(CLEAN(SUBSTITUTE(Setup!$B$2,CHAR(160)," "))))=0,"CHECK REVIEWER ID",IF(OR(A4="",(COUNTIF('C_jama.2024.24764'!$A$2:$A$9,A4)+COUNTIF('C_jama.2024.27643'!$A$2:$A$9,A4)+COUNTIF('C_jama.2025.11178'!$A$2:$A$38,A4)+COUNTIF('C_jama.2025.15185'!$A$2:$A$13,A4)+COUNTIF('C_jama.2025.15440'!$A$2:$A$3,A4)+COUNTIF('C_jama.2025.16450'!$A$2:$A$11,A4)+COUNTIF('C_jama.2025.19563'!$A$2:$A$8,A4)+COUNTIF('C_jama.2025.19843'!$A$2:$A$2,A4)+COUNTIF('C_jama.2025.20765'!$A$2:$A$14,A4)+COUNTIF('C_jama.2025.24175'!$A$2:$A$15,A4)+COUNTIF('C_jama.2025.4390'!$A$2:$A$4,A4)+COUNTIF('C_jama.2025.7583'!$A$2:$A$4,A4)+COUNTIF('C_jama.2025.7710'!$A$2:$A$5,A4)+COUNTIF('C_jama.2025.9110'!$A$2:$A$7,A4)+COUNTIF('C_jama.2025.9663'!$A$2:$A$4,A4))<>1,COUNTIFS(Candidates!$G$2:$G$132,A4,Candidates!$K$2:$K$132,"jama.2025.11178")<>1),"CHECK KEY",IF(OR(AND(NOT(AND(D4="retain",E4="statistical_results")),H4<>"",H4<>"not_applicable"),AND(NOT(AND(D4="retain",E4="statistical_results")),I4<>"",I4<>"not_applicable"),AND(NOT(AND(D4="retain",E4="statistical_results")),J4<>"",J4<>"not_applicable"),AND(NOT(AND(D4="retain",OR(E4="report_internal_inconsistency",E4="plan_material"))),K4<>"",K4<>"not_applicable"),AND(NOT(AND(D4="retain",E4="protocol_report")),L4<>"",L4<>"not_applicable")),"CLEAR INACTIVE VALUES",IF(OR(NOT(OR(D4="retain",D4="exclude",D4="discuss")),NOT(OR(E4="statistical_results",E4="report_internal_inconsistency",E4="plan_material",E4="protocol_report")),AND(AND(D4="retain",E4="statistical_results"),NOT(OR(H4="confirmed_issue",H4="probable_issue",H4="not_issue",H4="indeterminate"))),AND(AND(D4="retain",E4="statistical_results"),NOT(OR(I4="substantive",I4="minor_presentation",I4="indeterminate"))),AND(AND(D4="retain",E4="statistical_results"),J4<>"",NOT(OR(J4="direct",J4="possible",J4="unlikely",J4="unknown"))),AND(AND(D4="retain",OR(E4="report_internal_inconsistency",E4="plan_material")),NOT(OR(K4="substantive_inconsistency",K4="minor_presentation",K4="non_inconsistency",K4="indeterminate"))),AND(AND(D4="retain",E4="protocol_report"),L4<>"",NOT(OR(L4="substantive_difference",L4="minor_presentation",L4="version_timing",L4="non_inconsistency",L4="indeterminate")))),"CHECK FIELDS",IF(AND(F4<>"",NOT(OR(F4="no",F4="primary_done"))),"CHECK COMPLETE",IF(F4="primary_done","PRIMARY READY","PRIMARY DRAFT")))))),"CHECK INPUT / KEY") -> PRIMARY READY | H4: confirmed_issue | I4: substantive | R4: TEST 2025::jama.2025.11178::C003
A5: 2025::jama.2025.11178::C004 | B5: Health Coach eTable 1 follow-up-pattern partition | C5: results supplement — PDF p. 7, eTable 1, Health Coach column. | D5: retain | E5: statistical_results | F5: primary_done | G5: =IFERROR(IF(LEN(TRIM(CLEAN(SUBSTITUTE(Setup!$B$2,CHAR(160)," "))))=0,"CHECK REVIEWER ID",IF(OR(A5="",(COUNTIF('C_jama.2024.24764'!$A$2:$A$9,A5)+COUNTIF('C_jama.2024.27643'!$A$2:$A$9,A5)+COUNTIF('C_jama.2025.11178'!$A$2:$A$38,A5)+COUNTIF('C_jama.2025.15185'!$A$2:$A$13,A5)+COUNTIF('C_jama.2025.15440'!$A$2:$A$3,A5)+COUNTIF('C_jama.2025.16450'!$A$2:$A$11,A5)+COUNTIF('C_jama.2025.19563'!$A$2:$A$8,A5)+COUNTIF('C_jama.2025.19843'!$A$2:$A$2,A5)+COUNTIF('C_jama.2025.20765'!$A$2:$A$14,A5)+COUNTIF('C_jama.2025.24175'!$A$2:$A$15,A5)+COUNTIF('C_jama.2025.4390'!$A$2:$A$4,A5)+COUNTIF('C_jama.2025.7583'!$A$2:$A$4,A5)+COUNTIF('C_jama.2025.7710'!$A$2:$A$5,A5)+COUNTIF('C_jama.2025.9110'!$A$2:$A$7,A5)+COUNTIF('C_jama.2025.9663'!$A$2:$A$4,A5))<>1,COUNTIFS(Candidates!$G$2:$G$132,A5,Candidates!$K$2:$K$132,"jama.2025.11178")<>1),"CHECK KEY",IF(OR(AND(NOT(AND(D5="retain",E5="statistical_results")),H5<>"",H5<>"not_applicable"),AND(NOT(AND(D5="retain",E5="statistical_results")),I5<>"",I5<>"not_applicable"),AND(NOT(AND(D5="retain",E5="statistical_results")),J5<>"",J5<>"not_applicable"),AND(NOT(AND(D5="retain",OR(E5="report_internal_inconsistency",E5="plan_material"))),K5<>"",K5<>"not_applicable"),AND(NOT(AND(D5="retain",E5="protocol_report")),L5<>"",L5<>"not_applicable")),"CLEAR INACTIVE VALUES",IF(OR(NOT(OR(D5="retain",D5="exclude",D5="discuss")),NOT(OR(E5="statistical_results",E5="report_internal_inconsistency",E5="plan_material",E5="protocol_report")),AND(AND(D5="retain",E5="statistical_results"),NOT(OR(H5="confirmed_issue",H5="probable_issue",H5="not_issue",H5="indeterminate"))),AND(AND(D5="retain",E5="statistical_results"),NOT(OR(I5="substantive",I5="minor_presentation",I5="indeterminate"))),AND(AND(D5="retain",E5="statistical_results"),J5<>"",NOT(OR(J5="direct",J5="possible",J5="unlikely",J5="unknown"))),AND(AND(D5="retain",OR(E5="report_internal_inconsistency",E5="plan_material")),NOT(OR(K5="substantive_inconsistency",K5="minor_presentation",K5="non_inconsistency",K5="indeterminate"))),AND(AND(D5="retain",E5="protocol_report"),L5<>"",NOT(OR(L5="substantive_difference",L5="minor_presentation",L5="version_timing",L5="non_inconsistency",L5="indeterminate")))),"CHECK FIELDS",IF(AND(F5<>"",NOT(OR(F5="no",F5="primary_done"))),"CHECK COMPLETE",IF(F5="primary_done","PRIMARY READY","PRIMARY DRAFT")))))),"CHECK INPUT / KEY") -> PRIMARY READY | H5: confirmed_issue | I5: substantive | R5: TEST 2025::jama.2025.11178::C004
A6: 2025::jama.2025.11178::C005 | B6: Workbook current-depression percentage incompatible with its count | C6: workbook, worksheet eTable 3, cells A82:E83 and E2:E3. | D6: retain | E6: statistical_results | F6: primary_done | G6: =IFERROR(IF(LEN(TRIM(CLEAN(SUBSTITUTE(Setup!$B$2,CHAR(160)," "))))=0,"CHECK REVIEWER ID",IF(OR(A6="",(COUNTIF('C_jama.2024.24764'!$A$2:$A$9,A6)+COUNTIF('C_jama.2024.27643'!$A$2:$A$9,A6)+COUNTIF('C_jama.2025.11178'!$A$2:$A$38,A6)+COUNTIF('C_jama.2025.15185'!$A$2:$A$13,A6)+COUNTIF('C_jama.2025.15440'!$A$2:$A$3,A6)+COUNTIF('C_jama.2025.16450'!$A$2:$A$11,A6)+COUNTIF('C_jama.2025.19563'!$A$2:$A$8,A6)+COUNTIF('C_jama.2025.19843'!$A$2:$A$2,A6)+COUNTIF('C_jama.2025.20765'!$A$2:$A$14,A6)+COUNTIF('C_jama.2025.24175'!$A$2:$A$15,A6)+COUNTIF('C_jama.2025.4390'!$A$2:$A$4,A6)+COUNTIF('C_jama.2025.7583'!$A$2:$A$4,A6)+COUNTIF('C_jama.2025.7710'!$A$2:$A$5,A6)+COUNTIF('C_jama.2025.9110'!$A$2:$A$7,A6)+COUNTIF('C_jama.2025.9663'!$A$2:$A$4,A6))<>1,COUNTIFS(Candidates!$G$2:$G$132,A6,Candidates!$K$2:$K$132,"jama.2025.11178")<>1),"CHECK KEY",IF(OR(AND(NOT(AND(D6="retain",E6="statistical_results")),H6<>"",H6<>"not_applicable"),AND(NOT(AND(D6="retain",E6="statistical_results")),I6<>"",I6<>"not_applicable"),AND(NOT(AND(D6="retain",E6="statistical_results")),J6<>"",J6<>"not_applicable"),AND(NOT(AND(D6="retain",OR(E6="report_internal_inconsistency",E6="plan_material"))),K6<>"",K6<>"not_applicable"),AND(NOT(AND(D6="retain",E6="protocol_report")),L6<>"",L6<>"not_applicable")),"CLEAR INACTIVE VALUES",IF(OR(NOT(OR(D6="retain",D6="exclude",D6="discuss")),NOT(OR(E6="statistical_results",E6="report_internal_inconsistency",E6="plan_material",E6="protocol_report")),AND(AND(D6="retain",E6="statistical_results"),NOT(OR(H6="confirmed_issue",H6="probable_issue",H6="not_issue",H6="indeterminate"))),AND(AND(D6="retain",E6="statistical_results"),NOT(OR(I6="substantive",I6="minor_presentation",I6="indeterminate"))),AND(AND(D6="retain",E6="statistical_results"),J6<>"",NOT(OR(J6="direct",J6="possible",J6="unlikely",J6="unknown"))),AND(AND(D6="retain",OR(E6="report_internal_inconsistency",E6="plan_material")),NOT(OR(K6="substantive_inconsistency",K6="minor_presentation",K6="non_inconsistency",K6="indeterminate"))),AND(AND(D6="retain",E6="protocol_report"),L6<>"",NOT(OR(L6="substantive_difference",L6="minor_presentation",L6="version_timing",L6="non_inconsistency",L6="indeterminate")))),"CHECK FIELDS",IF(AND(F6<>"",NOT(OR(F6="no",F6="primary_done"))),"CHECK COMPLETE",IF(F6="primary_done","PRIMARY READY","PRIMARY DRAFT")))))),"CHECK INPUT / KEY") -> PRIMARY READY | H6: confirmed_issue | I6: substantive | R6: TEST 2025::jama.2025.11178::C005
A7: 2025::jama.2025.11178::C006 | B7: Workbook social-role cutoff labeled as mean (SD) | C7: workbook, worksheet eTable 3, cells A103:E104. | D7: retain | E7: report_internal_inconsistency | F7: primary_done | G7: =IFERROR(IF(LEN(TRIM(CLEAN(SUBSTITUTE(Setup!$B$2,CHAR(160)," "))))=0,"CHECK REVIEWER ID",IF(OR(A7="",(COUNTIF('C_jama.2024.24764'!$A$2:$A$9,A7)+COUNTIF('C_jama.2024.27643'!$A$2:$A$9,A7)+COUNTIF('C_jama.2025.11178'!$A$2:$A$38,A7)+COUNTIF('C_jama.2025.15185'!$A$2:$A$13,A7)+COUNTIF('C_jama.2025.15440'!$A$2:$A$3,A7)+COUNTIF('C_jama.2025.16450'!$A$2:$A$11,A7)+COUNTIF('C_jama.2025.19563'!$A$2:$A$8,A7)+COUNTIF('C_jama.2025.19843'!$A$2:$A$2,A7)+COUNTIF('C_jama.2025.20765'!$A$2:$A$14,A7)+COUNTIF('C_jama.2025.24175'!$A$2:$A$15,A7)+COUNTIF('C_jama.2025.4390'!$A$2:$A$4,A7)+COUNTIF('C_jama.2025.7583'!$A$2:$A$4,A7)+COUNTIF('C_jama.2025.7710'!$A$2:$A$5,A7)+COUNTIF('C_jama.2025.9110'!$A$2:$A$7,A7)+COUNTIF('C_jama.2025.9663'!$A$2:$A$4,A7))<>1,COUNTIFS(Candidates!$G$2:$G$132,A7,Candidates!$K$2:$K$132,"jama.2025.11178")<>1),"CHECK KEY",IF(OR(AND(NOT(AND(D7="retain",E7="statistical_results")),H7<>"",H7<>"not_applicable"),AND(NOT(AND(D7="retain",E7="statistical_results")),I7<>"",I7<>"not_applicable"),AND(NOT(AND(D7="retain",E7="statistical_results")),J7<>"",J7<>"not_applicable"),AND(NOT(AND(D7="retain",OR(E7="report_internal_inconsistency",E7="plan_material"))),K7<>"",K7<>"not_applicable"),AND(NOT(AND(D7="retain",E7="protocol_report")),L7<>"",L7<>"not_applicable")),"CLEAR INACTIVE VALUES",IF(OR(NOT(OR(D7="retain",D7="exclude",D7="discuss")),NOT(OR(E7="statistical_results",E7="report_internal_inconsistency",E7="plan_material",E7="protocol_report")),AND(AND(D7="retain",E7="statistical_results"),NOT(OR(H7="confirmed_issue",H7="probable_issue",H7="not_issue",H7="indeterminate"))),AND(AND(D7="retain",E7="statistical_results"),NOT(OR(I7="substantive",I7="minor_presentation",I7="indeterminate"))),AND(AND(D7="retain",E7="statistical_results"),J7<>"",NOT(OR(J7="direct",J7="possible",J7="unlikely",J7="unknown"))),AND(AND(D7="retain",OR(E7="report_internal_inconsistency",E7="plan_material")),NOT(OR(K7="substantive_inconsistency",K7="minor_presentation",K7="non_inconsistency",K7="indeterminate"))),AND(AND(D7="retain",E7="protocol_report"),L7<>"",NOT(OR(L7="substantive_difference",L7="minor_presentation",L7="version_timing",L7="non_inconsistency",L7="indeterminate")))),"CHECK FIELDS",IF(AND(F7<>"",NOT(OR(F7="no",F7="primary_done"))),"CHECK COMPLETE",IF(F7="primary_done","PRIMARY READY","PRIMARY DRAFT")))))),"CHECK INPUT / KEY") -> PRIMARY READY | K7: substantive_inconsistency | R7: TEST 2025::jama.2025.11178::C006
A8: 2025::jama.2025.11178::C007 | B8: Workbook physical-function cutoff labeled as mean (SD) | C8: workbook, worksheet eTable 3, cells A106:E107. | D8: retain | E8: report_internal_inconsistency | F8: primary_done | G8: =IFERROR(IF(LEN(TRIM(CLEAN(SUBSTITUTE(Setup!$B$2,CHAR(160)," "))))=0,"CHECK REVIEWER ID",IF(OR(A8="",(COUNTIF('C_jama.2024.24764'!$A$2:$A$9,A8)+COUNTIF('C_jama.2024.27643'!$A$2:$A$9,A8)+COUNTIF('C_jama.2025.11178'!$A$2:$A$38,A8)+COUNTIF('C_jama.2025.15185'!$A$2:$A$13,A8)+COUNTIF('C_jama.2025.15440'!$A$2:$A$3,A8)+COUNTIF('C_jama.2025.16450'!$A$2:$A$11,A8)+COUNTIF('C_jama.2025.19563'!$A$2:$A$8,A8)+COUNTIF('C_jama.2025.19843'!$A$2:$A$2,A8)+COUNTIF('C_jama.2025.20765'!$A$2:$A$14,A8)+COUNTIF('C_jama.2025.24175'!$A$2:$A$15,A8)+COUNTIF('C_jama.2025.4390'!$A$2:$A$4,A8)+COUNTIF('C_jama.2025.7583'!$A$2:$A$4,A8)+COUNTIF('C_jama.2025.7710'!$A$2:$A$5,A8)+COUNTIF('C_jama.2025.9110'!$A$2:$A$7,A8)+COUNTIF('C_jama.2025.9663'!$A$2:$A$4,A8))<>1,COUNTIFS(Candidates!$G$2:$G$132,A8,Candidates!$K$2:$K$132,"jama.2025.11178")<>1),"CHECK KEY",IF(OR(AND(NOT(AND(D8="retain",E8="statistical_results")),H8<>"",H8<>"not_applicable"),AND(NOT(AND(D8="retain",E8="statistical_results")),I8<>"",I8<>"not_applicable"),AND(NOT(AND(D8="retain",E8="statistical_results")),J8<>"",J8<>"not_applicable"),AND(NOT(AND(D8="retain",OR(E8="report_internal_inconsistency",E8="plan_material"))),K8<>"",K8<>"not_applicable"),AND(NOT(AND(D8="retain",E8="protocol_report")),L8<>"",L8<>"not_applicable")),"CLEAR INACTIVE VALUES",IF(OR(NOT(OR(D8="retain",D8="exclude",D8="discuss")),NOT(OR(E8="statistical_results",E8="report_internal_inconsistency",E8="plan_material",E8="protocol_report")),AND(AND(D8="retain",E8="statistical_results"),NOT(OR(H8="confirmed_issue",H8="probable_issue",H8="not_issue",H8="indeterminate"))),AND(AND(D8="retain",E8="statistical_results"),NOT(OR(I8="substantive",I8="minor_presentation",I8="indeterminate"))),AND(AND(D8="retain",E8="statistical_results"),J8<>"",NOT(OR(J8="direct",J8="possible",J8="unlikely",J8="unknown"))),AND(AND(D8="retain",OR(E8="report_internal_inconsistency",E8="plan_material")),NOT(OR(K8="substantive_inconsistency",K8="minor_presentation",K8="non_inconsistency",K8="indeterminate"))),AND(AND(D8="retain",E8="protocol_report"),L8<>"",NOT(OR(L8="substantive_difference",L8="minor_presentation",L8="version_timing",L8="non_inconsistency",L8="indeterminate")))),"CHECK FIELDS",IF(AND(F8<>"",NOT(OR(F8="no",F8="primary_done"))),"CHECK COMPLETE",IF(F8="primary_done","PRIMARY READY","PRIMARY DRAFT")))))),"CHECK INPUT / KEY") -> PRIMARY READY | K8: substantive_inconsistency | R8: TEST 2025::jama.2025.11178::C007
A9: 2025::jama.2025.11178::C008 | B9: Pain-severity 12-month painTRAINER SMD outside printed CI | C9: main article — PDF p. 10, Table 3, pain severity 12 months, painTRAINER vs usual care plus SMD. | D9: retain | E9: statistical_results | F9: primary_done | G9: =IFERROR(IF(LEN(TRIM(CLEAN(SUBSTITUTE(Setup!$B$2,CHAR(160)," "))))=0,"CHECK REVIEWER ID",IF(OR(A9="",(COUNTIF('C_jama.2024.24764'!$A$2:$A$9,A9)+COUNTIF('C_jama.2024.27643'!$A$2:$A$9,A9)+COUNTIF('C_jama.2025.11178'!$A$2:$A$38,A9)+COUNTIF('C_jama.2025.15185'!$A$2:$A$13,A9)+COUNTIF('C_jama.2025.15440'!$A$2:$A$3,A9)+COUNTIF('C_jama.2025.16450'!$A$2:$A$11,A9)+COUNTIF('C_jama.2025.19563'!$A$2:$A$8,A9)+COUNTIF('C_jama.2025.19843'!$A$2:$A$2,A9)+COUNTIF('C_jama.2025.20765'!$A$2:$A$14,A9)+COUNTIF('C_jama.2025.24175'!$A$2:$A$15,A9)+COUNTIF('C_jama.2025.4390'!$A$2:$A$4,A9)+COUNTIF('C_jama.2025.7583'!$A$2:$A$4,A9)+COUNTIF('C_jama.2025.7710'!$A$2:$A$5,A9)+COUNTIF('C_jama.2025.9110'!$A$2:$A$7,A9)+COUNTIF('C_jama.2025.9663'!$A$2:$A$4,A9))<>1,COUNTIFS(Candidates!$G$2:$G$132,A9,Candidates!$K$2:$K$132,"jama.2025.11178")<>1),"CHECK KEY",IF(OR(AND(NOT(AND(D9="retain",E9="statistical_results")),H9<>"",H9<>"not_applicable"),AND(NOT(AND(D9="retain",E9="statistical_results")),I9<>"",I9<>"not_applicable"),AND(NOT(AND(D9="retain",E9="statistical_results")),J9<>"",J9<>"not_applicable"),AND(NOT(AND(D9="retain",OR(E9="report_internal_inconsistency",E9="plan_material"))),K9<>"",K9<>"not_applicable"),AND(NOT(AND(D9="retain",E9="protocol_report")),L9<>"",L9<>"not_applicable")),"CLEAR INACTIVE VALUES",IF(OR(NOT(OR(D9="retain",D9="exclude",D9="discuss")),NOT(OR(E9="statistical_results",E9="report_internal_inconsistency",E9="plan_material",E9="protocol_report")),AND(AND(D9="retain",E9="statistical_results"),NOT(OR(H9="confirmed_issue",H9="probable_issue",H9="not_issue",H9="indeterminate"))),AND(AND(D9="retain",E9="statistical_results"),NOT(OR(I9="substantive",I9="minor_presentation",I9="indeterminate"))),AND(AND(D9="retain",E9="statistical_results"),J9<>"",NOT(OR(J9="direct",J9="possible",J9="unlikely",J9="unknown"))),AND(AND(D9="retain",OR(E9="report_internal_inconsistency",E9="plan_material")),NOT(OR(K9="substantive_inconsistency",K9="minor_presentation",K9="non_inconsistency",K9="indeterminate"))),AND(AND(D9="retain",E9="protocol_report"),L9<>"",NOT(OR(L9="substantive_difference",L9="minor_presentation",L9="version_timing",L9="non_inconsistency",L9="indeterminate")))),"CHECK FIELDS",IF(AND(F9<>"",NOT(OR(F9="no",F9="primary_done"))),"CHECK COMPLETE",IF(F9="primary_done","PRIMARY READY","PRIMARY DRAFT")))))),"CHECK INPUT / KEY") -> PRIMARY READY | H9: confirmed_issue | I9: substantive | R9: TEST 2025::jama.2025.11178::C008
A10: 2025::jama.2025.11178::C009 | B10: Pain-severity 12-month Health Coach SMD outside printed CI | C10: main article — PDF p. 10, Table 3, pain severity 12 months, Health Coach vs usual care plus SMD. | D10: retain | E10: statistical_results | F10: primary_done | G10: =IFERROR(IF(LEN(TRIM(CLEAN(SUBSTITUTE(Setup!$B$2,CHAR(160)," "))))=0,"CHECK REVIEWER ID",IF(OR(A10="",(COUNTIF('C_jama.2024.24764'!$A$2:$A$9,A10)+COUNTIF('C_jama.2024.27643'!$A$2:$A$9,A10)+COUNTIF('C_jama.2025.11178'!$A$2:$A$38,A10)+COUNTIF('C_jama.2025.15185'!$A$2:$A$13,A10)+COUNTIF('C_jama.2025.15440'!$A$2:$A$3,A10)+COUNTIF('C_jama.2025.16450'!$A$2:$A$11,A10)+COUNTIF('C_jama.2025.19563'!$A$2:$A$8,A10)+COUNTIF('C_jama.2025.19843'!$A$2:$A$2,A10)+COUNTIF('C_jama.2025.20765'!$A$2:$A$14,A10)+COUNTIF('C_jama.2025.24175'!$A$2:$A$15,A10)+COUNTIF('C_jama.2025.4390'!$A$2:$A$4,A10)+COUNTIF('C_jama.2025.7583'!$A$2:$A$4,A10)+COUNTIF('C_jama.2025.7710'!$A$2:$A$5,A10)+COUNTIF('C_jama.2025.9110'!$A$2:$A$7,A10)+COUNTIF('C_jama.2025.9663'!$A$2:$A$4,A10))<>1,COUNTIFS(Candidates!$G$2:$G$132,A10,Candidates!$K$2:$K$132,"jama.2025.11178")<>1),"CHECK KEY",IF(OR(AND(NOT(AND(D10="retain",E10="statistical_results")),H10<>"",H10<>"not_applicable"),AND(NOT(AND(D10="retain",E10="statistical_results")),I10<>"",I10<>"not_applicable"),AND(NOT(AND(D10="retain",E10="statistical_results")),J10<>"",J10<>"not_applicable"),AND(NOT(AND(D10="retain",OR(E10="report_internal_inconsistency",E10="plan_material"))),K10<>"",K10<>"not_applicable"),AND(NOT(AND(D10="retain",E10="protocol_report")),L10<>"",L10<>"not_applicable")),"CLEAR INACTIVE VALUES",IF(OR(NOT(OR(D10="retain",D10="exclude",D10="discuss")),NOT(OR(E10="statistical_results",E10="report_internal_inconsistency",E10="plan_material",E10="protocol_report")),AND(AND(D10="retain",E10="statistical_results"),NOT(OR(H10="confirmed_issue",H10="probable_issue",H10="not_issue",H10="indeterminate"))),AND(AND(D10="retain",E10="statistical_results"),NOT(OR(I10="substantive",I10="minor_presentation",I10="indeterminate"))),AND(AND(D10="retain",E10="statistical_results"),J10<>"",NOT(OR(J10="direct",J10="possible",J10="unlikely",J10="unknown"))),AND(AND(D10="retain",OR(E10="report_internal_inconsistency",E10="plan_material")),NOT(OR(K10="substantive_inconsistency",K10="minor_presentation",K10="non_inconsistency",K10="indeterminate"))),AND(AND(D10="retain",E10="protocol_report"),L10<>"",NOT(OR(L10="substantive_difference",L10="minor_presentation",L10="version_timing",L10="non_inconsistency",L10="indeterminate")))),"CHECK FIELDS",IF(AND(F10<>"",NOT(OR(F10="no",F10="primary_done"))),"CHECK COMPLETE",IF(F10="primary_done","PRIMARY READY","PRIMARY DRAFT")))))),"CHECK INPUT / KEY") -> PRIMARY READY | H10: confirmed_issue | I10: substantive | R10: TEST 2025::jama.2025.11178::C009
A11: 2025::jama.2025.11178::C010 | B11: Pain-intensity 12-month Health Coach SMD outside printed CI | C11: main article — PDF p. 10, Table 3, pain intensity 12 months, Health Coach vs usual care plus SMD. | D11: retain | E11: statistical_results | F11: primary_done | G11: =IFERROR(IF(LEN(TRIM(CLEAN(SUBSTITUTE(Setup!$B$2,CHAR(160)," "))))=0,"CHECK REVIEWER ID",IF(OR(A11="",(COUNTIF('C_jama.2024.24764'!$A$2:$A$9,A11)+COUNTIF('C_jama.2024.27643'!$A$2:$A$9,A11)+COUNTIF('C_jama.2025.11178'!$A$2:$A$38,A11)+COUNTIF('C_jama.2025.15185'!$A$2:$A$13,A11)+COUNTIF('C_jama.2025.15440'!$A$2:$A$3,A11)+COUNTIF('C_jama.2025.16450'!$A$2:$A$11,A11)+COUNTIF('C_jama.2025.19563'!$A$2:$A$8,A11)+COUNTIF('C_jama.2025.19843'!$A$2:$A$2,A11)+COUNTIF('C_jama.2025.20765'!$A$2:$A$14,A11)+COUNTIF('C_jama.2025.24175'!$A$2:$A$15,A11)+COUNTIF('C_jama.2025.4390'!$A$2:$A$4,A11)+COUNTIF('C_jama.2025.7583'!$A$2:$A$4,A11)+COUNTIF('C_jama.2025.7710'!$A$2:$A$5,A11)+COUNTIF('C_jama.2025.9110'!$A$2:$A$7,A11)+COUNTIF('C_jama.2025.9663'!$A$2:$A$4,A11))<>1,COUNTIFS(Candidates!$G$2:$G$132,A11,Candidates!$K$2:$K$132,"jama.2025.11178")<>1),"CHECK KEY",IF(OR(AND(NOT(AND(D11="retain",E11="statistical_results")),H11<>"",H11<>"not_applicable"),AND(NOT(AND(D11="retain",E11="statistical_results")),I11<>"",I11<>"not_applicable"),AND(NOT(AND(D11="retain",E11="statistical_results")),J11<>"",J11<>"not_applicable"),AND(NOT(AND(D11="retain",OR(E11="report_internal_inconsistency",E11="plan_material"))),K11<>"",K11<>"not_applicable"),AND(NOT(AND(D11="retain",E11="protocol_report")),L11<>"",L11<>"not_applicable")),"CLEAR INACTIVE VALUES",IF(OR(NOT(OR(D11="retain",D11="exclude",D11="discuss")),NOT(OR(E11="statistical_results",E11="report_internal_inconsistency",E11="plan_material",E11="protocol_report")),AND(AND(D11="retain",E11="statistical_results"),NOT(OR(H11="confirmed_issue",H11="probable_issue",H11="not_issue",H11="indeterminate"))),AND(AND(D11="retain",E11="statistical_results"),NOT(OR(I11="substantive",I11="minor_presentation",I11="indeterminate"))),AND(AND(D11="retain",E11="statistical_results"),J11<>"",NOT(OR(J11="direct",J11="possible",J11="unlikely",J11="unknown"))),AND(AND(D11="retain",OR(E11="report_internal_inconsistency",E11="plan_material")),NOT(OR(K11="substantive_inconsistency",K11="minor_presentation",K11="non_inconsistency",K11="indeterminate"))),AND(AND(D11="retain",E11="protocol_report"),L11<>"",NOT(OR(L11="substantive_difference",L11="minor_presentation",L11="version_timing",L11="non_inconsistency",L11="indeterminate")))),"CHECK FIELDS",IF(AND(F11<>"",NOT(OR(F11="no",F11="primary_done"))),"CHECK COMPLETE",IF(F11="primary_done","PRIMARY READY","PRIMARY DRAFT")))))),"CHECK INPUT / KEY") -> PRIMARY READY | H11: confirmed_issue | I11: substantive | R11: TEST 2025::jama.2025.11178::C010
A12: 2025::jama.2025.11178::C011 | B12: Pain-interference 12-month painTRAINER SMD outside printed CI | C12: main article — PDF p. 10, Table 3, interference 12 months, painTRAINER vs usual care plus SMD. | D12: retain | E12: statistical_results | F12: primary_done | G12: =IFERROR(IF(LEN(TRIM(CLEAN(SUBSTITUTE(Setup!$B$2,CHAR(160)," "))))=0,"CHECK REVIEWER ID",IF(OR(A12="",(COUNTIF('C_jama.2024.24764'!$A$2:$A$9,A12)+COUNTIF('C_jama.2024.27643'!$A$2:$A$9,A12)+COUNTIF('C_jama.2025.11178'!$A$2:$A$38,A12)+COUNTIF('C_jama.2025.15185'!$A$2:$A$13,A12)+COUNTIF('C_jama.2025.15440'!$A$2:$A$3,A12)+COUNTIF('C_jama.2025.16450'!$A$2:$A$11,A12)+COUNTIF('C_jama.2025.19563'!$A$2:$A$8,A12)+COUNTIF('C_jama.2025.19843'!$A$2:$A$2,A12)+COUNTIF('C_jama.2025.20765'!$A$2:$A$14,A12)+COUNTIF('C_jama.2025.24175'!$A$2:$A$15,A12)+COUNTIF('C_jama.2025.4390'!$A$2:$A$4,A12)+COUNTIF('C_jama.2025.7583'!$A$2:$A$4,A12)+COUNTIF('C_jama.2025.7710'!$A$2:$A$5,A12)+COUNTIF('C_jama.2025.9110'!$A$2:$A$7,A12)+COUNTIF('C_jama.2025.9663'!$A$2:$A$4,A12))<>1,COUNTIFS(Candidates!$G$2:$G$132,A12,Candidates!$K$2:$K$132,"jama.2025.11178")<>1),"CHECK KEY",IF(OR(AND(NOT(AND(D12="retain",E12="statistical_results")),H12<>"",H12<>"not_applicable"),AND(NOT(AND(D12="retain",E12="statistical_results")),I12<>"",I12<>"not_applicable"),AND(NOT(AND(D12="retain",E12="statistical_results")),J12<>"",J12<>"not_applicable"),AND(NOT(AND(D12="retain",OR(E12="report_internal_inconsistency",E12="plan_material"))),K12<>"",K12<>"not_applicable"),AND(NOT(AND(D12="retain",E12="protocol_report")),L12<>"",L12<>"not_applicable")),"CLEAR INACTIVE VALUES",IF(OR(NOT(OR(D12="retain",D12="exclude",D12="discuss")),NOT(OR(E12="statistical_results",E12="report_internal_inconsistency",E12="plan_material",E12="protocol_report")),AND(AND(D12="retain",E12="statistical_results"),NOT(OR(H12="confirmed_issue",H12="probable_issue",H12="not_issue",H12="indeterminate"))),AND(AND(D12="retain",E12="statistical_results"),NOT(OR(I12="substantive",I12="minor_presentation",I12="indeterminate"))),AND(AND(D12="retain",E12="statistical_results"),J12<>"",NOT(OR(J12="direct",J12="possible",J12="unlikely",J12="unknown"))),AND(AND(D12="retain",OR(E12="report_internal_inconsistency",E12="plan_material")),NOT(OR(K12="substantive_inconsistency",K12="minor_presentation",K12="non_inconsistency",K12="indeterminate"))),AND(AND(D12="retain",E12="protocol_report"),L12<>"",NOT(OR(L12="substantive_difference",L12="minor_presentation",L12="version_timing",L12="non_inconsistency",L12="indeterminate")))),"CHECK FIELDS",IF(AND(F12<>"",NOT(OR(F12="no",F12="primary_done"))),"CHECK COMPLETE",IF(F12="primary_done","PRIMARY READY","PRIMARY DRAFT")))))),"CHECK INPUT / KEY") -> PRIMARY READY | H12: confirmed_issue | I12: substantive | R12: TEST 2025::jama.2025.11178::C011
A13: 2025::jama.2025.11178::C012 | B13: Pain-interference 12-month Health Coach SMD outside printed CI | C13: main article — PDF p. 10, Table 3, interference 12 months, Health Coach vs usual care plus SMD. | D13: retain | E13: statistical_results | F13: primary_done | G13: =IFERROR(IF(LEN(TRIM(CLEAN(SUBSTITUTE(Setup!$B$2,CHAR(160)," "))))=0,"CHECK REVIEWER ID",IF(OR(A13="",(COUNTIF('C_jama.2024.24764'!$A$2:$A$9,A13)+COUNTIF('C_jama.2024.27643'!$A$2:$A$9,A13)+COUNTIF('C_jama.2025.11178'!$A$2:$A$38,A13)+COUNTIF('C_jama.2025.15185'!$A$2:$A$13,A13)+COUNTIF('C_jama.2025.15440'!$A$2:$A$3,A13)+COUNTIF('C_jama.2025.16450'!$A$2:$A$11,A13)+COUNTIF('C_jama.2025.19563'!$A$2:$A$8,A13)+COUNTIF('C_jama.2025.19843'!$A$2:$A$2,A13)+COUNTIF('C_jama.2025.20765'!$A$2:$A$14,A13)+COUNTIF('C_jama.2025.24175'!$A$2:$A$15,A13)+COUNTIF('C_jama.2025.4390'!$A$2:$A$4,A13)+COUNTIF('C_jama.2025.7583'!$A$2:$A$4,A13)+COUNTIF('C_jama.2025.7710'!$A$2:$A$5,A13)+COUNTIF('C_jama.2025.9110'!$A$2:$A$7,A13)+COUNTIF('C_jama.2025.9663'!$A$2:$A$4,A13))<>1,COUNTIFS(Candidates!$G$2:$G$132,A13,Candidates!$K$2:$K$132,"jama.2025.11178")<>1),"CHECK KEY",IF(OR(AND(NOT(AND(D13="retain",E13="statistical_results")),H13<>"",H13<>"not_applicable"),AND(NOT(AND(D13="retain",E13="statistical_results")),I13<>"",I13<>"not_applicable"),AND(NOT(AND(D13="retain",E13="statistical_results")),J13<>"",J13<>"not_applicable"),AND(NOT(AND(D13="retain",OR(E13="report_internal_inconsistency",E13="plan_material"))),K13<>"",K13<>"not_applicable"),AND(NOT(AND(D13="retain",E13="protocol_report")),L13<>"",L13<>"not_applicable")),"CLEAR INACTIVE VALUES",IF(OR(NOT(OR(D13="retain",D13="exclude",D13="discuss")),NOT(OR(E13="statistical_results",E13="report_internal_inconsistency",E13="plan_material",E13="protocol_report")),AND(AND(D13="retain",E13="statistical_results"),NOT(OR(H13="confirmed_issue",H13="probable_issue",H13="not_issue",H13="indeterminate"))),AND(AND(D13="retain",E13="statistical_results"),NOT(OR(I13="substantive",I13="minor_presentation",I13="indeterminate"))),AND(AND(D13="retain",E13="statistical_results"),J13<>"",NOT(OR(J13="direct",J13="possible",J13="unlikely",J13="unknown"))),AND(AND(D13="retain",OR(E13="report_internal_inconsistency",E13="plan_material")),NOT(OR(K13="substantive_inconsistency",K13="minor_presentation",K13="non_inconsistency",K13="indeterminate"))),AND(AND(D13="retain",E13="protocol_report"),L13<>"",NOT(OR(L13="substantive_difference",L13="minor_presentation",L13="version_timing",L13="non_inconsistency",L13="indeterminate")))),"CHECK FIELDS",IF(AND(F13<>"",NOT(OR(F13="no",F13="primary_done"))),"CHECK COMPLETE",IF(F13="primary_done","PRIMARY READY","PRIMARY DRAFT")))))),"CHECK INPUT / KEY") -> PRIMARY READY | H13: confirmed_issue | I13: substantive | R13: TEST 2025::jama.2025.11178::C012
A14: 2025::jama.2025.11178::C013 | B14: Social-role 3-month painTRAINER SMD endpoints reversed | C14: main article — PDF p. 10, Table 3, social role, 3 months, painTRAINER vs usual care plus SMD. | D14: retain | E14: statistical_results | F14: primary_done | G14: =IFERROR(IF(LEN(TRIM(CLEAN(SUBSTITUTE(Setup!$B$2,CHAR(160)," "))))=0,"CHECK REVIEWER ID",IF(OR(A14="",(COUNTIF('C_jama.2024.24764'!$A$2:$A$9,A14)+COUNTIF('C_jama.2024.27643'!$A$2:$A$9,A14)+COUNTIF('C_jama.2025.11178'!$A$2:$A$38,A14)+COUNTIF('C_jama.2025.15185'!$A$2:$A$13,A14)+COUNTIF('C_jama.2025.15440'!$A$2:$A$3,A14)+COUNTIF('C_jama.2025.16450'!$A$2:$A$11,A14)+COUNTIF('C_jama.2025.19563'!$A$2:$A$8,A14)+COUNTIF('C_jama.2025.19843'!$A$2:$A$2,A14)+COUNTIF('C_jama.2025.20765'!$A$2:$A$14,A14)+COUNTIF('C_jama.2025.24175'!$A$2:$A$15,A14)+COUNTIF('C_jama.2025.4390'!$A$2:$A$4,A14)+COUNTIF('C_jama.2025.7583'!$A$2:$A$4,A14)+COUNTIF('C_jama.2025.7710'!$A$2:$A$5,A14)+COUNTIF('C_jama.2025.9110'!$A$2:$A$7,A14)+COUNTIF('C_jama.2025.9663'!$A$2:$A$4,A14))<>1,COUNTIFS(Candidates!$G$2:$G$132,A14,Candidates!$K$2:$K$132,"jama.2025.11178")<>1),"CHECK KEY",IF(OR(AND(NOT(AND(D14="retain",E14="statistical_results")),H14<>"",H14<>"not_applicable"),AND(NOT(AND(D14="retain",E14="statistical_results")),I14<>"",I14<>"not_applicable"),AND(NOT(AND(D14="retain",E14="statistical_results")),J14<>"",J14<>"not_applicable"),AND(NOT(AND(D14="retain",OR(E14="report_internal_inconsistency",E14="plan_material"))),K14<>"",K14<>"not_applicable"),AND(NOT(AND(D14="retain",E14="protocol_report")),L14<>"",L14<>"not_applicable")),"CLEAR INACTIVE VALUES",IF(OR(NOT(OR(D14="retain",D14="exclude",D14="discuss")),NOT(OR(E14="statistical_results",E14="report_internal_inconsistency",E14="plan_material",E14="protocol_report")),AND(AND(D14="retain",E14="statistical_results"),NOT(OR(H14="confirmed_issue",H14="probable_issue",H14="not_issue",H14="indeterminate"))),AND(AND(D14="retain",E14="statistical_results"),NOT(OR(I14="substantive",I14="minor_presentation",I14="indeterminate"))),AND(AND(D14="retain",E14="statistical_results"),J14<>"",NOT(OR(J14="direct",J14="possible",J14="unlikely",J14="unknown"))),AND(AND(D14="retain",OR(E14="report_internal_inconsistency",E14="plan_material")),NOT(OR(K14="substantive_inconsistency",K14="minor_presentation",K14="non_inconsistency",K14="indeterminate"))),AND(AND(D14="retain",E14="protocol_report"),L14<>"",NOT(OR(L14="substantive_difference",L14="minor_presentation",L14="version_timing",L14="non_inconsistency",L14="indeterminate")))),"CHECK FIELDS",IF(AND(F14<>"",NOT(OR(F14="no",F14="primary_done"))),"CHECK COMPLETE",IF(F14="primary_done","PRIMARY READY","PRIMARY DRAFT")))))),"CHECK INPUT / KEY") -> PRIMARY READY | H14: confirmed_issue | I14: substantive | R14: TEST 2025::jama.2025.11178::C013
A15: 2025::jama.2025.11178::C014 | B15: Social-role 3-month Health Coach SMD endpoints reversed | C15: main article — PDF p. 10, Table 3, social role, 3 months, Health Coach vs usual care plus SMD. | D15: retain | E15: statistical_results | F15: primary_done | G15: =IFERROR(IF(LEN(TRIM(CLEAN(SUBSTITUTE(Setup!$B$2,CHAR(160)," "))))=0,"CHECK REVIEWER ID",IF(OR(A15="",(COUNTIF('C_jama.2024.24764'!$A$2:$A$9,A15)+COUNTIF('C_jama.2024.27643'!$A$2:$A$9,A15)+COUNTIF('C_jama.2025.11178'!$A$2:$A$38,A15)+COUNTIF('C_jama.2025.15185'!$A$2:$A$13,A15)+COUNTIF('C_jama.2025.15440'!$A$2:$A$3,A15)+COUNTIF('C_jama.2025.16450'!$A$2:$A$11,A15)+COUNTIF('C_jama.2025.19563'!$A$2:$A$8,A15)+COUNTIF('C_jama.2025.19843'!$A$2:$A$2,A15)+COUNTIF('C_jama.2025.20765'!$A$2:$A$14,A15)+COUNTIF('C_jama.2025.24175'!$A$2:$A$15,A15)+COUNTIF('C_jama.2025.4390'!$A$2:$A$4,A15)+COUNTIF('C_jama.2025.7583'!$A$2:$A$4,A15)+COUNTIF('C_jama.2025.7710'!$A$2:$A$5,A15)+COUNTIF('C_jama.2025.9110'!$A$2:$A$7,A15)+COUNTIF('C_jama.2025.9663'!$A$2:$A$4,A15))<>1,COUNTIFS(Candidates!$G$2:$G$132,A15,Candidates!$K$2:$K$132,"jama.2025.11178")<>1),"CHECK KEY",IF(OR(AND(NOT(AND(D15="retain",E15="statistical_results")),H15<>"",H15<>"not_applicable"),AND(NOT(AND(D15="retain",E15="statistical_results")),I15<>"",I15<>"not_applicable"),AND(NOT(AND(D15="retain",E15="statistical_results")),J15<>"",J15<>"not_applicable"),AND(NOT(AND(D15="retain",OR(E15="report_internal_inconsistency",E15="plan_material"))),K15<>"",K15<>"not_applicable"),AND(NOT(AND(D15="retain",E15="protocol_report")),L15<>"",L15<>"not_applicable")),"CLEAR INACTIVE VALUES",IF(OR(NOT(OR(D15="retain",D15="exclude",D15="discuss")),NOT(OR(E15="statistical_results",E15="report_internal_inconsistency",E15="plan_material",E15="protocol_report")),AND(AND(D15="retain",E15="statistical_results"),NOT(OR(H15="confirmed_issue",H15="probable_issue",H15="not_issue",H15="indeterminate"))),AND(AND(D15="retain",E15="statistical_results"),NOT(OR(I15="substantive",I15="minor_presentation",I15="indeterminate"))),AND(AND(D15="retain",E15="statistical_results"),J15<>"",NOT(OR(J15="direct",J15="possible",J15="unlikely",J15="unknown"))),AND(AND(D15="retain",OR(E15="report_internal_inconsistency",E15="plan_material")),NOT(OR(K15="substantive_inconsistency",K15="minor_presentation",K15="non_inconsistency",K15="indeterminate"))),AND(AND(D15="retain",E15="protocol_report"),L15<>"",NOT(OR(L15="substantive_difference",L15="minor_presentation",L15="version_timing",L15="non_inconsistency",L15="indeterminate")))),"CHECK FIELDS",IF(AND(F15<>"",NOT(OR(F15="no",F15="primary_done"))),"CHECK COMPLETE",IF(F15="primary_done","PRIMARY READY","PRIMARY DRAFT")))))),"CHECK INPUT / KEY") -> PRIMARY READY | H15: confirmed_issue | I15: substantive | R15: TEST 2025::jama.2025.11178::C014
A16: 2025::jama.2025.11178::C015 | B16: Social-role 3-month Health Coach versus painTRAINER SMD endpoints reversed | C16: main article — PDF p. 10, Table 3, social role, 3 months, Health Coach vs painTRAINER SMD. | D16: retain | E16: statistical_results | F16: primary_done | G16: =IFERROR(IF(LEN(TRIM(CLEAN(SUBSTITUTE(Setup!$B$2,CHAR(160)," "))))=0,"CHECK REVIEWER ID",IF(OR(A16="",(COUNTIF('C_jama.2024.24764'!$A$2:$A$9,A16)+COUNTIF('C_jama.2024.27643'!$A$2:$A$9,A16)+COUNTIF('C_jama.2025.11178'!$A$2:$A$38,A16)+COUNTIF('C_jama.2025.15185'!$A$2:$A$13,A16)+COUNTIF('C_jama.2025.15440'!$A$2:$A$3,A16)+COUNTIF('C_jama.2025.16450'!$A$2:$A$11,A16)+COUNTIF('C_jama.2025.19563'!$A$2:$A$8,A16)+COUNTIF('C_jama.2025.19843'!$A$2:$A$2,A16)+COUNTIF('C_jama.2025.20765'!$A$2:$A$14,A16)+COUNTIF('C_jama.2025.24175'!$A$2:$A$15,A16)+COUNTIF('C_jama.2025.4390'!$A$2:$A$4,A16)+COUNTIF('C_jama.2025.7583'!$A$2:$A$4,A16)+COUNTIF('C_jama.2025.7710'!$A$2:$A$5,A16)+COUNTIF('C_jama.2025.9110'!$A$2:$A$7,A16)+COUNTIF('C_jama.2025.9663'!$A$2:$A$4,A16))<>1,COUNTIFS(Candidates!$G$2:$G$132,A16,Candidates!$K$2:$K$132,"jama.2025.11178")<>1),"CHECK KEY",IF(OR(AND(NOT(AND(D16="retain",E16="statistical_results")),H16<>"",H16<>"not_applicable"),AND(NOT(AND(D16="retain",E16="statistical_results")),I16<>"",I16<>"not_applicable"),AND(NOT(AND(D16="retain",E16="statistical_results")),J16<>"",J16<>"not_applicable"),AND(NOT(AND(D16="retain",OR(E16="report_internal_inconsistency",E16="plan_material"))),K16<>"",K16<>"not_applicable"),AND(NOT(AND(D16="retain",E16="protocol_report")),L16<>"",L16<>"not_applicable")),"CLEAR INACTIVE VALUES",IF(OR(NOT(OR(D16="retain",D16="exclude",D16="discuss")),NOT(OR(E16="statistical_results",E16="report_internal_inconsistency",E16="plan_material",E16="protocol_report")),AND(AND(D16="retain",E16="statistical_results"),NOT(OR(H16="confirmed_issue",H16="probable_issue",H16="not_issue",H16="indeterminate"))),AND(AND(D16="retain",E16="statistical_results"),NOT(OR(I16="substantive",I16="minor_presentation",I16="indeterminate"))),AND(AND(D16="retain",E16="statistical_results"),J16<>"",NOT(OR(J16="direct",J16="possible",J16="unlikely",J16="unknown"))),AND(AND(D16="retain",OR(E16="report_internal_inconsistency",E16="plan_material")),NOT(OR(K16="substantive_inconsistency",K16="minor_presentation",K16="non_inconsistency",K16="indeterminate"))),AND(AND(D16="retain",E16="protocol_report"),L16<>"",NOT(OR(L16="substantive_difference",L16="minor_presentation",L16="version_timing",L16="non_inconsistency",L16="indeterminate")))),"CHECK FIELDS",IF(AND(F16<>"",NOT(OR(F16="no",F16="primary_done"))),"CHECK COMPLETE",IF(F16="primary_done","PRIMARY READY","PRIMARY DRAFT")))))),"CHECK INPUT / KEY") -> PRIMARY READY | H16: confirmed_issue | I16: substantive | R16: TEST 2025::jama.2025.11178::C015
A17: 2025::jama.2025.11178::C016 | B17: Social-role 6-month painTRAINER SMD endpoints reversed | C17: main article — PDF p. 10, Table 3, social role, 6 months, painTRAINER vs usual care plus SMD. | D17: retain | E17: statistical_results | F17: primary_done | G17: =IFERROR(IF(LEN(TRIM(CLEAN(SUBSTITUTE(Setup!$B$2,CHAR(160)," "))))=0,"CHECK REVIEWER ID",IF(OR(A17="",(COUNTIF('C_jama.2024.24764'!$A$2:$A$9,A17)+COUNTIF('C_jama.2024.27643'!$A$2:$A$9,A17)+COUNTIF('C_jama.2025.11178'!$A$2:$A$38,A17)+COUNTIF('C_jama.2025.15185'!$A$2:$A$13,A17)+COUNTIF('C_jama.2025.15440'!$A$2:$A$3,A17)+COUNTIF('C_jama.2025.16450'!$A$2:$A$11,A17)+COUNTIF('C_jama.2025.19563'!$A$2:$A$8,A17)+COUNTIF('C_jama.2025.19843'!$A$2:$A$2,A17)+COUNTIF('C_jama.2025.20765'!$A$2:$A$14,A17)+COUNTIF('C_jama.2025.24175'!$A$2:$A$15,A17)+COUNTIF('C_jama.2025.4390'!$A$2:$A$4,A17)+COUNTIF('C_jama.2025.7583'!$A$2:$A$4,A17)+COUNTIF('C_jama.2025.7710'!$A$2:$A$5,A17)+COUNTIF('C_jama.2025.9110'!$A$2:$A$7,A17)+COUNTIF('C_jama.2025.9663'!$A$2:$A$4,A17))<>1,COUNTIFS(Candidates!$G$2:$G$132,A17,Candidates!$K$2:$K$132,"jama.2025.11178")<>1),"CHECK KEY",IF(OR(AND(NOT(AND(D17="retain",E17="statistical_results")),H17<>"",H17<>"not_applicable"),AND(NOT(AND(D17="retain",E17="statistical_results")),I17<>"",I17<>"not_applicable"),AND(NOT(AND(D17="retain",E17="statistical_results")),J17<>"",J17<>"not_applicable"),AND(NOT(AND(D17="retain",OR(E17="report_internal_inconsistency",E17="plan_material"))),K17<>"",K17<>"not_applicable"),AND(NOT(AND(D17="retain",E17="protocol_report")),L17<>"",L17<>"not_applicable")),"CLEAR INACTIVE VALUES",IF(OR(NOT(OR(D17="retain",D17="exclude",D17="discuss")),NOT(OR(E17="statistical_results",E17="report_internal_inconsistency",E17="plan_material",E17="protocol_report")),AND(AND(D17="retain",E17="statistical_results"),NOT(OR(H17="confirmed_issue",H17="probable_issue",H17="not_issue",H17="indeterminate"))),AND(AND(D17="retain",E17="statistical_results"),NOT(OR(I17="substantive",I17="minor_presentation",I17="indeterminate"))),AND(AND(D17="retain",E17="statistical_results"),J17<>"",NOT(OR(J17="direct",J17="possible",J17="unlikely",J17="unknown"))),AND(AND(D17="retain",OR(E17="report_internal_inconsistency",E17="plan_material")),NOT(OR(K17="substantive_inconsistency",K17="minor_presentation",K17="non_inconsistency",K17="indeterminate"))),AND(AND(D17="retain",E17="protocol_report"),L17<>"",NOT(OR(L17="substantive_difference",L17="minor_presentation",L17="version_timing",L17="non_inconsistency",L17="indeterminate")))),"CHECK FIELDS",IF(AND(F17<>"",NOT(OR(F17="no",F17="primary_done"))),"CHECK COMPLETE",IF(F17="primary_done","PRIMARY READY","PRIMARY DRAFT")))))),"CHECK INPUT / KEY") -> PRIMARY READY | H17: confirmed_issue | I17: substantive | R17: TEST 2025::jama.2025.11178::C016
A18: 2025::jama.2025.11178::C017 | B18: Social-role 6-month Health Coach SMD endpoints reversed | C18: main article — PDF p. 10, Table 3, social role, 6 months, Health Coach vs usual care plus SMD. | D18: retain | E18: statistical_results | F18: primary_done | G18: =IFERROR(IF(LEN(TRIM(CLEAN(SUBSTITUTE(Setup!$B$2,CHAR(160)," "))))=0,"CHECK REVIEWER ID",IF(OR(A18="",(COUNTIF('C_jama.2024.24764'!$A$2:$A$9,A18)+COUNTIF('C_jama.2024.27643'!$A$2:$A$9,A18)+COUNTIF('C_jama.2025.11178'!$A$2:$A$38,A18)+COUNTIF('C_jama.2025.15185'!$A$2:$A$13,A18)+COUNTIF('C_jama.2025.15440'!$A$2:$A$3,A18)+COUNTIF('C_jama.2025.16450'!$A$2:$A$11,A18)+COUNTIF('C_jama.2025.19563'!$A$2:$A$8,A18)+COUNTIF('C_jama.2025.19843'!$A$2:$A$2,A18)+COUNTIF('C_jama.2025.20765'!$A$2:$A$14,A18)+COUNTIF('C_jama.2025.24175'!$A$2:$A$15,A18)+COUNTIF('C_jama.2025.4390'!$A$2:$A$4,A18)+COUNTIF('C_jama.2025.7583'!$A$2:$A$4,A18)+COUNTIF('C_jama.2025.7710'!$A$2:$A$5,A18)+COUNTIF('C_jama.2025.9110'!$A$2:$A$7,A18)+COUNTIF('C_jama.2025.9663'!$A$2:$A$4,A18))<>1,COUNTIFS(Candidates!$G$2:$G$132,A18,Candidates!$K$2:$K$132,"jama.2025.11178")<>1),"CHECK KEY",IF(OR(AND(NOT(AND(D18="retain",E18="statistical_results")),H18<>"",H18<>"not_applicable"),AND(NOT(AND(D18="retain",E18="statistical_results")),I18<>"",I18<>"not_applicable"),AND(NOT(AND(D18="retain",E18="statistical_results")),J18<>"",J18<>"not_applicable"),AND(NOT(AND(D18="retain",OR(E18="report_internal_inconsistency",E18="plan_material"))),K18<>"",K18<>"not_applicable"),AND(NOT(AND(D18="retain",E18="protocol_report")),L18<>"",L18<>"not_applicable")),"CLEAR INACTIVE VALUES",IF(OR(NOT(OR(D18="retain",D18="exclude",D18="discuss")),NOT(OR(E18="statistical_results",E18="report_internal_inconsistency",E18="plan_material",E18="protocol_report")),AND(AND(D18="retain",E18="statistical_results"),NOT(OR(H18="confirmed_issue",H18="probable_issue",H18="not_issue",H18="indeterminate"))),AND(AND(D18="retain",E18="statistical_results"),NOT(OR(I18="substantive",I18="minor_presentation",I18="indeterminate"))),AND(AND(D18="retain",E18="statistical_results"),J18<>"",NOT(OR(J18="direct",J18="possible",J18="unlikely",J18="unknown"))),AND(AND(D18="retain",OR(E18="report_internal_inconsistency",E18="plan_material")),NOT(OR(K18="substantive_inconsistency",K18="minor_presentation",K18="non_inconsistency",K18="indeterminate"))),AND(AND(D18="retain",E18="protocol_report"),L18<>"",NOT(OR(L18="substantive_difference",L18="minor_presentation",L18="version_timing",L18="non_inconsistency",L18="indeterminate")))),"CHECK FIELDS",IF(AND(F18<>"",NOT(OR(F18="no",F18="primary_done"))),"CHECK COMPLETE",IF(F18="primary_done","PRIMARY READY","PRIMARY DRAFT")))))),"CHECK INPUT / KEY") -> PRIMARY READY | H18: confirmed_issue | I18: substantive | R18: TEST 2025::jama.2025.11178::C017
A19: 2025::jama.2025.11178::C018 | B19: Social-role 6-month Health Coach versus painTRAINER SMD endpoints reversed | C19: main article — PDF p. 10, Table 3, social role, 6 months, Health Coach vs painTRAINER SMD. | D19: retain | E19: statistical_results | F19: primary_done | G19: =IFERROR(IF(LEN(TRIM(CLEAN(SUBSTITUTE(Setup!$B$2,CHAR(160)," "))))=0,"CHECK REVIEWER ID",IF(OR(A19="",(COUNTIF('C_jama.2024.24764'!$A$2:$A$9,A19)+COUNTIF('C_jama.2024.27643'!$A$2:$A$9,A19)+COUNTIF('C_jama.2025.11178'!$A$2:$A$38,A19)+COUNTIF('C_jama.2025.15185'!$A$2:$A$13,A19)+COUNTIF('C_jama.2025.15440'!$A$2:$A$3,A19)+COUNTIF('C_jama.2025.16450'!$A$2:$A$11,A19)+COUNTIF('C_jama.2025.19563'!$A$2:$A$8,A19)+COUNTIF('C_jama.2025.19843'!$A$2:$A$2,A19)+COUNTIF('C_jama.2025.20765'!$A$2:$A$14,A19)+COUNTIF('C_jama.2025.24175'!$A$2:$A$15,A19)+COUNTIF('C_jama.2025.4390'!$A$2:$A$4,A19)+COUNTIF('C_jama.2025.7583'!$A$2:$A$4,A19)+COUNTIF('C_jama.2025.7710'!$A$2:$A$5,A19)+COUNTIF('C_jama.2025.9110'!$A$2:$A$7,A19)+COUNTIF('C_jama.2025.9663'!$A$2:$A$4,A19))<>1,COUNTIFS(Candidates!$G$2:$G$132,A19,Candidates!$K$2:$K$132,"jama.2025.11178")<>1),"CHECK KEY",IF(OR(AND(NOT(AND(D19="retain",E19="statistical_results")),H19<>"",H19<>"not_applicable"),AND(NOT(AND(D19="retain",E19="statistical_results")),I19<>"",I19<>"not_applicable"),AND(NOT(AND(D19="retain",E19="statistical_results")),J19<>"",J19<>"not_applicable"),AND(NOT(AND(D19="retain",OR(E19="report_internal_inconsistency",E19="plan_material"))),K19<>"",K19<>"not_applicable"),AND(NOT(AND(D19="retain",E19="protocol_report")),L19<>"",L19<>"not_applicable")),"CLEAR INACTIVE VALUES",IF(OR(NOT(OR(D19="retain",D19="exclude",D19="discuss")),NOT(OR(E19="statistical_results",E19="report_internal_inconsistency",E19="plan_material",E19="protocol_report")),AND(AND(D19="retain",E19="statistical_results"),NOT(OR(H19="confirmed_issue",H19="probable_issue",H19="not_issue",H19="indeterminate"))),AND(AND(D19="retain",E19="statistical_results"),NOT(OR(I19="substantive",I19="minor_presentation",I19="indeterminate"))),AND(AND(D19="retain",E19="statistical_results"),J19<>"",NOT(OR(J19="direct",J19="possible",J19="unlikely",J19="unknown"))),AND(AND(D19="retain",OR(E19="report_internal_inconsistency",E19="plan_material")),NOT(OR(K19="substantive_inconsistency",K19="minor_presentation",K19="non_inconsistency",K19="indeterminate"))),AND(AND(D19="retain",E19="protocol_report"),L19<>"",NOT(OR(L19="substantive_difference",L19="minor_presentation",L19="version_timing",L19="non_inconsistency",L19="indeterminate")))),"CHECK FIELDS",IF(AND(F19<>"",NOT(OR(F19="no",F19="primary_done"))),"CHECK COMPLETE",IF(F19="primary_done","PRIMARY READY","PRIMARY DRAFT")))))),"CHECK INPUT / KEY") -> PRIMARY READY | H19: confirmed_issue | I19: substantive | R19: TEST 2025::jama.2025.11178::C018
A20: 2025::jama.2025.11178::C019 | B20: Social-role 12-month painTRAINER SMD endpoints reversed | C20: main article — PDF p. 10, Table 3, social role, 12 months, painTRAINER vs usual care plus SMD. | D20: retain | E20: statistical_results | F20: primary_done | G20: =IFERROR(IF(LEN(TRIM(CLEAN(SUBSTITUTE(Setup!$B$2,CHAR(160)," "))))=0,"CHECK REVIEWER ID",IF(OR(A20="",(COUNTIF('C_jama.2024.24764'!$A$2:$A$9,A20)+COUNTIF('C_jama.2024.27643'!$A$2:$A$9,A20)+COUNTIF('C_jama.2025.11178'!$A$2:$A$38,A20)+COUNTIF('C_jama.2025.15185'!$A$2:$A$13,A20)+COUNTIF('C_jama.2025.15440'!$A$2:$A$3,A20)+COUNTIF('C_jama.2025.16450'!$A$2:$A$11,A20)+COUNTIF('C_jama.2025.19563'!$A$2:$A$8,A20)+COUNTIF('C_jama.2025.19843'!$A$2:$A$2,A20)+COUNTIF('C_jama.2025.20765'!$A$2:$A$14,A20)+COUNTIF('C_jama.2025.24175'!$A$2:$A$15,A20)+COUNTIF('C_jama.2025.4390'!$A$2:$A$4,A20)+COUNTIF('C_jama.2025.7583'!$A$2:$A$4,A20)+COUNTIF('C_jama.2025.7710'!$A$2:$A$5,A20)+COUNTIF('C_jama.2025.9110'!$A$2:$A$7,A20)+COUNTIF('C_jama.2025.9663'!$A$2:$A$4,A20))<>1,COUNTIFS(Candidates!$G$2:$G$132,A20,Candidates!$K$2:$K$132,"jama.2025.11178")<>1),"CHECK KEY",IF(OR(AND(NOT(AND(D20="retain",E20="statistical_results")),H20<>"",H20<>"not_applicable"),AND(NOT(AND(D20="retain",E20="statistical_results")),I20<>"",I20<>"not_applicable"),AND(NOT(AND(D20="retain",E20="statistical_results")),J20<>"",J20<>"not_applicable"),AND(NOT(AND(D20="retain",OR(E20="report_internal_inconsistency",E20="plan_material"))),K20<>"",K20<>"not_applicable"),AND(NOT(AND(D20="retain",E20="protocol_report")),L20<>"",L20<>"not_applicable")),"CLEAR INACTIVE VALUES",IF(OR(NOT(OR(D20="retain",D20="exclude",D20="discuss")),NOT(OR(E20="statistical_results",E20="report_internal_inconsistency",E20="plan_material",E20="protocol_report")),AND(AND(D20="retain",E20="statistical_results"),NOT(OR(H20="confirmed_issue",H20="probable_issue",H20="not_issue",H20="indeterminate"))),AND(AND(D20="retain",E20="statistical_results"),NOT(OR(I20="substantive",I20="minor_presentation",I20="indeterminate"))),AND(AND(D20="retain",E20="statistical_results"),J20<>"",NOT(OR(J20="direct",J20="possible",J20="unlikely",J20="unknown"))),AND(AND(D20="retain",OR(E20="report_internal_inconsistency",E20="plan_material")),NOT(OR(K20="substantive_inconsistency",K20="minor_presentation",K20="non_inconsistency",K20="indeterminate"))),AND(AND(D20="retain",E20="protocol_report"),L20<>"",NOT(OR(L20="substantive_difference",L20="minor_presentation",L20="version_timing",L20="non_inconsistency",L20="indeterminate")))),"CHECK FIELDS",IF(AND(F20<>"",NOT(OR(F20="no",F20="primary_done"))),"CHECK COMPLETE",IF(F20="primary_done","PRIMARY READY","PRIMARY DRAFT")))))),"CHECK INPUT / KEY") -> PRIMARY READY | H20: confirmed_issue | I20: substantive | R20: TEST 2025::jama.2025.11178::C019
... A34: 2025::jama.2025.11178::C033 | B34: PGIC-pain 12-month Health Coach versus painTRAINER SMD outside printed CI | C34: main article — PDF p. 11, Table 3, PGIC-pain, 12 months, Health Coach vs painTRAINER SMD. | D34: retain | E34: statistical_results | F34: primary_done | G34: =IFERROR(IF(LEN(TRIM(CLEAN(SUBSTITUTE(Setup!$B$2,CHAR(160)," "))))=0,"CHECK REVIEWER ID",IF(OR(A34="",(COUNTIF('C_jama.2024.24764'!$A$2:$A$9,A34)+COUNTIF('C_jama.2024.27643'!$A$2:$A$9,A34)+COUNTIF('C_jama.2025.11178'!$A$2:$A$38,A34)+COUNTIF('C_jama.2025.15185'!$A$2:$A$13,A34)+COUNTIF('C_jama.2025.15440'!$A$2:$A$3,A34)+COUNTIF('C_jama.2025.16450'!$A$2:$A$11,A34)+COUNTIF('C_jama.2025.19563'!$A$2:$A$8,A34)+COUNTIF('C_jama.2025.19843'!$A$2:$A$2,A34)+COUNTIF('C_jama.2025.20765'!$A$2:$A$14,A34)+COUNTIF('C_jama.2025.24175'!$A$2:$A$15,A34)+COUNTIF('C_jama.2025.4390'!$A$2:$A$4,A34)+COUNTIF('C_jama.2025.7583'!$A$2:$A$4,A34)+COUNTIF('C_jama.2025.7710'!$A$2:$A$5,A34)+COUNTIF('C_jama.2025.9110'!$A$2:$A$7,A34)+COUNTIF('C_jama.2025.9663'!$A$2:$A$4,A34))<>1,COUNTIFS(Candidates!$G$2:$G$132,A34,Candidates!$K$2:$K$132,"jama.2025.11178")<>1),"CHECK KEY",IF(OR(AND(NOT(AND(D34="retain",E34="statistical_results")),H34<>"",H34<>"not_applicable"),AND(NOT(AND(D34="retain",E34="statistical_results")),I34<>"",I34<>"not_applicable"),AND(NOT(AND(D34="retain",E34="statistical_results")),J34<>"",J34<>"not_applicable"),AND(NOT(AND(D34="retain",OR(E34="report_internal_inconsistency",E34="plan_material"))),K34<>"",K34<>"not_applicable"),AND(NOT(AND(D34="retain",E34="protocol_report")),L34<>"",L34<>"not_applicable")),"CLEAR INACTIVE VALUES",IF(OR(NOT(OR(D34="retain",D34="exclude",D34="discuss")),NOT(OR(E34="statistical_results",E34="report_internal_inconsistency",E34="plan_material",E34="protocol_report")),AND(AND(D34="retain",E34="statistical_results"),NOT(OR(H34="confirmed_issue",H34="probable_issue",H34="not_issue",H34="indeterminate"))),AND(AND(D34="retain",E34="statistical_results"),NOT(OR(I34="substantive",I34="minor_presentation",I34="indeterminate"))),AND(AND(D34="retain",E34="statistical_results"),J34<>"",NOT(OR(J34="direct",J34="possible",J34="unlikely",J34="unknown"))),AND(AND(D34="retain",OR(E34="report_internal_inconsistency",E34="plan_material")),NOT(OR(K34="substantive_inconsistency",K34="minor_presentation",K34="non_inconsistency",K34="indeterminate"))),AND(AND(D34="retain",E34="protocol_report"),L34<>"",NOT(OR(L34="substantive_difference",L34="minor_presentation",L34="version_timing",L34="non_inconsistency",L34="indeterminate")))),"CHECK FIELDS",IF(AND(F34<>"",NOT(OR(F34="no",F34="primary_done"))),"CHECK COMPLETE",IF(F34="primary_done","PRIMARY READY","PRIMARY DRAFT")))))),"CHECK INPUT / KEY") -> PRIMARY READY | H34: confirmed_issue | I34: substantive | R34: TEST 2025::jama.2025.11178::C033
A35: 2025::jama.2025.11178::C034 | B35: Female total differs across sources if the printed derivations are intended to match | C35: main article — PDF p. 1, Abstract; main article — PDF p. 6, Table 1; workbook, worksheet eTable 3, cells A11:B11. | D35: retain | E35: report_internal_inconsistency | F35: primary_done | G35: =IFERROR(IF(LEN(TRIM(CLEAN(SUBSTITUTE(Setup!$B$2,CHAR(160)," "))))=0,"CHECK REVIEWER ID",IF(OR(A35="",(COUNTIF('C_jama.2024.24764'!$A$2:$A$9,A35)+COUNTIF('C_jama.2024.27643'!$A$2:$A$9,A35)+COUNTIF('C_jama.2025.11178'!$A$2:$A$38,A35)+COUNTIF('C_jama.2025.15185'!$A$2:$A$13,A35)+COUNTIF('C_jama.2025.15440'!$A$2:$A$3,A35)+COUNTIF('C_jama.2025.16450'!$A$2:$A$11,A35)+COUNTIF('C_jama.2025.19563'!$A$2:$A$8,A35)+COUNTIF('C_jama.2025.19843'!$A$2:$A$2,A35)+COUNTIF('C_jama.2025.20765'!$A$2:$A$14,A35)+COUNTIF('C_jama.2025.24175'!$A$2:$A$15,A35)+COUNTIF('C_jama.2025.4390'!$A$2:$A$4,A35)+COUNTIF('C_jama.2025.7583'!$A$2:$A$4,A35)+COUNTIF('C_jama.2025.7710'!$A$2:$A$5,A35)+COUNTIF('C_jama.2025.9110'!$A$2:$A$7,A35)+COUNTIF('C_jama.2025.9663'!$A$2:$A$4,A35))<>1,COUNTIFS(Candidates!$G$2:$G$132,A35,Candidates!$K$2:$K$132,"jama.2025.11178")<>1),"CHECK KEY",IF(OR(AND(NOT(AND(D35="retain",E35="statistical_results")),H35<>"",H35<>"not_applicable"),AND(NOT(AND(D35="retain",E35="statistical_results")),I35<>"",I35<>"not_applicable"),AND(NOT(AND(D35="retain",E35="statistical_results")),J35<>"",J35<>"not_applicable"),AND(NOT(AND(D35="retain",OR(E35="report_internal_inconsistency",E35="plan_material"))),K35<>"",K35<>"not_applicable"),AND(NOT(AND(D35="retain",E35="protocol_report")),L35<>"",L35<>"not_applicable")),"CLEAR INACTIVE VALUES",IF(OR(NOT(OR(D35="retain",D35="exclude",D35="discuss")),NOT(OR(E35="statistical_results",E35="report_internal_inconsistency",E35="plan_material",E35="protocol_report")),AND(AND(D35="retain",E35="statistical_results"),NOT(OR(H35="confirmed_issue",H35="probable_issue",H35="not_issue",H35="indeterminate"))),AND(AND(D35="retain",E35="statistical_results"),NOT(OR(I35="substantive",I35="minor_presentation",I35="indeterminate"))),AND(AND(D35="retain",E35="statistical_results"),J35<>"",NOT(OR(J35="direct",J35="possible",J35="unlikely",J35="unknown"))),AND(AND(D35="retain",OR(E35="report_internal_inconsistency",E35="plan_material")),NOT(OR(K35="substantive_inconsistency",K35="minor_presentation",K35="non_inconsistency",K35="indeterminate"))),AND(AND(D35="retain",E35="protocol_report"),L35<>"",NOT(OR(L35="substantive_difference",L35="minor_presentation",L35="version_timing",L35="non_inconsistency",L35="indeterminate")))),"CHECK FIELDS",IF(AND(F35<>"",NOT(OR(F35="no",F35="primary_done"))),"CHECK COMPLETE",IF(F35="primary_done","PRIMARY READY","PRIMARY DRAFT")))))),"CHECK INPUT / KEY") -> PRIMARY READY | K35: substantive_inconsistency | R35: TEST 2025::jama.2025.11178::C034
A36: 2025::jama.2025.11178::C035 | B36: Narrative current-depression percentage differs from Table 1/workbook record | C36: main article — PDF p. 4, Results; main article — PDF p. 6, Table 1; workbook, worksheet eTable 3, cells A82:B82. | D36: retain | E36: report_internal_inconsistency | F36: primary_done | G36: =IFERROR(IF(LEN(TRIM(CLEAN(SUBSTITUTE(Setup!$B$2,CHAR(160)," "))))=0,"CHECK REVIEWER ID",IF(OR(A36="",(COUNTIF('C_jama.2024.24764'!$A$2:$A$9,A36)+COUNTIF('C_jama.2024.27643'!$A$2:$A$9,A36)+COUNTIF('C_jama.2025.11178'!$A$2:$A$38,A36)+COUNTIF('C_jama.2025.15185'!$A$2:$A$13,A36)+COUNTIF('C_jama.2025.15440'!$A$2:$A$3,A36)+COUNTIF('C_jama.2025.16450'!$A$2:$A$11,A36)+COUNTIF('C_jama.2025.19563'!$A$2:$A$8,A36)+COUNTIF('C_jama.2025.19843'!$A$2:$A$2,A36)+COUNTIF('C_jama.2025.20765'!$A$2:$A$14,A36)+COUNTIF('C_jama.2025.24175'!$A$2:$A$15,A36)+COUNTIF('C_jama.2025.4390'!$A$2:$A$4,A36)+COUNTIF('C_jama.2025.7583'!$A$2:$A$4,A36)+COUNTIF('C_jama.2025.7710'!$A$2:$A$5,A36)+COUNTIF('C_jama.2025.9110'!$A$2:$A$7,A36)+COUNTIF('C_jama.2025.9663'!$A$2:$A$4,A36))<>1,COUNTIFS(Candidates!$G$2:$G$132,A36,Candidates!$K$2:$K$132,"jama.2025.11178")<>1),"CHECK KEY",IF(OR(AND(NOT(AND(D36="retain",E36="statistical_results")),H36<>"",H36<>"not_applicable"),AND(NOT(AND(D36="retain",E36="statistical_results")),I36<>"",I36<>"not_applicable"),AND(NOT(AND(D36="retain",E36="statistical_results")),J36<>"",J36<>"not_applicable"),AND(NOT(AND(D36="retain",OR(E36="report_internal_inconsistency",E36="plan_material"))),K36<>"",K36<>"not_applicable"),AND(NOT(AND(D36="retain",E36="protocol_report")),L36<>"",L36<>"not_applicable")),"CLEAR INACTIVE VALUES",IF(OR(NOT(OR(D36="retain",D36="exclude",D36="discuss")),NOT(OR(E36="statistical_results",E36="report_internal_inconsistency",E36="plan_material",E36="protocol_report")),AND(AND(D36="retain",E36="statistical_results"),NOT(OR(H36="confirmed_issue",H36="probable_issue",H36="not_issue",H36="indeterminate"))),AND(AND(D36="retain",E36="statistical_results"),NOT(OR(I36="substantive",I36="minor_presentation",I36="indeterminate"))),AND(AND(D36="retain",E36="statistical_results"),J36<>"",NOT(OR(J36="direct",J36="possible",J36="unlikely",J36="unknown"))),AND(AND(D36="retain",OR(E36="report_internal_inconsistency",E36="plan_material")),NOT(OR(K36="substantive_inconsistency",K36="minor_presentation",K36="non_inconsistency",K36="indeterminate"))),AND(AND(D36="retain",E36="protocol_report"),L36<>"",NOT(OR(L36="substantive_difference",L36="minor_presentation",L36="version_timing",L36="non_inconsistency",L36="indeterminate")))),"CHECK FIELDS",IF(AND(F36<>"",NOT(OR(F36="no",F36="primary_done"))),"CHECK COMPLETE",IF(F36="primary_done","PRIMARY READY","PRIMARY DRAFT")))))),"CHECK INPUT / KEY") -> PRIMARY READY | K36: substantive_inconsistency | R36: TEST 2025::jama.2025.11178::C035
A37: 2025::jama.2025.11178::C036 | B37: painTRAINER 3-month pain-severity SMD differs between narrative and Table 3 | C37: main article — PDF p. 7, Secondary Outcomes; main article — PDF p. 10, Table 3. | D37: retain | E37: report_internal_inconsistency | F37: primary_done | G37: =IFERROR(IF(LEN(TRIM(CLEAN(SUBSTITUTE(Setup!$B$2,CHAR(160)," "))))=0,"CHECK REVIEWER ID",IF(OR(A37="",(COUNTIF('C_jama.2024.24764'!$A$2:$A$9,A37)+COUNTIF('C_jama.2024.27643'!$A$2:$A$9,A37)+COUNTIF('C_jama.2025.11178'!$A$2:$A$38,A37)+COUNTIF('C_jama.2025.15185'!$A$2:$A$13,A37)+COUNTIF('C_jama.2025.15440'!$A$2:$A$3,A37)+COUNTIF('C_jama.2025.16450'!$A$2:$A$11,A37)+COUNTIF('C_jama.2025.19563'!$A$2:$A$8,A37)+COUNTIF('C_jama.2025.19843'!$A$2:$A$2,A37)+COUNTIF('C_jama.2025.20765'!$A$2:$A$14,A37)+COUNTIF('C_jama.2025.24175'!$A$2:$A$15,A37)+COUNTIF('C_jama.2025.4390'!$A$2:$A$4,A37)+COUNTIF('C_jama.2025.7583'!$A$2:$A$4,A37)+COUNTIF('C_jama.2025.7710'!$A$2:$A$5,A37)+COUNTIF('C_jama.2025.9110'!$A$2:$A$7,A37)+COUNTIF('C_jama.2025.9663'!$A$2:$A$4,A37))<>1,COUNTIFS(Candidates!$G$2:$G$132,A37,Candidates!$K$2:$K$132,"jama.2025.11178")<>1),"CHECK KEY",IF(OR(AND(NOT(AND(D37="retain",E37="statistical_results")),H37<>"",H37<>"not_applicable"),AND(NOT(AND(D37="retain",E37="statistical_results")),I37<>"",I37<>"not_applicable"),AND(NOT(AND(D37="retain",E37="statistical_results")),J37<>"",J37<>"not_applicable"),AND(NOT(AND(D37="retain",OR(E37="report_internal_inconsistency",E37="plan_material"))),K37<>"",K37<>"not_applicable"),AND(NOT(AND(D37="retain",E37="protocol_report")),L37<>"",L37<>"not_applicable")),"CLEAR INACTIVE VALUES",IF(OR(NOT(OR(D37="retain",D37="exclude",D37="discuss")),NOT(OR(E37="statistical_results",E37="report_internal_inconsistency",E37="plan_material",E37="protocol_report")),AND(AND(D37="retain",E37="statistical_results"),NOT(OR(H37="confirmed_issue",H37="probable_issue",H37="not_issue",H37="indeterminate"))),AND(AND(D37="retain",E37="statistical_results"),NOT(OR(I37="substantive",I37="minor_presentation",I37="indeterminate"))),AND(AND(D37="retain",E37="statistical_results"),J37<>"",NOT(OR(J37="direct",J37="possible",J37="unlikely",J37="unknown"))),AND(AND(D37="retain",OR(E37="report_internal_inconsistency",E37="plan_material")),NOT(OR(K37="substantive_inconsistency",K37="minor_presentation",K37="non_inconsistency",K37="indeterminate"))),AND(AND(D37="retain",E37="protocol_report"),L37<>"",NOT(OR(L37="substantive_difference",L37="minor_presentation",L37="version_timing",L37="non_inconsistency",L37="indeterminate")))),"CHECK FIELDS",IF(AND(F37<>"",NOT(OR(F37="no",F37="primary_done"))),"CHECK COMPLETE",IF(F37="primary_done","PRIMARY READY","PRIMARY DRAFT")))))),"CHECK INPUT / KEY") -> PRIMARY READY | K37: substantive_inconsistency | R37: TEST 2025::jama.2025.11178::C036
A38: 2025::jama.2025.11178::C037 | B38: Health Coach 3-month pain-severity SMD differs between narrative and Table 3 | C38: main article — PDF p. 7, Secondary Outcomes; main article — PDF p. 10, Table 3. | D38: retain | E38: report_internal_inconsistency | F38: primary_done | G38: =IFERROR(IF(LEN(TRIM(CLEAN(SUBSTITUTE(Setup!$B$2,CHAR(160)," "))))=0,"CHECK REVIEWER ID",IF(OR(A38="",(COUNTIF('C_jama.2024.24764'!$A$2:$A$9,A38)+COUNTIF('C_jama.2024.27643'!$A$2:$A$9,A38)+COUNTIF('C_jama.2025.11178'!$A$2:$A$38,A38)+COUNTIF('C_jama.2025.15185'!$A$2:$A$13,A38)+COUNTIF('C_jama.2025.15440'!$A$2:$A$3,A38)+COUNTIF('C_jama.2025.16450'!$A$2:$A$11,A38)+COUNTIF('C_jama.2025.19563'!$A$2:$A$8,A38)+COUNTIF('C_jama.2025.19843'!$A$2:$A$2,A38)+COUNTIF('C_jama.2025.20765'!$A$2:$A$14,A38)+COUNTIF('C_jama.2025.24175'!$A$2:$A$15,A38)+COUNTIF('C_jama.2025.4390'!$A$2:$A$4,A38)+COUNTIF('C_jama.2025.7583'!$A$2:$A$4,A38)+COUNTIF('C_jama.2025.7710'!$A$2:$A$5,A38)+COUNTIF('C_jama.2025.9110'!$A$2:$A$7,A38)+COUNTIF('C_jama.2025.9663'!$A$2:$A$4,A38))<>1,COUNTIFS(Candidates!$G$2:$G$132,A38,Candidates!$K$2:$K$132,"jama.2025.11178")<>1),"CHECK KEY",IF(OR(AND(NOT(AND(D38="retain",E38="statistical_results")),H38<>"",H38<>"not_applicable"),AND(NOT(AND(D38="retain",E38="statistical_results")),I38<>"",I38<>"not_applicable"),AND(NOT(AND(D38="retain",E38="statistical_results")),J38<>"",J38<>"not_applicable"),AND(NOT(AND(D38="retain",OR(E38="report_internal_inconsistency",E38="plan_material"))),K38<>"",K38<>"not_applicable"),AND(NOT(AND(D38="retain",E38="protocol_report")),L38<>"",L38<>"not_applicable")),"CLEAR INACTIVE VALUES",IF(OR(NOT(OR(D38="retain",D38="exclude",D38="discuss")),NOT(OR(E38="statistical_results",E38="report_internal_inconsistency",E38="plan_material",E38="protocol_report")),AND(AND(D38="retain",E38="statistical_results"),NOT(OR(H38="confirmed_issue",H38="probable_issue",H38="not_issue",H38="indeterminate"))),AND(AND(D38="retain",E38="statistical_results"),NOT(OR(I38="substantive",I38="minor_presentation",I38="indeterminate"))),AND(AND(D38="retain",E38="statistical_results"),J38<>"",NOT(OR(J38="direct",J38="possible",J38="unlikely",J38="unknown"))),AND(AND(D38="retain",OR(E38="report_internal_inconsistency",E38="plan_material")),NOT(OR(K38="substantive_inconsistency",K38="minor_presentation",K38="non_inconsistency",K38="indeterminate"))),AND(AND(D38="retain",E38="protocol_report"),L38<>"",NOT(OR(L38="substantive_difference",L38="minor_presentation",L38="version_timing",L38="non_inconsistency",L38="indeterminate")))),"CHECK FIELDS",IF(AND(F38<>"",NOT(OR(F38="no",F38="primary_done"))),"CHECK COMPLETE",IF(F38="primary_done","PRIMARY READY","PRIMARY DRAFT")))))),"CHECK INPUT / KEY") -> PRIMARY READY | K38: substantive_inconsistency | R38: TEST 2025::jama.2025.11178::C037

Sheet C_jama.2025.15185
A1: Candidate key | B1: Candidate title | C1: Source location | D1: Disposition | E1: Review domain (AI suggestion; editable) | F1: Complete | G1: Validation hint | H1: Statistcal_or_numerical issue | I1: Substantiveness | J1: Downstream impact | K1: Report-internal or planning-material inconsistency | L1: Protocol interpretation | R1: Notes (optional)
A2: 2025::jama.2025.15185::C001 | B2: Baseline index-stroke type counts differ across baseline tables | C2: DOC-001, main article — PDF p. 4, Table 1; DOC-004, Supplement 3 — PDF p. 10 and PDF p. 11, eTable 1. | D2: retain | E2: report_internal_inconsistency | F2: primary_done | G2: =IFERROR(IF(LEN(TRIM(CLEAN(SUBSTITUTE(Setup!$B$2,CHAR(160)," "))))=0,"CHECK REVIEWER ID",IF(OR(A2="",(COUNTIF('C_jama.2024.24764'!$A$2:$A$9,A2)+COUNTIF('C_jama.2024.27643'!$A$2:$A$9,A2)+COUNTIF('C_jama.2025.11178'!$A$2:$A$38,A2)+COUNTIF('C_jama.2025.15185'!$A$2:$A$13,A2)+COUNTIF('C_jama.2025.15440'!$A$2:$A$3,A2)+COUNTIF('C_jama.2025.16450'!$A$2:$A$11,A2)+COUNTIF('C_jama.2025.19563'!$A$2:$A$8,A2)+COUNTIF('C_jama.2025.19843'!$A$2:$A$2,A2)+COUNTIF('C_jama.2025.20765'!$A$2:$A$14,A2)+COUNTIF('C_jama.2025.24175'!$A$2:$A$15,A2)+COUNTIF('C_jama.2025.4390'!$A$2:$A$4,A2)+COUNTIF('C_jama.2025.7583'!$A$2:$A$4,A2)+COUNTIF('C_jama.2025.7710'!$A$2:$A$5,A2)+COUNTIF('C_jama.2025.9110'!$A$2:$A$7,A2)+COUNTIF('C_jama.2025.9663'!$A$2:$A$4,A2))<>1,COUNTIFS(Candidates!$G$2:$G$132,A2,Candidates!$K$2:$K$132,"jama.2025.15185")<>1),"CHECK KEY",IF(OR(AND(NOT(AND(D2="retain",E2="statistical_results")),H2<>"",H2<>"not_applicable"),AND(NOT(AND(D2="retain",E2="statistical_results")),I2<>"",I2<>"not_applicable"),AND(NOT(AND(D2="retain",E2="statistical_results")),J2<>"",J2<>"not_applicable"),AND(NOT(AND(D2="retain",OR(E2="report_internal_inconsistency",E2="plan_material"))),K2<>"",K2<>"not_applicable"),AND(NOT(AND(D2="retain",E2="protocol_report")),L2<>"",L2<>"not_applicable")),"CLEAR INACTIVE VALUES",IF(OR(NOT(OR(D2="retain",D2="exclude",D2="discuss")),NOT(OR(E2="statistical_results",E2="report_internal_inconsistency",E2="plan_material",E2="protocol_report")),AND(AND(D2="retain",E2="statistical_results"),NOT(OR(H2="confirmed_issue",H2="probable_issue",H2="not_issue",H2="indeterminate"))),AND(AND(D2="retain",E2="statistical_results"),NOT(OR(I2="substantive",I2="minor_presentation",I2="indeterminate"))),AND(AND(D2="retain",E2="statistical_results"),J2<>"",NOT(OR(J2="direct",J2="possible",J2="unlikely",J2="unknown"))),AND(AND(D2="retain",OR(E2="report_internal_inconsistency",E2="plan_material")),NOT(OR(K2="substantive_inconsistency",K2="minor_presentation",K2="non_inconsistency",K2="indeterminate"))),AND(AND(D2="retain",E2="protocol_report"),L2<>"",NOT(OR(L2="substantive_difference",L2="minor_presentation",L2="version_timing",L2="non_inconsistency",L2="indeterminate")))),"CHECK FIELDS",IF(AND(F2<>"",NOT(OR(F2="no",F2="primary_done"))),"CHECK COMPLETE",IF(F2="primary_done","PRIMARY READY","PRIMARY DRAFT")))))),"CHECK INPUT / KEY") -> PRIMARY READY | K2: substantive_inconsistency | R2: TEST 2025::jama.2025.15185::C001
A3: 2025::jama.2025.15185::C002 | B3: Baseline NIHSS statistic and label do not reconcile across tables | C3: DOC-001, main article — PDF p. 4, Table 1, and PDF p. 5, Results; DOC-004, Supplement 3 — PDF p. 11, eTable 1. | D3: retain | E3: report_internal_inconsistency | F3: primary_done | G3: =IFERROR(IF(LEN(TRIM(CLEAN(SUBSTITUTE(Setup!$B$2,CHAR(160)," "))))=0,"CHECK REVIEWER ID",IF(OR(A3="",(COUNTIF('C_jama.2024.24764'!$A$2:$A$9,A3)+COUNTIF('C_jama.2024.27643'!$A$2:$A$9,A3)+COUNTIF('C_jama.2025.11178'!$A$2:$A$38,A3)+COUNTIF('C_jama.2025.15185'!$A$2:$A$13,A3)+COUNTIF('C_jama.2025.15440'!$A$2:$A$3,A3)+COUNTIF('C_jama.2025.16450'!$A$2:$A$11,A3)+COUNTIF('C_jama.2025.19563'!$A$2:$A$8,A3)+COUNTIF('C_jama.2025.19843'!$A$2:$A$2,A3)+COUNTIF('C_jama.2025.20765'!$A$2:$A$14,A3)+COUNTIF('C_jama.2025.24175'!$A$2:$A$15,A3)+COUNTIF('C_jama.2025.4390'!$A$2:$A$4,A3)+COUNTIF('C_jama.2025.7583'!$A$2:$A$4,A3)+COUNTIF('C_jama.2025.7710'!$A$2:$A$5,A3)+COUNTIF('C_jama.2025.9110'!$A$2:$A$7,A3)+COUNTIF('C_jama.2025.9663'!$A$2:$A$4,A3))<>1,COUNTIFS(Candidates!$G$2:$G$132,A3,Candidates!$K$2:$K$132,"jama.2025.15185")<>1),"CHECK KEY",IF(OR(AND(NOT(AND(D3="retain",E3="statistical_results")),H3<>"",H3<>"not_applicable"),AND(NOT(AND(D3="retain",E3="statistical_results")),I3<>"",I3<>"not_applicable"),AND(NOT(AND(D3="retain",E3="statistical_results")),J3<>"",J3<>"not_applicable"),AND(NOT(AND(D3="retain",OR(E3="report_internal_inconsistency",E3="plan_material"))),K3<>"",K3<>"not_applicable"),AND(NOT(AND(D3="retain",E3="protocol_report")),L3<>"",L3<>"not_applicable")),"CLEAR INACTIVE VALUES",IF(OR(NOT(OR(D3="retain",D3="exclude",D3="discuss")),NOT(OR(E3="statistical_results",E3="report_internal_inconsistency",E3="plan_material",E3="protocol_report")),AND(AND(D3="retain",E3="statistical_results"),NOT(OR(H3="confirmed_issue",H3="probable_issue",H3="not_issue",H3="indeterminate"))),AND(AND(D3="retain",E3="statistical_results"),NOT(OR(I3="substantive",I3="minor_presentation",I3="indeterminate"))),AND(AND(D3="retain",E3="statistical_results"),J3<>"",NOT(OR(J3="direct",J3="possible",J3="unlikely",J3="unknown"))),AND(AND(D3="retain",OR(E3="report_internal_inconsistency",E3="plan_material")),NOT(OR(K3="substantive_inconsistency",K3="minor_presentation",K3="non_inconsistency",K3="indeterminate"))),AND(AND(D3="retain",E3="protocol_report"),L3<>"",NOT(OR(L3="substantive_difference",L3="minor_presentation",L3="version_timing",L3="non_inconsistency",L3="indeterminate")))),"CHECK FIELDS",IF(AND(F3<>"",NOT(OR(F3="no",F3="primary_done"))),"CHECK COMPLETE",IF(F3="primary_done","PRIMARY READY","PRIMARY DRAFT")))))),"CHECK INPUT / KEY") -> PRIMARY READY | K3: substantive_inconsistency | R3: TEST 2025::jama.2025.15185::C002
A4: 2025::jama.2025.15185::C003 | B4: Time from stroke onset to randomization differs across baseline tables | C4: DOC-001, main article — PDF p. 4, Table 1; DOC-004, Supplement 3 — PDF p. 11, eTable 1. | D4: retain | E4: report_internal_inconsistency | F4: primary_done | G4: =IFERROR(IF(LEN(TRIM(CLEAN(SUBSTITUTE(Setup!$B$2,CHAR(160)," "))))=0,"CHECK REVIEWER ID",IF(OR(A4="",(COUNTIF('C_jama.2024.24764'!$A$2:$A$9,A4)+COUNTIF('C_jama.2024.27643'!$A$2:$A$9,A4)+COUNTIF('C_jama.2025.11178'!$A$2:$A$38,A4)+COUNTIF('C_jama.2025.15185'!$A$2:$A$13,A4)+COUNTIF('C_jama.2025.15440'!$A$2:$A$3,A4)+COUNTIF('C_jama.2025.16450'!$A$2:$A$11,A4)+COUNTIF('C_jama.2025.19563'!$A$2:$A$8,A4)+COUNTIF('C_jama.2025.19843'!$A$2:$A$2,A4)+COUNTIF('C_jama.2025.20765'!$A$2:$A$14,A4)+COUNTIF('C_jama.2025.24175'!$A$2:$A$15,A4)+COUNTIF('C_jama.2025.4390'!$A$2:$A$4,A4)+COUNTIF('C_jama.2025.7583'!$A$2:$A$4,A4)+COUNTIF('C_jama.2025.7710'!$A$2:$A$5,A4)+COUNTIF('C_jama.2025.9110'!$A$2:$A$7,A4)+COUNTIF('C_jama.2025.9663'!$A$2:$A$4,A4))<>1,COUNTIFS(Candidates!$G$2:$G$132,A4,Candidates!$K$2:$K$132,"jama.2025.15185")<>1),"CHECK KEY",IF(OR(AND(NOT(AND(D4="retain",E4="statistical_results")),H4<>"",H4<>"not_applicable"),AND(NOT(AND(D4="retain",E4="statistical_results")),I4<>"",I4<>"not_applicable"),AND(NOT(AND(D4="retain",E4="statistical_results")),J4<>"",J4<>"not_applicable"),AND(NOT(AND(D4="retain",OR(E4="report_internal_inconsistency",E4="plan_material"))),K4<>"",K4<>"not_applicable"),AND(NOT(AND(D4="retain",E4="protocol_report")),L4<>"",L4<>"not_applicable")),"CLEAR INACTIVE VALUES",IF(OR(NOT(OR(D4="retain",D4="exclude",D4="discuss")),NOT(OR(E4="statistical_results",E4="report_internal_inconsistency",E4="plan_material",E4="protocol_report")),AND(AND(D4="retain",E4="statistical_results"),NOT(OR(H4="confirmed_issue",H4="probable_issue",H4="not_issue",H4="indeterminate"))),AND(AND(D4="retain",E4="statistical_results"),NOT(OR(I4="substantive",I4="minor_presentation",I4="indeterminate"))),AND(AND(D4="retain",E4="statistical_results"),J4<>"",NOT(OR(J4="direct",J4="possible",J4="unlikely",J4="unknown"))),AND(AND(D4="retain",OR(E4="report_internal_inconsistency",E4="plan_material")),NOT(OR(K4="substantive_inconsistency",K4="minor_presentation",K4="non_inconsistency",K4="indeterminate"))),AND(AND(D4="retain",E4="protocol_report"),L4<>"",NOT(OR(L4="substantive_difference",L4="minor_presentation",L4="version_timing",L4="non_inconsistency",L4="indeterminate")))),"CHECK FIELDS",IF(AND(F4<>"",NOT(OR(F4="no",F4="primary_done"))),"CHECK COMPLETE",IF(F4="primary_done","PRIMARY READY","PRIMARY DRAFT")))))),"CHECK INPUT / KEY") -> PRIMARY READY | K4: substantive_inconsistency | R4: TEST 2025::jama.2025.15185::C003
A5: 2025::jama.2025.15185::C004 | B5: Estimand 4 confidence-interval upper endpoint differs within eTable 2 | C5: DOC-004, Supplement 3 — PDF p. 12, eTable 2 narrative; PDF p. 13, Estimand 4 row. | D5: retain | E5: statistical_results | F5: primary_done | G5: =IFERROR(IF(LEN(TRIM(CLEAN(SUBSTITUTE(Setup!$B$2,CHAR(160)," "))))=0,"CHECK REVIEWER ID",IF(OR(A5="",(COUNTIF('C_jama.2024.24764'!$A$2:$A$9,A5)+COUNTIF('C_jama.2024.27643'!$A$2:$A$9,A5)+COUNTIF('C_jama.2025.11178'!$A$2:$A$38,A5)+COUNTIF('C_jama.2025.15185'!$A$2:$A$13,A5)+COUNTIF('C_jama.2025.15440'!$A$2:$A$3,A5)+COUNTIF('C_jama.2025.16450'!$A$2:$A$11,A5)+COUNTIF('C_jama.2025.19563'!$A$2:$A$8,A5)+COUNTIF('C_jama.2025.19843'!$A$2:$A$2,A5)+COUNTIF('C_jama.2025.20765'!$A$2:$A$14,A5)+COUNTIF('C_jama.2025.24175'!$A$2:$A$15,A5)+COUNTIF('C_jama.2025.4390'!$A$2:$A$4,A5)+COUNTIF('C_jama.2025.7583'!$A$2:$A$4,A5)+COUNTIF('C_jama.2025.7710'!$A$2:$A$5,A5)+COUNTIF('C_jama.2025.9110'!$A$2:$A$7,A5)+COUNTIF('C_jama.2025.9663'!$A$2:$A$4,A5))<>1,COUNTIFS(Candidates!$G$2:$G$132,A5,Candidates!$K$2:$K$132,"jama.2025.15185")<>1),"CHECK KEY",IF(OR(AND(NOT(AND(D5="retain",E5="statistical_results")),H5<>"",H5<>"not_applicable"),AND(NOT(AND(D5="retain",E5="statistical_results")),I5<>"",I5<>"not_applicable"),AND(NOT(AND(D5="retain",E5="statistical_results")),J5<>"",J5<>"not_applicable"),AND(NOT(AND(D5="retain",OR(E5="report_internal_inconsistency",E5="plan_material"))),K5<>"",K5<>"not_applicable"),AND(NOT(AND(D5="retain",E5="protocol_report")),L5<>"",L5<>"not_applicable")),"CLEAR INACTIVE VALUES",IF(OR(NOT(OR(D5="retain",D5="exclude",D5="discuss")),NOT(OR(E5="statistical_results",E5="report_internal_inconsistency",E5="plan_material",E5="protocol_report")),AND(AND(D5="retain",E5="statistical_results"),NOT(OR(H5="confirmed_issue",H5="probable_issue",H5="not_issue",H5="indeterminate"))),AND(AND(D5="retain",E5="statistical_results"),NOT(OR(I5="substantive",I5="minor_presentation",I5="indeterminate"))),AND(AND(D5="retain",E5="statistical_results"),J5<>"",NOT(OR(J5="direct",J5="possible",J5="unlikely",J5="unknown"))),AND(AND(D5="retain",OR(E5="report_internal_inconsistency",E5="plan_material")),NOT(OR(K5="substantive_inconsistency",K5="minor_presentation",K5="non_inconsistency",K5="indeterminate"))),AND(AND(D5="retain",E5="protocol_report"),L5<>"",NOT(OR(L5="substantive_difference",L5="minor_presentation",L5="version_timing",L5="non_inconsistency",L5="indeterminate")))),"CHECK FIELDS",IF(AND(F5<>"",NOT(OR(F5="no",F5="primary_done"))),"CHECK COMPLETE",IF(F5="primary_done","PRIMARY READY","PRIMARY DRAFT")))))),"CHECK INPUT / KEY") -> PRIMARY READY | H5: confirmed_issue | I5: substantive | R5: TEST 2025::jama.2025.15185::C004
A6: 2025::jama.2025.15185::C005 | B6: Levodopa PROMIS-29 descriptive mean differs between main text and eTable 4 | C6: DOC-001, main article — PDF p. 6, Secondary Outcomes; DOC-004, Supplement 3 — PDF p. 15, eTable 4. | D6: retain | E6: report_internal_inconsistency | F6: primary_done | G6: =IFERROR(IF(LEN(TRIM(CLEAN(SUBSTITUTE(Setup!$B$2,CHAR(160)," "))))=0,"CHECK REVIEWER ID",IF(OR(A6="",(COUNTIF('C_jama.2024.24764'!$A$2:$A$9,A6)+COUNTIF('C_jama.2024.27643'!$A$2:$A$9,A6)+COUNTIF('C_jama.2025.11178'!$A$2:$A$38,A6)+COUNTIF('C_jama.2025.15185'!$A$2:$A$13,A6)+COUNTIF('C_jama.2025.15440'!$A$2:$A$3,A6)+COUNTIF('C_jama.2025.16450'!$A$2:$A$11,A6)+COUNTIF('C_jama.2025.19563'!$A$2:$A$8,A6)+COUNTIF('C_jama.2025.19843'!$A$2:$A$2,A6)+COUNTIF('C_jama.2025.20765'!$A$2:$A$14,A6)+COUNTIF('C_jama.2025.24175'!$A$2:$A$15,A6)+COUNTIF('C_jama.2025.4390'!$A$2:$A$4,A6)+COUNTIF('C_jama.2025.7583'!$A$2:$A$4,A6)+COUNTIF('C_jama.2025.7710'!$A$2:$A$5,A6)+COUNTIF('C_jama.2025.9110'!$A$2:$A$7,A6)+COUNTIF('C_jama.2025.9663'!$A$2:$A$4,A6))<>1,COUNTIFS(Candidates!$G$2:$G$132,A6,Candidates!$K$2:$K$132,"jama.2025.15185")<>1),"CHECK KEY",IF(OR(AND(NOT(AND(D6="retain",E6="statistical_results")),H6<>"",H6<>"not_applicable"),AND(NOT(AND(D6="retain",E6="statistical_results")),I6<>"",I6<>"not_applicable"),AND(NOT(AND(D6="retain",E6="statistical_results")),J6<>"",J6<>"not_applicable"),AND(NOT(AND(D6="retain",OR(E6="report_internal_inconsistency",E6="plan_material"))),K6<>"",K6<>"not_applicable"),AND(NOT(AND(D6="retain",E6="protocol_report")),L6<>"",L6<>"not_applicable")),"CLEAR INACTIVE VALUES",IF(OR(NOT(OR(D6="retain",D6="exclude",D6="discuss")),NOT(OR(E6="statistical_results",E6="report_internal_inconsistency",E6="plan_material",E6="protocol_report")),AND(AND(D6="retain",E6="statistical_results"),NOT(OR(H6="confirmed_issue",H6="probable_issue",H6="not_issue",H6="indeterminate"))),AND(AND(D6="retain",E6="statistical_results"),NOT(OR(I6="substantive",I6="minor_presentation",I6="indeterminate"))),AND(AND(D6="retain",E6="statistical_results"),J6<>"",NOT(OR(J6="direct",J6="possible",J6="unlikely",J6="unknown"))),AND(AND(D6="retain",OR(E6="report_internal_inconsistency",E6="plan_material")),NOT(OR(K6="substantive_inconsistency",K6="minor_presentation",K6="non_inconsistency",K6="indeterminate"))),AND(AND(D6="retain",E6="protocol_report"),L6<>"",NOT(OR(L6="substantive_difference",L6="minor_presentation",L6="version_timing",L6="non_inconsistency",L6="indeterminate")))),"CHECK FIELDS",IF(AND(F6<>"",NOT(OR(F6="no",F6="primary_done"))),"CHECK COMPLETE",IF(F6="primary_done","PRIMARY READY","PRIMARY DRAFT")))))),"CHECK INPUT / KEY") -> PRIMARY READY | K6: substantive_inconsistency | R6: TEST 2025::jama.2025.15185::C005
A7: 2025::jama.2025.15185::C006 | B7: PROMIS-10 descriptive means differ between main text and eTable 4 | C7: DOC-001, main article — PDF p. 6, Secondary Outcomes; DOC-004, Supplement 3 — PDF p. 15, eTable 4. | D7: retain | E7: report_internal_inconsistency | F7: primary_done | G7: =IFERROR(IF(LEN(TRIM(CLEAN(SUBSTITUTE(Setup!$B$2,CHAR(160)," "))))=0,"CHECK REVIEWER ID",IF(OR(A7="",(COUNTIF('C_jama.2024.24764'!$A$2:$A$9,A7)+COUNTIF('C_jama.2024.27643'!$A$2:$A$9,A7)+COUNTIF('C_jama.2025.11178'!$A$2:$A$38,A7)+COUNTIF('C_jama.2025.15185'!$A$2:$A$13,A7)+COUNTIF('C_jama.2025.15440'!$A$2:$A$3,A7)+COUNTIF('C_jama.2025.16450'!$A$2:$A$11,A7)+COUNTIF('C_jama.2025.19563'!$A$2:$A$8,A7)+COUNTIF('C_jama.2025.19843'!$A$2:$A$2,A7)+COUNTIF('C_jama.2025.20765'!$A$2:$A$14,A7)+COUNTIF('C_jama.2025.24175'!$A$2:$A$15,A7)+COUNTIF('C_jama.2025.4390'!$A$2:$A$4,A7)+COUNTIF('C_jama.2025.7583'!$A$2:$A$4,A7)+COUNTIF('C_jama.2025.7710'!$A$2:$A$5,A7)+COUNTIF('C_jama.2025.9110'!$A$2:$A$7,A7)+COUNTIF('C_jama.2025.9663'!$A$2:$A$4,A7))<>1,COUNTIFS(Candidates!$G$2:$G$132,A7,Candidates!$K$2:$K$132,"jama.2025.15185")<>1),"CHECK KEY",IF(OR(AND(NOT(AND(D7="retain",E7="statistical_results")),H7<>"",H7<>"not_applicable"),AND(NOT(AND(D7="retain",E7="statistical_results")),I7<>"",I7<>"not_applicable"),AND(NOT(AND(D7="retain",E7="statistical_results")),J7<>"",J7<>"not_applicable"),AND(NOT(AND(D7="retain",OR(E7="report_internal_inconsistency",E7="plan_material"))),K7<>"",K7<>"not_applicable"),AND(NOT(AND(D7="retain",E7="protocol_report")),L7<>"",L7<>"not_applicable")),"CLEAR INACTIVE VALUES",IF(OR(NOT(OR(D7="retain",D7="exclude",D7="discuss")),NOT(OR(E7="statistical_results",E7="report_internal_inconsistency",E7="plan_material",E7="protocol_report")),AND(AND(D7="retain",E7="statistical_results"),NOT(OR(H7="confirmed_issue",H7="probable_issue",H7="not_issue",H7="indeterminate"))),AND(AND(D7="retain",E7="statistical_results"),NOT(OR(I7="substantive",I7="minor_presentation",I7="indeterminate"))),AND(AND(D7="retain",E7="statistical_results"),J7<>"",NOT(OR(J7="direct",J7="possible",J7="unlikely",J7="unknown"))),AND(AND(D7="retain",OR(E7="report_internal_inconsistency",E7="plan_material")),NOT(OR(K7="substantive_inconsistency",K7="minor_presentation",K7="non_inconsistency",K7="indeterminate"))),AND(AND(D7="retain",E7="protocol_report"),L7<>"",NOT(OR(L7="substantive_difference",L7="minor_presentation",L7="version_timing",L7="non_inconsistency",L7="indeterminate")))),"CHECK FIELDS",IF(AND(F7<>"",NOT(OR(F7="no",F7="primary_done"))),"CHECK COMPLETE",IF(F7="primary_done","PRIMARY READY","PRIMARY DRAFT")))))),"CHECK INPUT / KEY") -> PRIMARY READY | K7: substantive_inconsistency | R7: TEST 2025::jama.2025.15185::C006
A8: 2025::jama.2025.15185::C007 | B8: Placebo five-week FMA standard deviation differs from eTable 4 | C8: DOC-001, main article — PDF p. 6, Secondary Outcomes; DOC-004, Supplement 3 — PDF p. 15, eTable 4. | D8: retain | E8: report_internal_inconsistency | F8: primary_done | G8: =IFERROR(IF(LEN(TRIM(CLEAN(SUBSTITUTE(Setup!$B$2,CHAR(160)," "))))=0,"CHECK REVIEWER ID",IF(OR(A8="",(COUNTIF('C_jama.2024.24764'!$A$2:$A$9,A8)+COUNTIF('C_jama.2024.27643'!$A$2:$A$9,A8)+COUNTIF('C_jama.2025.11178'!$A$2:$A$38,A8)+COUNTIF('C_jama.2025.15185'!$A$2:$A$13,A8)+COUNTIF('C_jama.2025.15440'!$A$2:$A$3,A8)+COUNTIF('C_jama.2025.16450'!$A$2:$A$11,A8)+COUNTIF('C_jama.2025.19563'!$A$2:$A$8,A8)+COUNTIF('C_jama.2025.19843'!$A$2:$A$2,A8)+COUNTIF('C_jama.2025.20765'!$A$2:$A$14,A8)+COUNTIF('C_jama.2025.24175'!$A$2:$A$15,A8)+COUNTIF('C_jama.2025.4390'!$A$2:$A$4,A8)+COUNTIF('C_jama.2025.7583'!$A$2:$A$4,A8)+COUNTIF('C_jama.2025.7710'!$A$2:$A$5,A8)+COUNTIF('C_jama.2025.9110'!$A$2:$A$7,A8)+COUNTIF('C_jama.2025.9663'!$A$2:$A$4,A8))<>1,COUNTIFS(Candidates!$G$2:$G$132,A8,Candidates!$K$2:$K$132,"jama.2025.15185")<>1),"CHECK KEY",IF(OR(AND(NOT(AND(D8="retain",E8="statistical_results")),H8<>"",H8<>"not_applicable"),AND(NOT(AND(D8="retain",E8="statistical_results")),I8<>"",I8<>"not_applicable"),AND(NOT(AND(D8="retain",E8="statistical_results")),J8<>"",J8<>"not_applicable"),AND(NOT(AND(D8="retain",OR(E8="report_internal_inconsistency",E8="plan_material"))),K8<>"",K8<>"not_applicable"),AND(NOT(AND(D8="retain",E8="protocol_report")),L8<>"",L8<>"not_applicable")),"CLEAR INACTIVE VALUES",IF(OR(NOT(OR(D8="retain",D8="exclude",D8="discuss")),NOT(OR(E8="statistical_results",E8="report_internal_inconsistency",E8="plan_material",E8="protocol_report")),AND(AND(D8="retain",E8="statistical_results"),NOT(OR(H8="confirmed_issue",H8="probable_issue",H8="not_issue",H8="indeterminate"))),AND(AND(D8="retain",E8="statistical_results"),NOT(OR(I8="substantive",I8="minor_presentation",I8="indeterminate"))),AND(AND(D8="retain",E8="statistical_results"),J8<>"",NOT(OR(J8="direct",J8="possible",J8="unlikely",J8="unknown"))),AND(AND(D8="retain",OR(E8="report_internal_inconsistency",E8="plan_material")),NOT(OR(K8="substantive_inconsistency",K8="minor_presentation",K8="non_inconsistency",K8="indeterminate"))),AND(AND(D8="retain",E8="protocol_report"),L8<>"",NOT(OR(L8="substantive_difference",L8="minor_presentation",L8="version_timing",L8="non_inconsistency",L8="indeterminate")))),"CHECK FIELDS",IF(AND(F8<>"",NOT(OR(F8="no",F8="primary_done"))),"CHECK COMPLETE",IF(F8="primary_done","PRIMARY READY","PRIMARY DRAFT")))))),"CHECK INPUT / KEY") -> PRIMARY READY | K8: substantive_inconsistency | R8: TEST 2025::jama.2025.15185::C007
A9: 2025::jama.2025.15185::C008 | B9: Placebo PRAI no-improvement numerator differs between main text and eTable 4 | C9: DOC-001, main article — PDF p. 6, Secondary Outcomes; DOC-004, Supplement 3 — PDF p. 15, eTable 4. | D9: retain | E9: report_internal_inconsistency | F9: primary_done | G9: =IFERROR(IF(LEN(TRIM(CLEAN(SUBSTITUTE(Setup!$B$2,CHAR(160)," "))))=0,"CHECK REVIEWER ID",IF(OR(A9="",(COUNTIF('C_jama.2024.24764'!$A$2:$A$9,A9)+COUNTIF('C_jama.2024.27643'!$A$2:$A$9,A9)+COUNTIF('C_jama.2025.11178'!$A$2:$A$38,A9)+COUNTIF('C_jama.2025.15185'!$A$2:$A$13,A9)+COUNTIF('C_jama.2025.15440'!$A$2:$A$3,A9)+COUNTIF('C_jama.2025.16450'!$A$2:$A$11,A9)+COUNTIF('C_jama.2025.19563'!$A$2:$A$8,A9)+COUNTIF('C_jama.2025.19843'!$A$2:$A$2,A9)+COUNTIF('C_jama.2025.20765'!$A$2:$A$14,A9)+COUNTIF('C_jama.2025.24175'!$A$2:$A$15,A9)+COUNTIF('C_jama.2025.4390'!$A$2:$A$4,A9)+COUNTIF('C_jama.2025.7583'!$A$2:$A$4,A9)+COUNTIF('C_jama.2025.7710'!$A$2:$A$5,A9)+COUNTIF('C_jama.2025.9110'!$A$2:$A$7,A9)+COUNTIF('C_jama.2025.9663'!$A$2:$A$4,A9))<>1,COUNTIFS(Candidates!$G$2:$G$132,A9,Candidates!$K$2:$K$132,"jama.2025.15185")<>1),"CHECK KEY",IF(OR(AND(NOT(AND(D9="retain",E9="statistical_results")),H9<>"",H9<>"not_applicable"),AND(NOT(AND(D9="retain",E9="statistical_results")),I9<>"",I9<>"not_applicable"),AND(NOT(AND(D9="retain",E9="statistical_results")),J9<>"",J9<>"not_applicable"),AND(NOT(AND(D9="retain",OR(E9="report_internal_inconsistency",E9="plan_material"))),K9<>"",K9<>"not_applicable"),AND(NOT(AND(D9="retain",E9="protocol_report")),L9<>"",L9<>"not_applicable")),"CLEAR INACTIVE VALUES",IF(OR(NOT(OR(D9="retain",D9="exclude",D9="discuss")),NOT(OR(E9="statistical_results",E9="report_internal_inconsistency",E9="plan_material",E9="protocol_report")),AND(AND(D9="retain",E9="statistical_results"),NOT(OR(H9="confirmed_issue",H9="probable_issue",H9="not_issue",H9="indeterminate"))),AND(AND(D9="retain",E9="statistical_results"),NOT(OR(I9="substantive",I9="minor_presentation",I9="indeterminate"))),AND(AND(D9="retain",E9="statistical_results"),J9<>"",NOT(OR(J9="direct",J9="possible",J9="unlikely",J9="unknown"))),AND(AND(D9="retain",OR(E9="report_internal_inconsistency",E9="plan_material")),NOT(OR(K9="substantive_inconsistency",K9="minor_presentation",K9="non_inconsistency",K9="indeterminate"))),AND(AND(D9="retain",E9="protocol_report"),L9<>"",NOT(OR(L9="substantive_difference",L9="minor_presentation",L9="version_timing",L9="non_inconsistency",L9="indeterminate")))),"CHECK FIELDS",IF(AND(F9<>"",NOT(OR(F9="no",F9="primary_done"))),"CHECK COMPLETE",IF(F9="primary_done","PRIMARY READY","PRIMARY DRAFT")))))),"CHECK INPUT / KEY") -> PRIMARY READY | K9: substantive_inconsistency | R9: TEST 2025::jama.2025.15185::C008
A10: 2025::jama.2025.15185::C009 | B10: eTable 6 overall adverse-event total is one below arms and category sums | C10: DOC-001, main article — PDF p. 6, Table 2 and narrative, and PDF p. 7; DOC-004, Supplement 3 — PDF p. 17, eTable 6. | D10: retain | E10: statistical_results | F10: primary_done | G10: =IFERROR(IF(LEN(TRIM(CLEAN(SUBSTITUTE(Setup!$B$2,CHAR(160)," "))))=0,"CHECK REVIEWER ID",IF(OR(A10="",(COUNTIF('C_jama.2024.24764'!$A$2:$A$9,A10)+COUNTIF('C_jama.2024.27643'!$A$2:$A$9,A10)+COUNTIF('C_jama.2025.11178'!$A$2:$A$38,A10)+COUNTIF('C_jama.2025.15185'!$A$2:$A$13,A10)+COUNTIF('C_jama.2025.15440'!$A$2:$A$3,A10)+COUNTIF('C_jama.2025.16450'!$A$2:$A$11,A10)+COUNTIF('C_jama.2025.19563'!$A$2:$A$8,A10)+COUNTIF('C_jama.2025.19843'!$A$2:$A$2,A10)+COUNTIF('C_jama.2025.20765'!$A$2:$A$14,A10)+COUNTIF('C_jama.2025.24175'!$A$2:$A$15,A10)+COUNTIF('C_jama.2025.4390'!$A$2:$A$4,A10)+COUNTIF('C_jama.2025.7583'!$A$2:$A$4,A10)+COUNTIF('C_jama.2025.7710'!$A$2:$A$5,A10)+COUNTIF('C_jama.2025.9110'!$A$2:$A$7,A10)+COUNTIF('C_jama.2025.9663'!$A$2:$A$4,A10))<>1,COUNTIFS(Candidates!$G$2:$G$132,A10,Candidates!$K$2:$K$132,"jama.2025.15185")<>1),"CHECK KEY",IF(OR(AND(NOT(AND(D10="retain",E10="statistical_results")),H10<>"",H10<>"not_applicable"),AND(NOT(AND(D10="retain",E10="statistical_results")),I10<>"",I10<>"not_applicable"),AND(NOT(AND(D10="retain",E10="statistical_results")),J10<>"",J10<>"not_applicable"),AND(NOT(AND(D10="retain",OR(E10="report_internal_inconsistency",E10="plan_material"))),K10<>"",K10<>"not_applicable"),AND(NOT(AND(D10="retain",E10="protocol_report")),L10<>"",L10<>"not_applicable")),"CLEAR INACTIVE VALUES",IF(OR(NOT(OR(D10="retain",D10="exclude",D10="discuss")),NOT(OR(E10="statistical_results",E10="report_internal_inconsistency",E10="plan_material",E10="protocol_report")),AND(AND(D10="retain",E10="statistical_results"),NOT(OR(H10="confirmed_issue",H10="probable_issue",H10="not_issue",H10="indeterminate"))),AND(AND(D10="retain",E10="statistical_results"),NOT(OR(I10="substantive",I10="minor_presentation",I10="indeterminate"))),AND(AND(D10="retain",E10="statistical_results"),J10<>"",NOT(OR(J10="direct",J10="possible",J10="unlikely",J10="unknown"))),AND(AND(D10="retain",OR(E10="report_internal_inconsistency",E10="plan_material")),NOT(OR(K10="substantive_inconsistency",K10="minor_presentation",K10="non_inconsistency",K10="indeterminate"))),AND(AND(D10="retain",E10="protocol_report"),L10<>"",NOT(OR(L10="substantive_difference",L10="minor_presentation",L10="version_timing",L10="non_inconsistency",L10="indeterminate")))),"CHECK FIELDS",IF(AND(F10<>"",NOT(OR(F10="no",F10="primary_done"))),"CHECK COMPLETE",IF(F10="primary_done","PRIMARY READY","PRIMARY DRAFT")))))),"CHECK INPUT / KEY") -> PRIMARY READY | H10: confirmed_issue | I10: substantive | R10: TEST 2025::jama.2025.15185::C009
A11: 2025::jama.2025.15185::C010 | B11: eFigure 4 switches locally from FMA to FMMA without qualification | C11: DOC-004, Supplement 3 — PDF p. 23, eFigure 4; DOC-003, Supplement 2 — PDF p. 2, SAP objective; DOC-001, main article — PDF p. 1, PDF p. 3, and PDF p. 6. | D11: retain | E11: report_internal_inconsistency | F11: primary_done | G11: =IFERROR(IF(LEN(TRIM(CLEAN(SUBSTITUTE(Setup!$B$2,CHAR(160)," "))))=0,"CHECK REVIEWER ID",IF(OR(A11="",(COUNTIF('C_jama.2024.24764'!$A$2:$A$9,A11)+COUNTIF('C_jama.2024.27643'!$A$2:$A$9,A11)+COUNTIF('C_jama.2025.11178'!$A$2:$A$38,A11)+COUNTIF('C_jama.2025.15185'!$A$2:$A$13,A11)+COUNTIF('C_jama.2025.15440'!$A$2:$A$3,A11)+COUNTIF('C_jama.2025.16450'!$A$2:$A$11,A11)+COUNTIF('C_jama.2025.19563'!$A$2:$A$8,A11)+COUNTIF('C_jama.2025.19843'!$A$2:$A$2,A11)+COUNTIF('C_jama.2025.20765'!$A$2:$A$14,A11)+COUNTIF('C_jama.2025.24175'!$A$2:$A$15,A11)+COUNTIF('C_jama.2025.4390'!$A$2:$A$4,A11)+COUNTIF('C_jama.2025.7583'!$A$2:$A$4,A11)+COUNTIF('C_jama.2025.7710'!$A$2:$A$5,A11)+COUNTIF('C_jama.2025.9110'!$A$2:$A$7,A11)+COUNTIF('C_jama.2025.9663'!$A$2:$A$4,A11))<>1,COUNTIFS(Candidates!$G$2:$G$132,A11,Candidates!$K$2:$K$132,"jama.2025.15185")<>1),"CHECK KEY",IF(OR(AND(NOT(AND(D11="retain",E11="statistical_results")),H11<>"",H11<>"not_applicable"),AND(NOT(AND(D11="retain",E11="statistical_results")),I11<>"",I11<>"not_applicable"),AND(NOT(AND(D11="retain",E11="statistical_results")),J11<>"",J11<>"not_applicable"),AND(NOT(AND(D11="retain",OR(E11="report_internal_inconsistency",E11="plan_material"))),K11<>"",K11<>"not_applicable"),AND(NOT(AND(D11="retain",E11="protocol_report")),L11<>"",L11<>"not_applicable")),"CLEAR INACTIVE VALUES",IF(OR(NOT(OR(D11="retain",D11="exclude",D11="discuss")),NOT(OR(E11="statistical_results",E11="report_internal_inconsistency",E11="plan_material",E11="protocol_report")),AND(AND(D11="retain",E11="statistical_results"),NOT(OR(H11="confirmed_issue",H11="probable_issue",H11="not_issue",H11="indeterminate"))),AND(AND(D11="retain",E11="statistical_results"),NOT(OR(I11="substantive",I11="minor_presentation",I11="indeterminate"))),AND(AND(D11="retain",E11="statistical_results"),J11<>"",NOT(OR(J11="direct",J11="possible",J11="unlikely",J11="unknown"))),AND(AND(D11="retain",OR(E11="report_internal_inconsistency",E11="plan_material")),NOT(OR(K11="substantive_inconsistency",K11="minor_presentation",K11="non_inconsistency",K11="indeterminate"))),AND(AND(D11="retain",E11="protocol_report"),L11<>"",NOT(OR(L11="substantive_difference",L11="minor_presentation",L11="version_timing",L11="non_inconsistency",L11="indeterminate")))),"CHECK FIELDS",IF(AND(F11<>"",NOT(OR(F11="no",F11="primary_done"))),"CHECK COMPLETE",IF(F11="primary_done","PRIMARY READY","PRIMARY DRAFT")))))),"CHECK INPUT / KEY") -> PRIMARY READY | K11: substantive_inconsistency | R11: TEST 2025::jama.2025.15185::C010
A12: 2025::jama.2025.15185::C011 | B12: Estimand 4 win ratio appears under an FMA mean-difference column heading | C12: DOC-004, Supplement 3 — PDF p. 13, eTable 2 column heading and Estimand 4 row. | D12: retain | E12: report_internal_inconsistency | F12: primary_done | G12: =IFERROR(IF(LEN(TRIM(CLEAN(SUBSTITUTE(Setup!$B$2,CHAR(160)," "))))=0,"CHECK REVIEWER ID",IF(OR(A12="",(COUNTIF('C_jama.2024.24764'!$A$2:$A$9,A12)+COUNTIF('C_jama.2024.27643'!$A$2:$A$9,A12)+COUNTIF('C_jama.2025.11178'!$A$2:$A$38,A12)+COUNTIF('C_jama.2025.15185'!$A$2:$A$13,A12)+COUNTIF('C_jama.2025.15440'!$A$2:$A$3,A12)+COUNTIF('C_jama.2025.16450'!$A$2:$A$11,A12)+COUNTIF('C_jama.2025.19563'!$A$2:$A$8,A12)+COUNTIF('C_jama.2025.19843'!$A$2:$A$2,A12)+COUNTIF('C_jama.2025.20765'!$A$2:$A$14,A12)+COUNTIF('C_jama.2025.24175'!$A$2:$A$15,A12)+COUNTIF('C_jama.2025.4390'!$A$2:$A$4,A12)+COUNTIF('C_jama.2025.7583'!$A$2:$A$4,A12)+COUNTIF('C_jama.2025.7710'!$A$2:$A$5,A12)+COUNTIF('C_jama.2025.9110'!$A$2:$A$7,A12)+COUNTIF('C_jama.2025.9663'!$A$2:$A$4,A12))<>1,COUNTIFS(Candidates!$G$2:$G$132,A12,Candidates!$K$2:$K$132,"jama.2025.15185")<>1),"CHECK KEY",IF(OR(AND(NOT(AND(D12="retain",E12="statistical_results")),H12<>"",H12<>"not_applicable"),AND(NOT(AND(D12="retain",E12="statistical_results")),I12<>"",I12<>"not_applicable"),AND(NOT(AND(D12="retain",E12="statistical_results")),J12<>"",J12<>"not_applicable"),AND(NOT(AND(D12="retain",OR(E12="report_internal_inconsistency",E12="plan_material"))),K12<>"",K12<>"not_applicable"),AND(NOT(AND(D12="retain",E12="protocol_report")),L12<>"",L12<>"not_applicable")),"CLEAR INACTIVE VALUES",IF(OR(NOT(OR(D12="retain",D12="exclude",D12="discuss")),NOT(OR(E12="statistical_results",E12="report_internal_inconsistency",E12="plan_material",E12="protocol_report")),AND(AND(D12="retain",E12="statistical_results"),NOT(OR(H12="confirmed_issue",H12="probable_issue",H12="not_issue",H12="indeterminate"))),AND(AND(D12="retain",E12="statistical_results"),NOT(OR(I12="substantive",I12="minor_presentation",I12="indeterminate"))),AND(AND(D12="retain",E12="statistical_results"),J12<>"",NOT(OR(J12="direct",J12="possible",J12="unlikely",J12="unknown"))),AND(AND(D12="retain",OR(E12="report_internal_inconsistency",E12="plan_material")),NOT(OR(K12="substantive_inconsistency",K12="minor_presentation",K12="non_inconsistency",K12="indeterminate"))),AND(AND(D12="retain",E12="protocol_report"),L12<>"",NOT(OR(L12="substantive_difference",L12="minor_presentation",L12="version_timing",L12="non_inconsistency",L12="indeterminate")))),"CHECK FIELDS",IF(AND(F12<>"",NOT(OR(F12="no",F12="primary_done"))),"CHECK COMPLETE",IF(F12="primary_done","PRIMARY READY","PRIMARY DRAFT")))))),"CHECK INPUT / KEY") -> PRIMARY READY | K12: substantive_inconsistency | R12: TEST 2025::jama.2025.15185::C011
A13: 2025::jama.2025.15185::C012 | B13: Estimand 4 is called an odds ratio in prose and a win ratio in the table | C13: DOC-004, Supplement 3 — PDF p. 12, eTable 2 narrative; PDF p. 13, Estimand 4 row. | D13: retain | E13: report_internal_inconsistency | F13: primary_done | G13: =IFERROR(IF(LEN(TRIM(CLEAN(SUBSTITUTE(Setup!$B$2,CHAR(160)," "))))=0,"CHECK REVIEWER ID",IF(OR(A13="",(COUNTIF('C_jama.2024.24764'!$A$2:$A$9,A13)+COUNTIF('C_jama.2024.27643'!$A$2:$A$9,A13)+COUNTIF('C_jama.2025.11178'!$A$2:$A$38,A13)+COUNTIF('C_jama.2025.15185'!$A$2:$A$13,A13)+COUNTIF('C_jama.2025.15440'!$A$2:$A$3,A13)+COUNTIF('C_jama.2025.16450'!$A$2:$A$11,A13)+COUNTIF('C_jama.2025.19563'!$A$2:$A$8,A13)+COUNTIF('C_jama.2025.19843'!$A$2:$A$2,A13)+COUNTIF('C_jama.2025.20765'!$A$2:$A$14,A13)+COUNTIF('C_jama.2025.24175'!$A$2:$A$15,A13)+COUNTIF('C_jama.2025.4390'!$A$2:$A$4,A13)+COUNTIF('C_jama.2025.7583'!$A$2:$A$4,A13)+COUNTIF('C_jama.2025.7710'!$A$2:$A$5,A13)+COUNTIF('C_jama.2025.9110'!$A$2:$A$7,A13)+COUNTIF('C_jama.2025.9663'!$A$2:$A$4,A13))<>1,COUNTIFS(Candidates!$G$2:$G$132,A13,Candidates!$K$2:$K$132,"jama.2025.15185")<>1),"CHECK KEY",IF(OR(AND(NOT(AND(D13="retain",E13="statistical_results")),H13<>"",H13<>"not_applicable"),AND(NOT(AND(D13="retain",E13="statistical_results")),I13<>"",I13<>"not_applicable"),AND(NOT(AND(D13="retain",E13="statistical_results")),J13<>"",J13<>"not_applicable"),AND(NOT(AND(D13="retain",OR(E13="report_internal_inconsistency",E13="plan_material"))),K13<>"",K13<>"not_applicable"),AND(NOT(AND(D13="retain",E13="protocol_report")),L13<>"",L13<>"not_applicable")),"CLEAR INACTIVE VALUES",IF(OR(NOT(OR(D13="retain",D13="exclude",D13="discuss")),NOT(OR(E13="statistical_results",E13="report_internal_inconsistency",E13="plan_material",E13="protocol_report")),AND(AND(D13="retain",E13="statistical_results"),NOT(OR(H13="confirmed_issue",H13="probable_issue",H13="not_issue",H13="indeterminate"))),AND(AND(D13="retain",E13="statistical_results"),NOT(OR(I13="substantive",I13="minor_presentation",I13="indeterminate"))),AND(AND(D13="retain",E13="statistical_results"),J13<>"",NOT(OR(J13="direct",J13="possible",J13="unlikely",J13="unknown"))),AND(AND(D13="retain",OR(E13="report_internal_inconsistency",E13="plan_material")),NOT(OR(K13="substantive_inconsistency",K13="minor_presentation",K13="non_inconsistency",K13="indeterminate"))),AND(AND(D13="retain",E13="protocol_report"),L13<>"",NOT(OR(L13="substantive_difference",L13="minor_presentation",L13="version_timing",L13="non_inconsistency",L13="indeterminate")))),"CHECK FIELDS",IF(AND(F13<>"",NOT(OR(F13="no",F13="primary_done"))),"CHECK COMPLETE",IF(F13="primary_done","PRIMARY READY","PRIMARY DRAFT")))))),"CHECK INPUT / KEY") -> PRIMARY READY | K13: substantive_inconsistency | R13: TEST 2025::jama.2025.15185::C012

Sheet C_jama.2025.15440
A1: Candidate key | B1: Candidate title | C1: Source location | D1: Disposition | E1: Review domain (AI suggestion; editable) | F1: Complete | G1: Validation hint | H1: Statistcal_or_numerical issue | I1: Substantiveness | J1: Downstream impact | K1: Report-internal or planning-material inconsistency | L1: Protocol interpretation | R1: Notes (optional)
A2: 2025::jama.2025.15440::C001 | B2: Conflicting confidence intervals for the matched any-stroke rate ratio | C2: DOC-001: jama_wijesurendra_2025_oi_250068_1760999665.28362.pdf — PDF p. 1 (abstract); PDF p. 5 (results narrative); and PDF p. 7 (Figure 4B). | D2: retain | E2: report_internal_inconsistency | F2: primary_done | G2: =IFERROR(IF(LEN(TRIM(CLEAN(SUBSTITUTE(Setup!$B$2,CHAR(160)," "))))=0,"CHECK REVIEWER ID",IF(OR(A2="",(COUNTIF('C_jama.2024.24764'!$A$2:$A$9,A2)+COUNTIF('C_jama.2024.27643'!$A$2:$A$9,A2)+COUNTIF('C_jama.2025.11178'!$A$2:$A$38,A2)+COUNTIF('C_jama.2025.15185'!$A$2:$A$13,A2)+COUNTIF('C_jama.2025.15440'!$A$2:$A$3,A2)+COUNTIF('C_jama.2025.16450'!$A$2:$A$11,A2)+COUNTIF('C_jama.2025.19563'!$A$2:$A$8,A2)+COUNTIF('C_jama.2025.19843'!$A$2:$A$2,A2)+COUNTIF('C_jama.2025.20765'!$A$2:$A$14,A2)+COUNTIF('C_jama.2025.24175'!$A$2:$A$15,A2)+COUNTIF('C_jama.2025.4390'!$A$2:$A$4,A2)+COUNTIF('C_jama.2025.7583'!$A$2:$A$4,A2)+COUNTIF('C_jama.2025.7710'!$A$2:$A$5,A2)+COUNTIF('C_jama.2025.9110'!$A$2:$A$7,A2)+COUNTIF('C_jama.2025.9663'!$A$2:$A$4,A2))<>1,COUNTIFS(Candidates!$G$2:$G$132,A2,Candidates!$K$2:$K$132,"jama.2025.15440")<>1),"CHECK KEY",IF(OR(AND(NOT(AND(D2="retain",E2="statistical_results")),H2<>"",H2<>"not_applicable"),AND(NOT(AND(D2="retain",E2="statistical_results")),I2<>"",I2<>"not_applicable"),AND(NOT(AND(D2="retain",E2="statistical_results")),J2<>"",J2<>"not_applicable"),AND(NOT(AND(D2="retain",OR(E2="report_internal_inconsistency",E2="plan_material"))),K2<>"",K2<>"not_applicable"),AND(NOT(AND(D2="retain",E2="protocol_report")),L2<>"",L2<>"not_applicable")),"CLEAR INACTIVE VALUES",IF(OR(NOT(OR(D2="retain",D2="exclude",D2="discuss")),NOT(OR(E2="statistical_results",E2="report_internal_inconsistency",E2="plan_material",E2="protocol_report")),AND(AND(D2="retain",E2="statistical_results"),NOT(OR(H2="confirmed_issue",H2="probable_issue",H2="not_issue",H2="indeterminate"))),AND(AND(D2="retain",E2="statistical_results"),NOT(OR(I2="substantive",I2="minor_presentation",I2="indeterminate"))),AND(AND(D2="retain",E2="statistical_results"),J2<>"",NOT(OR(J2="direct",J2="possible",J2="unlikely",J2="unknown"))),AND(AND(D2="retain",OR(E2="report_internal_inconsistency",E2="plan_material")),NOT(OR(K2="substantive_inconsistency",K2="minor_presentation",K2="non_inconsistency",K2="indeterminate"))),AND(AND(D2="retain",E2="protocol_report"),L2<>"",NOT(OR(L2="substantive_difference",L2="minor_presentation",L2="version_timing",L2="non_inconsistency",L2="indeterminate")))),"CHECK FIELDS",IF(AND(F2<>"",NOT(OR(F2="no",F2="primary_done"))),"CHECK COMPLETE",IF(F2="primary_done","PRIMARY READY","PRIMARY DRAFT")))))),"CHECK INPUT / KEY") -> PRIMARY READY | K2: substantive_inconsistency | R2: TEST 2025::jama.2025.15440::C001
A3: 2025::jama.2025.15440::C002 | B3: Stroke subtype counts do not partition the displayed any-stroke count in the patch group | C3: DOC-001: jama_wijesurendra_2025_oi_250068_1760999665.28362.pdf — PDF p. 7, Figure 4B rows Presumed ischemic stroke, Hemorrhagic stroke, and Any stroke, including its caption/footnote. The matching any-stroke total also appears on PDF p. 5 and PDF p. 1. | D3: retain | E3: statistical_results | F3: primary_done | G3: =IFERROR(IF(LEN(TRIM(CLEAN(SUBSTITUTE(Setup!$B$2,CHAR(160)," "))))=0,"CHECK REVIEWER ID",IF(OR(A3="",(COUNTIF('C_jama.2024.24764'!$A$2:$A$9,A3)+COUNTIF('C_jama.2024.27643'!$A$2:$A$9,A3)+COUNTIF('C_jama.2025.11178'!$A$2:$A$38,A3)+COUNTIF('C_jama.2025.15185'!$A$2:$A$13,A3)+COUNTIF('C_jama.2025.15440'!$A$2:$A$3,A3)+COUNTIF('C_jama.2025.16450'!$A$2:$A$11,A3)+COUNTIF('C_jama.2025.19563'!$A$2:$A$8,A3)+COUNTIF('C_jama.2025.19843'!$A$2:$A$2,A3)+COUNTIF('C_jama.2025.20765'!$A$2:$A$14,A3)+COUNTIF('C_jama.2025.24175'!$A$2:$A$15,A3)+COUNTIF('C_jama.2025.4390'!$A$2:$A$4,A3)+COUNTIF('C_jama.2025.7583'!$A$2:$A$4,A3)+COUNTIF('C_jama.2025.7710'!$A$2:$A$5,A3)+COUNTIF('C_jama.2025.9110'!$A$2:$A$7,A3)+COUNTIF('C_jama.2025.9663'!$A$2:$A$4,A3))<>1,COUNTIFS(Candidates!$G$2:$G$132,A3,Candidates!$K$2:$K$132,"jama.2025.15440")<>1),"CHECK KEY",IF(OR(AND(NOT(AND(D3="retain",E3="statistical_results")),H3<>"",H3<>"not_applicable"),AND(NOT(AND(D3="retain",E3="statistical_results")),I3<>"",I3<>"not_applicable"),AND(NOT(AND(D3="retain",E3="statistical_results")),J3<>"",J3<>"not_applicable"),AND(NOT(AND(D3="retain",OR(E3="report_internal_inconsistency",E3="plan_material"))),K3<>"",K3<>"not_applicable"),AND(NOT(AND(D3="retain",E3="protocol_report")),L3<>"",L3<>"not_applicable")),"CLEAR INACTIVE VALUES",IF(OR(NOT(OR(D3="retain",D3="exclude",D3="discuss")),NOT(OR(E3="statistical_results",E3="report_internal_inconsistency",E3="plan_material",E3="protocol_report")),AND(AND(D3="retain",E3="statistical_results"),NOT(OR(H3="confirmed_issue",H3="probable_issue",H3="not_issue",H3="indeterminate"))),AND(AND(D3="retain",E3="statistical_results"),NOT(OR(I3="substantive",I3="minor_presentation",I3="indeterminate"))),AND(AND(D3="retain",E3="statistical_results"),J3<>"",NOT(OR(J3="direct",J3="possible",J3="unlikely",J3="unknown"))),AND(AND(D3="retain",OR(E3="report_internal_inconsistency",E3="plan_material")),NOT(OR(K3="substantive_inconsistency",K3="minor_presentation",K3="non_inconsistency",K3="indeterminate"))),AND(AND(D3="retain",E3="protocol_report"),L3<>"",NOT(OR(L3="substantive_difference",L3="minor_presentation",L3="version_timing",L3="non_inconsistency",L3="indeterminate")))),"CHECK FIELDS",IF(AND(F3<>"",NOT(OR(F3="no",F3="primary_done"))),"CHECK COMPLETE",IF(F3="primary_done","PRIMARY READY","PRIMARY DRAFT")))))),"CHECK INPUT / KEY") -> PRIMARY READY | H3: confirmed_issue | I3: substantive | R3: TEST 2025::jama.2025.15440::C002

Sheet C_jama.2025.16450
A1: Candidate key | B1: Candidate title | C1: Source location | D1: Disposition | E1: Review domain (AI suggestion; editable) | F1: Complete | G1: Validation hint | H1: Statistcal_or_numerical issue | I1: Substantiveness | J1: Downstream impact | K1: Report-internal or planning-material inconsistency | L1: Protocol interpretation | R1: Notes (optional)
A2: 2025::jama.2025.16450::C001 | B2: eTable 4 expands RR as risk difference although the table reports relative risk | C2: DOC-005 results supplement — PDF p. 7 (eTable 4 header and PDA row); results supplement — PDF p. 8 (abbreviations and binary-outcome model text). | D2: retain | E2: report_internal_inconsistency | F2: primary_done | G2: =IFERROR(IF(LEN(TRIM(CLEAN(SUBSTITUTE(Setup!$B$2,CHAR(160)," "))))=0,"CHECK REVIEWER ID",IF(OR(A2="",(COUNTIF('C_jama.2024.24764'!$A$2:$A$9,A2)+COUNTIF('C_jama.2024.27643'!$A$2:$A$9,A2)+COUNTIF('C_jama.2025.11178'!$A$2:$A$38,A2)+COUNTIF('C_jama.2025.15185'!$A$2:$A$13,A2)+COUNTIF('C_jama.2025.15440'!$A$2:$A$3,A2)+COUNTIF('C_jama.2025.16450'!$A$2:$A$11,A2)+COUNTIF('C_jama.2025.19563'!$A$2:$A$8,A2)+COUNTIF('C_jama.2025.19843'!$A$2:$A$2,A2)+COUNTIF('C_jama.2025.20765'!$A$2:$A$14,A2)+COUNTIF('C_jama.2025.24175'!$A$2:$A$15,A2)+COUNTIF('C_jama.2025.4390'!$A$2:$A$4,A2)+COUNTIF('C_jama.2025.7583'!$A$2:$A$4,A2)+COUNTIF('C_jama.2025.7710'!$A$2:$A$5,A2)+COUNTIF('C_jama.2025.9110'!$A$2:$A$7,A2)+COUNTIF('C_jama.2025.9663'!$A$2:$A$4,A2))<>1,COUNTIFS(Candidates!$G$2:$G$132,A2,Candidates!$K$2:$K$132,"jama.2025.16450")<>1),"CHECK KEY",IF(OR(AND(NOT(AND(D2="retain",E2="statistical_results")),H2<>"",H2<>"not_applicable"),AND(NOT(AND(D2="retain",E2="statistical_results")),I2<>"",I2<>"not_applicable"),AND(NOT(AND(D2="retain",E2="statistical_results")),J2<>"",J2<>"not_applicable"),AND(NOT(AND(D2="retain",OR(E2="report_internal_inconsistency",E2="plan_material"))),K2<>"",K2<>"not_applicable"),AND(NOT(AND(D2="retain",E2="protocol_report")),L2<>"",L2<>"not_applicable")),"CLEAR INACTIVE VALUES",IF(OR(NOT(OR(D2="retain",D2="exclude",D2="discuss")),NOT(OR(E2="statistical_results",E2="report_internal_inconsistency",E2="plan_material",E2="protocol_report")),AND(AND(D2="retain",E2="statistical_results"),NOT(OR(H2="confirmed_issue",H2="probable_issue",H2="not_issue",H2="indeterminate"))),AND(AND(D2="retain",E2="statistical_results"),NOT(OR(I2="substantive",I2="minor_presentation",I2="indeterminate"))),AND(AND(D2="retain",E2="statistical_results"),J2<>"",NOT(OR(J2="direct",J2="possible",J2="unlikely",J2="unknown"))),AND(AND(D2="retain",OR(E2="report_internal_inconsistency",E2="plan_material")),NOT(OR(K2="substantive_inconsistency",K2="minor_presentation",K2="non_inconsistency",K2="indeterminate"))),AND(AND(D2="retain",E2="protocol_report"),L2<>"",NOT(OR(L2="substantive_difference",L2="minor_presentation",L2="version_timing",L2="non_inconsistency",L2="indeterminate")))),"CHECK FIELDS",IF(AND(F2<>"",NOT(OR(F2="no",F2="primary_done"))),"CHECK COMPLETE",IF(F2="primary_done","PRIMARY READY","PRIMARY DRAFT")))))),"CHECK INPUT / KEY") -> PRIMARY READY | K2: substantive_inconsistency | R2: TEST 2025::jama.2025.16450::C001
A3: 2025::jama.2025.16450::C002 | B3: Registered eligibility-bound discrepancy is not reproduced on direct-source recheck | C3: DOC-002 protocol — PDF p. 4; DOC-003 manual — PDF p. 7; DOC-004 SAP — PDF p. 8 and SAP — PDF p. 15; DOC-001 main article — PDF p. 2. | D3: retain | E3: protocol_report | F3: primary_done | G3: =IFERROR(IF(LEN(TRIM(CLEAN(SUBSTITUTE(Setup!$B$2,CHAR(160)," "))))=0,"CHECK REVIEWER ID",IF(OR(A3="",(COUNTIF('C_jama.2024.24764'!$A$2:$A$9,A3)+COUNTIF('C_jama.2024.27643'!$A$2:$A$9,A3)+COUNTIF('C_jama.2025.11178'!$A$2:$A$38,A3)+COUNTIF('C_jama.2025.15185'!$A$2:$A$13,A3)+COUNTIF('C_jama.2025.15440'!$A$2:$A$3,A3)+COUNTIF('C_jama.2025.16450'!$A$2:$A$11,A3)+COUNTIF('C_jama.2025.19563'!$A$2:$A$8,A3)+COUNTIF('C_jama.2025.19843'!$A$2:$A$2,A3)+COUNTIF('C_jama.2025.20765'!$A$2:$A$14,A3)+COUNTIF('C_jama.2025.24175'!$A$2:$A$15,A3)+COUNTIF('C_jama.2025.4390'!$A$2:$A$4,A3)+COUNTIF('C_jama.2025.7583'!$A$2:$A$4,A3)+COUNTIF('C_jama.2025.7710'!$A$2:$A$5,A3)+COUNTIF('C_jama.2025.9110'!$A$2:$A$7,A3)+COUNTIF('C_jama.2025.9663'!$A$2:$A$4,A3))<>1,COUNTIFS(Candidates!$G$2:$G$132,A3,Candidates!$K$2:$K$132,"jama.2025.16450")<>1),"CHECK KEY",IF(OR(AND(NOT(AND(D3="retain",E3="statistical_results")),H3<>"",H3<>"not_applicable"),AND(NOT(AND(D3="retain",E3="statistical_results")),I3<>"",I3<>"not_applicable"),AND(NOT(AND(D3="retain",E3="statistical_results")),J3<>"",J3<>"not_applicable"),AND(NOT(AND(D3="retain",OR(E3="report_internal_inconsistency",E3="plan_material"))),K3<>"",K3<>"not_applicable"),AND(NOT(AND(D3="retain",E3="protocol_report")),L3<>"",L3<>"not_applicable")),"CLEAR INACTIVE VALUES",IF(OR(NOT(OR(D3="retain",D3="exclude",D3="discuss")),NOT(OR(E3="statistical_results",E3="report_internal_inconsistency",E3="plan_material",E3="protocol_report")),AND(AND(D3="retain",E3="statistical_results"),NOT(OR(H3="confirmed_issue",H3="probable_issue",H3="not_issue",H3="indeterminate"))),AND(AND(D3="retain",E3="statistical_results"),NOT(OR(I3="substantive",I3="minor_presentation",I3="indeterminate"))),AND(AND(D3="retain",E3="statistical_results"),J3<>"",NOT(OR(J3="direct",J3="possible",J3="unlikely",J3="unknown"))),AND(AND(D3="retain",OR(E3="report_internal_inconsistency",E3="plan_material")),NOT(OR(K3="substantive_inconsistency",K3="minor_presentation",K3="non_inconsistency",K3="indeterminate"))),AND(AND(D3="retain",E3="protocol_report"),L3<>"",NOT(OR(L3="substantive_difference",L3="minor_presentation",L3="version_timing",L3="non_inconsistency",L3="indeterminate")))),"CHECK FIELDS",IF(AND(F3<>"",NOT(OR(F3="no",F3="primary_done"))),"CHECK COMPLETE",IF(F3="primary_done","PRIMARY READY","PRIMARY DRAFT")))))),"CHECK INPUT / KEY") -> PRIMARY READY | R3: TEST 2025::jama.2025.16450::C002
A4: 2025::jama.2025.16450::C003 | B4: Registered first-dose discrepancy is not reproduced on direct-source recheck | C4: DOC-002 protocol — PDF p. 4; DOC-003 manual — PDF p. 7 and manual — PDF p. 12; DOC-004 SAP — PDF p. 8; DOC-001 main article — PDF p. 2; DOC-005 results supplement — PDF p. 4. | D4: retain | E4: protocol_report | F4: primary_done | G4: =IFERROR(IF(LEN(TRIM(CLEAN(SUBSTITUTE(Setup!$B$2,CHAR(160)," "))))=0,"CHECK REVIEWER ID",IF(OR(A4="",(COUNTIF('C_jama.2024.24764'!$A$2:$A$9,A4)+COUNTIF('C_jama.2024.27643'!$A$2:$A$9,A4)+COUNTIF('C_jama.2025.11178'!$A$2:$A$38,A4)+COUNTIF('C_jama.2025.15185'!$A$2:$A$13,A4)+COUNTIF('C_jama.2025.15440'!$A$2:$A$3,A4)+COUNTIF('C_jama.2025.16450'!$A$2:$A$11,A4)+COUNTIF('C_jama.2025.19563'!$A$2:$A$8,A4)+COUNTIF('C_jama.2025.19843'!$A$2:$A$2,A4)+COUNTIF('C_jama.2025.20765'!$A$2:$A$14,A4)+COUNTIF('C_jama.2025.24175'!$A$2:$A$15,A4)+COUNTIF('C_jama.2025.4390'!$A$2:$A$4,A4)+COUNTIF('C_jama.2025.7583'!$A$2:$A$4,A4)+COUNTIF('C_jama.2025.7710'!$A$2:$A$5,A4)+COUNTIF('C_jama.2025.9110'!$A$2:$A$7,A4)+COUNTIF('C_jama.2025.9663'!$A$2:$A$4,A4))<>1,COUNTIFS(Candidates!$G$2:$G$132,A4,Candidates!$K$2:$K$132,"jama.2025.16450")<>1),"CHECK KEY",IF(OR(AND(NOT(AND(D4="retain",E4="statistical_results")),H4<>"",H4<>"not_applicable"),AND(NOT(AND(D4="retain",E4="statistical_results")),I4<>"",I4<>"not_applicable"),AND(NOT(AND(D4="retain",E4="statistical_results")),J4<>"",J4<>"not_applicable"),AND(NOT(AND(D4="retain",OR(E4="report_internal_inconsistency",E4="plan_material"))),K4<>"",K4<>"not_applicable"),AND(NOT(AND(D4="retain",E4="protocol_report")),L4<>"",L4<>"not_applicable")),"CLEAR INACTIVE VALUES",IF(OR(NOT(OR(D4="retain",D4="exclude",D4="discuss")),NOT(OR(E4="statistical_results",E4="report_internal_inconsistency",E4="plan_material",E4="protocol_report")),AND(AND(D4="retain",E4="statistical_results"),NOT(OR(H4="confirmed_issue",H4="probable_issue",H4="not_issue",H4="indeterminate"))),AND(AND(D4="retain",E4="statistical_results"),NOT(OR(I4="substantive",I4="minor_presentation",I4="indeterminate"))),AND(AND(D4="retain",E4="statistical_results"),J4<>"",NOT(OR(J4="direct",J4="possible",J4="unlikely",J4="unknown"))),AND(AND(D4="retain",OR(E4="report_internal_inconsistency",E4="plan_material")),NOT(OR(K4="substantive_inconsistency",K4="minor_presentation",K4="non_inconsistency",K4="indeterminate"))),AND(AND(D4="retain",E4="protocol_report"),L4<>"",NOT(OR(L4="substantive_difference",L4="minor_presentation",L4="version_timing",L4="non_inconsistency",L4="indeterminate")))),"CHECK FIELDS",IF(AND(F4<>"",NOT(OR(F4="no",F4="primary_done"))),"CHECK COMPLETE",IF(F4="primary_done","PRIMARY READY","PRIMARY DRAFT")))))),"CHECK INPUT / KEY") -> PRIMARY READY | R4: TEST 2025::jama.2025.16450::C003
A5: 2025::jama.2025.16450::C004 | B5: Severe-NDI GMFCS cutoff differs between the manual and SAP | C5: DOC-003 manual — PDF p. 14 and manual — PDF p. 16; DOC-004 SAP — PDF p. 10 and SAP — PDF p. 33. | D5: retain | E5: plan_material | F5: primary_done | G5: =IFERROR(IF(LEN(TRIM(CLEAN(SUBSTITUTE(Setup!$B$2,CHAR(160)," "))))=0,"CHECK REVIEWER ID",IF(OR(A5="",(COUNTIF('C_jama.2024.24764'!$A$2:$A$9,A5)+COUNTIF('C_jama.2024.27643'!$A$2:$A$9,A5)+COUNTIF('C_jama.2025.11178'!$A$2:$A$38,A5)+COUNTIF('C_jama.2025.15185'!$A$2:$A$13,A5)+COUNTIF('C_jama.2025.15440'!$A$2:$A$3,A5)+COUNTIF('C_jama.2025.16450'!$A$2:$A$11,A5)+COUNTIF('C_jama.2025.19563'!$A$2:$A$8,A5)+COUNTIF('C_jama.2025.19843'!$A$2:$A$2,A5)+COUNTIF('C_jama.2025.20765'!$A$2:$A$14,A5)+COUNTIF('C_jama.2025.24175'!$A$2:$A$15,A5)+COUNTIF('C_jama.2025.4390'!$A$2:$A$4,A5)+COUNTIF('C_jama.2025.7583'!$A$2:$A$4,A5)+COUNTIF('C_jama.2025.7710'!$A$2:$A$5,A5)+COUNTIF('C_jama.2025.9110'!$A$2:$A$7,A5)+COUNTIF('C_jama.2025.9663'!$A$2:$A$4,A5))<>1,COUNTIFS(Candidates!$G$2:$G$132,A5,Candidates!$K$2:$K$132,"jama.2025.16450")<>1),"CHECK KEY",IF(OR(AND(NOT(AND(D5="retain",E5="statistical_results")),H5<>"",H5<>"not_applicable"),AND(NOT(AND(D5="retain",E5="statistical_results")),I5<>"",I5<>"not_applicable"),AND(NOT(AND(D5="retain",E5="statistical_results")),J5<>"",J5<>"not_applicable"),AND(NOT(AND(D5="retain",OR(E5="report_internal_inconsistency",E5="plan_material"))),K5<>"",K5<>"not_applicable"),AND(NOT(AND(D5="retain",E5="protocol_report")),L5<>"",L5<>"not_applicable")),"CLEAR INACTIVE VALUES",IF(OR(NOT(OR(D5="retain",D5="exclude",D5="discuss")),NOT(OR(E5="statistical_results",E5="report_internal_inconsistency",E5="plan_material",E5="protocol_report")),AND(AND(D5="retain",E5="statistical_results"),NOT(OR(H5="confirmed_issue",H5="probable_issue",H5="not_issue",H5="indeterminate"))),AND(AND(D5="retain",E5="statistical_results"),NOT(OR(I5="substantive",I5="minor_presentation",I5="indeterminate"))),AND(AND(D5="retain",E5="statistical_results"),J5<>"",NOT(OR(J5="direct",J5="possible",J5="unlikely",J5="unknown"))),AND(AND(D5="retain",OR(E5="report_internal_inconsistency",E5="plan_material")),NOT(OR(K5="substantive_inconsistency",K5="minor_presentation",K5="non_inconsistency",K5="indeterminate"))),AND(AND(D5="retain",E5="protocol_report"),L5<>"",NOT(OR(L5="substantive_difference",L5="minor_presentation",L5="version_timing",L5="non_inconsistency",L5="indeterminate")))),"CHECK FIELDS",IF(AND(F5<>"",NOT(OR(F5="no",F5="primary_done"))),"CHECK COMPLETE",IF(F5="primary_done","PRIMARY READY","PRIMARY DRAFT")))))),"CHECK INPUT / KEY") -> PRIMARY READY | K5: substantive_inconsistency | R5: TEST 2025::jama.2025.16450::C004
A6: 2025::jama.2025.16450::C005 | B6: Registered severe-NDI instrument-edition discrepancy is not reproduced on direct-source recheck | C6: DOC-003 manual — PDF p. 14 and manual — PDF p. 16; DOC-004 SAP — PDF p. 10, SAP — PDF p. 33, and SAP — PDF p. 34. | D6: retain | E6: plan_material | F6: primary_done | G6: =IFERROR(IF(LEN(TRIM(CLEAN(SUBSTITUTE(Setup!$B$2,CHAR(160)," "))))=0,"CHECK REVIEWER ID",IF(OR(A6="",(COUNTIF('C_jama.2024.24764'!$A$2:$A$9,A6)+COUNTIF('C_jama.2024.27643'!$A$2:$A$9,A6)+COUNTIF('C_jama.2025.11178'!$A$2:$A$38,A6)+COUNTIF('C_jama.2025.15185'!$A$2:$A$13,A6)+COUNTIF('C_jama.2025.15440'!$A$2:$A$3,A6)+COUNTIF('C_jama.2025.16450'!$A$2:$A$11,A6)+COUNTIF('C_jama.2025.19563'!$A$2:$A$8,A6)+COUNTIF('C_jama.2025.19843'!$A$2:$A$2,A6)+COUNTIF('C_jama.2025.20765'!$A$2:$A$14,A6)+COUNTIF('C_jama.2025.24175'!$A$2:$A$15,A6)+COUNTIF('C_jama.2025.4390'!$A$2:$A$4,A6)+COUNTIF('C_jama.2025.7583'!$A$2:$A$4,A6)+COUNTIF('C_jama.2025.7710'!$A$2:$A$5,A6)+COUNTIF('C_jama.2025.9110'!$A$2:$A$7,A6)+COUNTIF('C_jama.2025.9663'!$A$2:$A$4,A6))<>1,COUNTIFS(Candidates!$G$2:$G$132,A6,Candidates!$K$2:$K$132,"jama.2025.16450")<>1),"CHECK KEY",IF(OR(AND(NOT(AND(D6="retain",E6="statistical_results")),H6<>"",H6<>"not_applicable"),AND(NOT(AND(D6="retain",E6="statistical_results")),I6<>"",I6<>"not_applicable"),AND(NOT(AND(D6="retain",E6="statistical_results")),J6<>"",J6<>"not_applicable"),AND(NOT(AND(D6="retain",OR(E6="report_internal_inconsistency",E6="plan_material"))),K6<>"",K6<>"not_applicable"),AND(NOT(AND(D6="retain",E6="protocol_report")),L6<>"",L6<>"not_applicable")),"CLEAR INACTIVE VALUES",IF(OR(NOT(OR(D6="retain",D6="exclude",D6="discuss")),NOT(OR(E6="statistical_results",E6="report_internal_inconsistency",E6="plan_material",E6="protocol_report")),AND(AND(D6="retain",E6="statistical_results"),NOT(OR(H6="confirmed_issue",H6="probable_issue",H6="not_issue",H6="indeterminate"))),AND(AND(D6="retain",E6="statistical_results"),NOT(OR(I6="substantive",I6="minor_presentation",I6="indeterminate"))),AND(AND(D6="retain",E6="statistical_results"),J6<>"",NOT(OR(J6="direct",J6="possible",J6="unlikely",J6="unknown"))),AND(AND(D6="retain",OR(E6="report_internal_inconsistency",E6="plan_material")),NOT(OR(K6="substantive_inconsistency",K6="minor_presentation",K6="non_inconsistency",K6="indeterminate"))),AND(AND(D6="retain",E6="protocol_report"),L6<>"",NOT(OR(L6="substantive_difference",L6="minor_presentation",L6="version_timing",L6="non_inconsistency",L6="indeterminate")))),"CHECK FIELDS",IF(AND(F6<>"",NOT(OR(F6="no",F6="primary_done"))),"CHECK COMPLETE",IF(F6="primary_done","PRIMARY READY","PRIMARY DRAFT")))))),"CHECK INPUT / KEY") -> PRIMARY READY | K6: substantive_inconsistency | R6: TEST 2025::jama.2025.16450::C005
A7: 2025::jama.2025.16450::C006 | B7: Registered first-interim-alpha discrepancy is not reproduced on direct-source recheck | C7: DOC-002 protocol — PDF p. 29; DOC-004 SAP — PDF p. 26. | D7: retain | E7: plan_material | F7: primary_done | G7: =IFERROR(IF(LEN(TRIM(CLEAN(SUBSTITUTE(Setup!$B$2,CHAR(160)," "))))=0,"CHECK REVIEWER ID",IF(OR(A7="",(COUNTIF('C_jama.2024.24764'!$A$2:$A$9,A7)+COUNTIF('C_jama.2024.27643'!$A$2:$A$9,A7)+COUNTIF('C_jama.2025.11178'!$A$2:$A$38,A7)+COUNTIF('C_jama.2025.15185'!$A$2:$A$13,A7)+COUNTIF('C_jama.2025.15440'!$A$2:$A$3,A7)+COUNTIF('C_jama.2025.16450'!$A$2:$A$11,A7)+COUNTIF('C_jama.2025.19563'!$A$2:$A$8,A7)+COUNTIF('C_jama.2025.19843'!$A$2:$A$2,A7)+COUNTIF('C_jama.2025.20765'!$A$2:$A$14,A7)+COUNTIF('C_jama.2025.24175'!$A$2:$A$15,A7)+COUNTIF('C_jama.2025.4390'!$A$2:$A$4,A7)+COUNTIF('C_jama.2025.7583'!$A$2:$A$4,A7)+COUNTIF('C_jama.2025.7710'!$A$2:$A$5,A7)+COUNTIF('C_jama.2025.9110'!$A$2:$A$7,A7)+COUNTIF('C_jama.2025.9663'!$A$2:$A$4,A7))<>1,COUNTIFS(Candidates!$G$2:$G$132,A7,Candidates!$K$2:$K$132,"jama.2025.16450")<>1),"CHECK KEY",IF(OR(AND(NOT(AND(D7="retain",E7="statistical_results")),H7<>"",H7<>"not_applicable"),AND(NOT(AND(D7="retain",E7="statistical_results")),I7<>"",I7<>"not_applicable"),AND(NOT(AND(D7="retain",E7="statistical_results")),J7<>"",J7<>"not_applicable"),AND(NOT(AND(D7="retain",OR(E7="report_internal_inconsistency",E7="plan_material"))),K7<>"",K7<>"not_applicable"),AND(NOT(AND(D7="retain",E7="protocol_report")),L7<>"",L7<>"not_applicable")),"CLEAR INACTIVE VALUES",IF(OR(NOT(OR(D7="retain",D7="exclude",D7="discuss")),NOT(OR(E7="statistical_results",E7="report_internal_inconsistency",E7="plan_material",E7="protocol_report")),AND(AND(D7="retain",E7="statistical_results"),NOT(OR(H7="confirmed_issue",H7="probable_issue",H7="not_issue",H7="indeterminate"))),AND(AND(D7="retain",E7="statistical_results"),NOT(OR(I7="substantive",I7="minor_presentation",I7="indeterminate"))),AND(AND(D7="retain",E7="statistical_results"),J7<>"",NOT(OR(J7="direct",J7="possible",J7="unlikely",J7="unknown"))),AND(AND(D7="retain",OR(E7="report_internal_inconsistency",E7="plan_material")),NOT(OR(K7="substantive_inconsistency",K7="minor_presentation",K7="non_inconsistency",K7="indeterminate"))),AND(AND(D7="retain",E7="protocol_report"),L7<>"",NOT(OR(L7="substantive_difference",L7="minor_presentation",L7="version_timing",L7="non_inconsistency",L7="indeterminate")))),"CHECK FIELDS",IF(AND(F7<>"",NOT(OR(F7="no",F7="primary_done"))),"CHECK COMPLETE",IF(F7="primary_done","PRIMARY READY","PRIMARY DRAFT")))))),"CHECK INPUT / KEY") -> PRIMARY READY | K7: substantive_inconsistency | R7: TEST 2025::jama.2025.16450::C006
A8: 2025::jama.2025.16450::C007 | B8: Final primary-analysis alpha differs between the article and prospective documents | C8: DOC-001 main article — PDF p. 3 and main article — PDF p. 7; DOC-002 protocol — PDF p. 29; DOC-004 SAP — PDF p. 26. | D8: retain | E8: protocol_report | F8: primary_done | G8: =IFERROR(IF(LEN(TRIM(CLEAN(SUBSTITUTE(Setup!$B$2,CHAR(160)," "))))=0,"CHECK REVIEWER ID",IF(OR(A8="",(COUNTIF('C_jama.2024.24764'!$A$2:$A$9,A8)+COUNTIF('C_jama.2024.27643'!$A$2:$A$9,A8)+COUNTIF('C_jama.2025.11178'!$A$2:$A$38,A8)+COUNTIF('C_jama.2025.15185'!$A$2:$A$13,A8)+COUNTIF('C_jama.2025.15440'!$A$2:$A$3,A8)+COUNTIF('C_jama.2025.16450'!$A$2:$A$11,A8)+COUNTIF('C_jama.2025.19563'!$A$2:$A$8,A8)+COUNTIF('C_jama.2025.19843'!$A$2:$A$2,A8)+COUNTIF('C_jama.2025.20765'!$A$2:$A$14,A8)+COUNTIF('C_jama.2025.24175'!$A$2:$A$15,A8)+COUNTIF('C_jama.2025.4390'!$A$2:$A$4,A8)+COUNTIF('C_jama.2025.7583'!$A$2:$A$4,A8)+COUNTIF('C_jama.2025.7710'!$A$2:$A$5,A8)+COUNTIF('C_jama.2025.9110'!$A$2:$A$7,A8)+COUNTIF('C_jama.2025.9663'!$A$2:$A$4,A8))<>1,COUNTIFS(Candidates!$G$2:$G$132,A8,Candidates!$K$2:$K$132,"jama.2025.16450")<>1),"CHECK KEY",IF(OR(AND(NOT(AND(D8="retain",E8="statistical_results")),H8<>"",H8<>"not_applicable"),AND(NOT(AND(D8="retain",E8="statistical_results")),I8<>"",I8<>"not_applicable"),AND(NOT(AND(D8="retain",E8="statistical_results")),J8<>"",J8<>"not_applicable"),AND(NOT(AND(D8="retain",OR(E8="report_internal_inconsistency",E8="plan_material"))),K8<>"",K8<>"not_applicable"),AND(NOT(AND(D8="retain",E8="protocol_report")),L8<>"",L8<>"not_applicable")),"CLEAR INACTIVE VALUES",IF(OR(NOT(OR(D8="retain",D8="exclude",D8="discuss")),NOT(OR(E8="statistical_results",E8="report_internal_inconsistency",E8="plan_material",E8="protocol_report")),AND(AND(D8="retain",E8="statistical_results"),NOT(OR(H8="confirmed_issue",H8="probable_issue",H8="not_issue",H8="indeterminate"))),AND(AND(D8="retain",E8="statistical_results"),NOT(OR(I8="substantive",I8="minor_presentation",I8="indeterminate"))),AND(AND(D8="retain",E8="statistical_results"),J8<>"",NOT(OR(J8="direct",J8="possible",J8="unlikely",J8="unknown"))),AND(AND(D8="retain",OR(E8="report_internal_inconsistency",E8="plan_material")),NOT(OR(K8="substantive_inconsistency",K8="minor_presentation",K8="non_inconsistency",K8="indeterminate"))),AND(AND(D8="retain",E8="protocol_report"),L8<>"",NOT(OR(L8="substantive_difference",L8="minor_presentation",L8="version_timing",L8="non_inconsistency",L8="indeterminate")))),"CHECK FIELDS",IF(AND(F8<>"",NOT(OR(F8="no",F8="primary_done"))),"CHECK COMPLETE",IF(F8="primary_done","PRIMARY READY","PRIMARY DRAFT")))))),"CHECK INPUT / KEY") -> PRIMARY READY | R8: TEST 2025::jama.2025.16450::C007
A9: 2025::jama.2025.16450::C008 | B9: Trial center count differs between final and prospective documents | C9: DOC-001 main article — PDF p. 1; DOC-002 protocol — PDF p. 29; DOC-004 SAP — PDF p. 8. | D9: retain | E9: protocol_report | F9: primary_done | G9: =IFERROR(IF(LEN(TRIM(CLEAN(SUBSTITUTE(Setup!$B$2,CHAR(160)," "))))=0,"CHECK REVIEWER ID",IF(OR(A9="",(COUNTIF('C_jama.2024.24764'!$A$2:$A$9,A9)+COUNTIF('C_jama.2024.27643'!$A$2:$A$9,A9)+COUNTIF('C_jama.2025.11178'!$A$2:$A$38,A9)+COUNTIF('C_jama.2025.15185'!$A$2:$A$13,A9)+COUNTIF('C_jama.2025.15440'!$A$2:$A$3,A9)+COUNTIF('C_jama.2025.16450'!$A$2:$A$11,A9)+COUNTIF('C_jama.2025.19563'!$A$2:$A$8,A9)+COUNTIF('C_jama.2025.19843'!$A$2:$A$2,A9)+COUNTIF('C_jama.2025.20765'!$A$2:$A$14,A9)+COUNTIF('C_jama.2025.24175'!$A$2:$A$15,A9)+COUNTIF('C_jama.2025.4390'!$A$2:$A$4,A9)+COUNTIF('C_jama.2025.7583'!$A$2:$A$4,A9)+COUNTIF('C_jama.2025.7710'!$A$2:$A$5,A9)+COUNTIF('C_jama.2025.9110'!$A$2:$A$7,A9)+COUNTIF('C_jama.2025.9663'!$A$2:$A$4,A9))<>1,COUNTIFS(Candidates!$G$2:$G$132,A9,Candidates!$K$2:$K$132,"jama.2025.16450")<>1),"CHECK KEY",IF(OR(AND(NOT(AND(D9="retain",E9="statistical_results")),H9<>"",H9<>"not_applicable"),AND(NOT(AND(D9="retain",E9="statistical_results")),I9<>"",I9<>"not_applicable"),AND(NOT(AND(D9="retain",E9="statistical_results")),J9<>"",J9<>"not_applicable"),AND(NOT(AND(D9="retain",OR(E9="report_internal_inconsistency",E9="plan_material"))),K9<>"",K9<>"not_applicable"),AND(NOT(AND(D9="retain",E9="protocol_report")),L9<>"",L9<>"not_applicable")),"CLEAR INACTIVE VALUES",IF(OR(NOT(OR(D9="retain",D9="exclude",D9="discuss")),NOT(OR(E9="statistical_results",E9="report_internal_inconsistency",E9="plan_material",E9="protocol_report")),AND(AND(D9="retain",E9="statistical_results"),NOT(OR(H9="confirmed_issue",H9="probable_issue",H9="not_issue",H9="indeterminate"))),AND(AND(D9="retain",E9="statistical_results"),NOT(OR(I9="substantive",I9="minor_presentation",I9="indeterminate"))),AND(AND(D9="retain",E9="statistical_results"),J9<>"",NOT(OR(J9="direct",J9="possible",J9="unlikely",J9="unknown"))),AND(AND(D9="retain",OR(E9="report_internal_inconsistency",E9="plan_material")),NOT(OR(K9="substantive_inconsistency",K9="minor_presentation",K9="non_inconsistency",K9="indeterminate"))),AND(AND(D9="retain",E9="protocol_report"),L9<>"",NOT(OR(L9="substantive_difference",L9="minor_presentation",L9="version_timing",L9="non_inconsistency",L9="indeterminate")))),"CHECK FIELDS",IF(AND(F9<>"",NOT(OR(F9="no",F9="primary_done"))),"CHECK COMPLETE",IF(F9="primary_done","PRIMARY READY","PRIMARY DRAFT")))))),"CHECK INPUT / KEY") -> PRIMARY READY | R9: TEST 2025::jama.2025.16450::C008
A10: 2025::jama.2025.16450::C009 | B10: Table 3 RR label conflicts with a stated common-OR approximation | C10: DOC-001 main article — PDF p. 8 (Table 3 additional open-label surfactant row and footnote g). | D10: retain | E10: report_internal_inconsistency | F10: primary_done | G10: =IFERROR(IF(LEN(TRIM(CLEAN(SUBSTITUTE(Setup!$B$2,CHAR(160)," "))))=0,"CHECK REVIEWER ID",IF(OR(A10="",(COUNTIF('C_jama.2024.24764'!$A$2:$A$9,A10)+COUNTIF('C_jama.2024.27643'!$A$2:$A$9,A10)+COUNTIF('C_jama.2025.11178'!$A$2:$A$38,A10)+COUNTIF('C_jama.2025.15185'!$A$2:$A$13,A10)+COUNTIF('C_jama.2025.15440'!$A$2:$A$3,A10)+COUNTIF('C_jama.2025.16450'!$A$2:$A$11,A10)+COUNTIF('C_jama.2025.19563'!$A$2:$A$8,A10)+COUNTIF('C_jama.2025.19843'!$A$2:$A$2,A10)+COUNTIF('C_jama.2025.20765'!$A$2:$A$14,A10)+COUNTIF('C_jama.2025.24175'!$A$2:$A$15,A10)+COUNTIF('C_jama.2025.4390'!$A$2:$A$4,A10)+COUNTIF('C_jama.2025.7583'!$A$2:$A$4,A10)+COUNTIF('C_jama.2025.7710'!$A$2:$A$5,A10)+COUNTIF('C_jama.2025.9110'!$A$2:$A$7,A10)+COUNTIF('C_jama.2025.9663'!$A$2:$A$4,A10))<>1,COUNTIFS(Candidates!$G$2:$G$132,A10,Candidates!$K$2:$K$132,"jama.2025.16450")<>1),"CHECK KEY",IF(OR(AND(NOT(AND(D10="retain",E10="statistical_results")),H10<>"",H10<>"not_applicable"),AND(NOT(AND(D10="retain",E10="statistical_results")),I10<>"",I10<>"not_applicable"),AND(NOT(AND(D10="retain",E10="statistical_results")),J10<>"",J10<>"not_applicable"),AND(NOT(AND(D10="retain",OR(E10="report_internal_inconsistency",E10="plan_material"))),K10<>"",K10<>"not_applicable"),AND(NOT(AND(D10="retain",E10="protocol_report")),L10<>"",L10<>"not_applicable")),"CLEAR INACTIVE VALUES",IF(OR(NOT(OR(D10="retain",D10="exclude",D10="discuss")),NOT(OR(E10="statistical_results",E10="report_internal_inconsistency",E10="plan_material",E10="protocol_report")),AND(AND(D10="retain",E10="statistical_results"),NOT(OR(H10="confirmed_issue",H10="probable_issue",H10="not_issue",H10="indeterminate"))),AND(AND(D10="retain",E10="statistical_results"),NOT(OR(I10="substantive",I10="minor_presentation",I10="indeterminate"))),AND(AND(D10="retain",E10="statistical_results"),J10<>"",NOT(OR(J10="direct",J10="possible",J10="unlikely",J10="unknown"))),AND(AND(D10="retain",OR(E10="report_internal_inconsistency",E10="plan_material")),NOT(OR(K10="substantive_inconsistency",K10="minor_presentation",K10="non_inconsistency",K10="indeterminate"))),AND(AND(D10="retain",E10="protocol_report"),L10<>"",NOT(OR(L10="substantive_difference",L10="minor_presentation",L10="version_timing",L10="non_inconsistency",L10="indeterminate")))),"CHECK FIELDS",IF(AND(F10<>"",NOT(OR(F10="no",F10="primary_done"))),"CHECK COMPLETE",IF(F10="primary_done","PRIMARY READY","PRIMARY DRAFT")))))),"CHECK INPUT / KEY") -> PRIMARY READY | K10: substantive_inconsistency | R10: TEST 2025::jama.2025.16450::C009
A11: 2025::jama.2025.16450::C010 | B11: eTable 3 relative-risk header conflicts with odds-ratio approximation footnote | C11: DOC-005 results supplement — PDF p. 5 and results supplement — PDF p. 6 (eTable 3 header and footnote b). | D11: retain | E11: report_internal_inconsistency | F11: primary_done | G11: =IFERROR(IF(LEN(TRIM(CLEAN(SUBSTITUTE(Setup!$B$2,CHAR(160)," "))))=0,"CHECK REVIEWER ID",IF(OR(A11="",(COUNTIF('C_jama.2024.24764'!$A$2:$A$9,A11)+COUNTIF('C_jama.2024.27643'!$A$2:$A$9,A11)+COUNTIF('C_jama.2025.11178'!$A$2:$A$38,A11)+COUNTIF('C_jama.2025.15185'!$A$2:$A$13,A11)+COUNTIF('C_jama.2025.15440'!$A$2:$A$3,A11)+COUNTIF('C_jama.2025.16450'!$A$2:$A$11,A11)+COUNTIF('C_jama.2025.19563'!$A$2:$A$8,A11)+COUNTIF('C_jama.2025.19843'!$A$2:$A$2,A11)+COUNTIF('C_jama.2025.20765'!$A$2:$A$14,A11)+COUNTIF('C_jama.2025.24175'!$A$2:$A$15,A11)+COUNTIF('C_jama.2025.4390'!$A$2:$A$4,A11)+COUNTIF('C_jama.2025.7583'!$A$2:$A$4,A11)+COUNTIF('C_jama.2025.7710'!$A$2:$A$5,A11)+COUNTIF('C_jama.2025.9110'!$A$2:$A$7,A11)+COUNTIF('C_jama.2025.9663'!$A$2:$A$4,A11))<>1,COUNTIFS(Candidates!$G$2:$G$132,A11,Candidates!$K$2:$K$132,"jama.2025.16450")<>1),"CHECK KEY",IF(OR(AND(NOT(AND(D11="retain",E11="statistical_results")),H11<>"",H11<>"not_applicable"),AND(NOT(AND(D11="retain",E11="statistical_results")),I11<>"",I11<>"not_applicable"),AND(NOT(AND(D11="retain",E11="statistical_results")),J11<>"",J11<>"not_applicable"),AND(NOT(AND(D11="retain",OR(E11="report_internal_inconsistency",E11="plan_material"))),K11<>"",K11<>"not_applicable"),AND(NOT(AND(D11="retain",E11="protocol_report")),L11<>"",L11<>"not_applicable")),"CLEAR INACTIVE VALUES",IF(OR(NOT(OR(D11="retain",D11="exclude",D11="discuss")),NOT(OR(E11="statistical_results",E11="report_internal_inconsistency",E11="plan_material",E11="protocol_report")),AND(AND(D11="retain",E11="statistical_results"),NOT(OR(H11="confirmed_issue",H11="probable_issue",H11="not_issue",H11="indeterminate"))),AND(AND(D11="retain",E11="statistical_results"),NOT(OR(I11="substantive",I11="minor_presentation",I11="indeterminate"))),AND(AND(D11="retain",E11="statistical_results"),J11<>"",NOT(OR(J11="direct",J11="possible",J11="unlikely",J11="unknown"))),AND(AND(D11="retain",OR(E11="report_internal_inconsistency",E11="plan_material")),NOT(OR(K11="substantive_inconsistency",K11="minor_presentation",K11="non_inconsistency",K11="indeterminate"))),AND(AND(D11="retain",E11="protocol_report"),L11<>"",NOT(OR(L11="substantive_difference",L11="minor_presentation",L11="version_timing",L11="non_inconsistency",L11="indeterminate")))),"CHECK FIELDS",IF(AND(F11<>"",NOT(OR(F11="no",F11="primary_done"))),"CHECK COMPLETE",IF(F11="primary_done","PRIMARY READY","PRIMARY DRAFT")))))),"CHECK INPUT / KEY") -> PRIMARY READY | K11: substantive_inconsistency | R11: TEST 2025::jama.2025.16450::C010

Sheet C_jama.2025.19563
A1: Candidate key | B1: Candidate title | C1: Source location | D1: Disposition | E1: Review domain (AI suggestion; editable) | F1: Complete | G1: Validation hint | H1: Statistcal_or_numerical issue | I1: Substantiveness | J1: Downstream impact | K1: Report-internal or planning-material inconsistency | L1: Protocol interpretation | R1: Notes (optional)
A2: 2025::jama.2025.19563::C001 | B2: Protocol and reported primary endpoint differ on the diabetes-range A1C failure condition | C2: DOC-002 protocol — PDF p. 15; DOC-001 main article — PDF p. 4; DOC-003 supplement — PDF p. 30 (explicit global-failure clause); DOC-003 supplement — PDF p. 56 (15-participant table). | D2: retain | E2: protocol_report | F2: primary_done | G2: =IFERROR(IF(LEN(TRIM(CLEAN(SUBSTITUTE(Setup!$B$2,CHAR(160)," "))))=0,"CHECK REVIEWER ID",IF(OR(A2="",(COUNTIF('C_jama.2024.24764'!$A$2:$A$9,A2)+COUNTIF('C_jama.2024.27643'!$A$2:$A$9,A2)+COUNTIF('C_jama.2025.11178'!$A$2:$A$38,A2)+COUNTIF('C_jama.2025.15185'!$A$2:$A$13,A2)+COUNTIF('C_jama.2025.15440'!$A$2:$A$3,A2)+COUNTIF('C_jama.2025.16450'!$A$2:$A$11,A2)+COUNTIF('C_jama.2025.19563'!$A$2:$A$8,A2)+COUNTIF('C_jama.2025.19843'!$A$2:$A$2,A2)+COUNTIF('C_jama.2025.20765'!$A$2:$A$14,A2)+COUNTIF('C_jama.2025.24175'!$A$2:$A$15,A2)+COUNTIF('C_jama.2025.4390'!$A$2:$A$4,A2)+COUNTIF('C_jama.2025.7583'!$A$2:$A$4,A2)+COUNTIF('C_jama.2025.7710'!$A$2:$A$5,A2)+COUNTIF('C_jama.2025.9110'!$A$2:$A$7,A2)+COUNTIF('C_jama.2025.9663'!$A$2:$A$4,A2))<>1,COUNTIFS(Candidates!$G$2:$G$132,A2,Candidates!$K$2:$K$132,"jama.2025.19563")<>1),"CHECK KEY",IF(OR(AND(NOT(AND(D2="retain",E2="statistical_results")),H2<>"",H2<>"not_applicable"),AND(NOT(AND(D2="retain",E2="statistical_results")),I2<>"",I2<>"not_applicable"),AND(NOT(AND(D2="retain",E2="statistical_results")),J2<>"",J2<>"not_applicable"),AND(NOT(AND(D2="retain",OR(E2="report_internal_inconsistency",E2="plan_material"))),K2<>"",K2<>"not_applicable"),AND(NOT(AND(D2="retain",E2="protocol_report")),L2<>"",L2<>"not_applicable")),"CLEAR INACTIVE VALUES",IF(OR(NOT(OR(D2="retain",D2="exclude",D2="discuss")),NOT(OR(E2="statistical_results",E2="report_internal_inconsistency",E2="plan_material",E2="protocol_report")),AND(AND(D2="retain",E2="statistical_results"),NOT(OR(H2="confirmed_issue",H2="probable_issue",H2="not_issue",H2="indeterminate"))),AND(AND(D2="retain",E2="statistical_results"),NOT(OR(I2="substantive",I2="minor_presentation",I2="indeterminate"))),AND(AND(D2="retain",E2="statistical_results"),J2<>"",NOT(OR(J2="direct",J2="possible",J2="unlikely",J2="unknown"))),AND(AND(D2="retain",OR(E2="report_internal_inconsistency",E2="plan_material")),NOT(OR(K2="substantive_inconsistency",K2="minor_presentation",K2="non_inconsistency",K2="indeterminate"))),AND(AND(D2="retain",E2="protocol_report"),L2<>"",NOT(OR(L2="substantive_difference",L2="minor_presentation",L2="version_timing",L2="non_inconsistency",L2="indeterminate")))),"CHECK FIELDS",IF(AND(F2<>"",NOT(OR(F2="no",F2="primary_done"))),"CHECK COMPLETE",IF(F2="primary_done","PRIMARY READY","PRIMARY DRAFT")))))),"CHECK INPUT / KEY") -> PRIMARY READY | R2: TEST 2025::jama.2025.19563::C001
A3: 2025::jama.2025.19563::C002 | B3: 312 listed 12-month A1C measurements versus 313 participants with A1C available | C3: DOC-003 supplement — PDF p. 8; DOC-001 main article — PDF p. 4; DOC-001 main article — PDF p. 5; DOC-003 supplement — PDF p. 50. | D3: retain | E3: statistical_results | F3: primary_done | G3: =IFERROR(IF(LEN(TRIM(CLEAN(SUBSTITUTE(Setup!$B$2,CHAR(160)," "))))=0,"CHECK REVIEWER ID",IF(OR(A3="",(COUNTIF('C_jama.2024.24764'!$A$2:$A$9,A3)+COUNTIF('C_jama.2024.27643'!$A$2:$A$9,A3)+COUNTIF('C_jama.2025.11178'!$A$2:$A$38,A3)+COUNTIF('C_jama.2025.15185'!$A$2:$A$13,A3)+COUNTIF('C_jama.2025.15440'!$A$2:$A$3,A3)+COUNTIF('C_jama.2025.16450'!$A$2:$A$11,A3)+COUNTIF('C_jama.2025.19563'!$A$2:$A$8,A3)+COUNTIF('C_jama.2025.19843'!$A$2:$A$2,A3)+COUNTIF('C_jama.2025.20765'!$A$2:$A$14,A3)+COUNTIF('C_jama.2025.24175'!$A$2:$A$15,A3)+COUNTIF('C_jama.2025.4390'!$A$2:$A$4,A3)+COUNTIF('C_jama.2025.7583'!$A$2:$A$4,A3)+COUNTIF('C_jama.2025.7710'!$A$2:$A$5,A3)+COUNTIF('C_jama.2025.9110'!$A$2:$A$7,A3)+COUNTIF('C_jama.2025.9663'!$A$2:$A$4,A3))<>1,COUNTIFS(Candidates!$G$2:$G$132,A3,Candidates!$K$2:$K$132,"jama.2025.19563")<>1),"CHECK KEY",IF(OR(AND(NOT(AND(D3="retain",E3="statistical_results")),H3<>"",H3<>"not_applicable"),AND(NOT(AND(D3="retain",E3="statistical_results")),I3<>"",I3<>"not_applicable"),AND(NOT(AND(D3="retain",E3="statistical_results")),J3<>"",J3<>"not_applicable"),AND(NOT(AND(D3="retain",OR(E3="report_internal_inconsistency",E3="plan_material"))),K3<>"",K3<>"not_applicable"),AND(NOT(AND(D3="retain",E3="protocol_report")),L3<>"",L3<>"not_applicable")),"CLEAR INACTIVE VALUES",IF(OR(NOT(OR(D3="retain",D3="exclude",D3="discuss")),NOT(OR(E3="statistical_results",E3="report_internal_inconsistency",E3="plan_material",E3="protocol_report")),AND(AND(D3="retain",E3="statistical_results"),NOT(OR(H3="confirmed_issue",H3="probable_issue",H3="not_issue",H3="indeterminate"))),AND(AND(D3="retain",E3="statistical_results"),NOT(OR(I3="substantive",I3="minor_presentation",I3="indeterminate"))),AND(AND(D3="retain",E3="statistical_results"),J3<>"",NOT(OR(J3="direct",J3="possible",J3="unlikely",J3="unknown"))),AND(AND(D3="retain",OR(E3="report_internal_inconsistency",E3="plan_material")),NOT(OR(K3="substantive_inconsistency",K3="minor_presentation",K3="non_inconsistency",K3="indeterminate"))),AND(AND(D3="retain",E3="protocol_report"),L3<>"",NOT(OR(L3="substantive_difference",L3="minor_presentation",L3="version_timing",L3="non_inconsistency",L3="indeterminate")))),"CHECK FIELDS",IF(AND(F3<>"",NOT(OR(F3="no",F3="primary_done"))),"CHECK COMPLETE",IF(F3="primary_done","PRIMARY READY","PRIMARY DRAFT")))))),"CHECK INPUT / KEY") -> PRIMARY READY | H3: confirmed_issue | I3: substantive | R3: TEST 2025::jama.2025.19563::C002
A4: 2025::jama.2025.19563::C003 | B4: Figure 3 labels BMI values in kg/m² as “weight” | C4: DOC-001 main article — PDF p. 8; DOC-001 main article — PDF p. 6; DOC-003 supplement — PDF p. 53. | D4: retain | E4: report_internal_inconsistency | F4: primary_done | G4: =IFERROR(IF(LEN(TRIM(CLEAN(SUBSTITUTE(Setup!$B$2,CHAR(160)," "))))=0,"CHECK REVIEWER ID",IF(OR(A4="",(COUNTIF('C_jama.2024.24764'!$A$2:$A$9,A4)+COUNTIF('C_jama.2024.27643'!$A$2:$A$9,A4)+COUNTIF('C_jama.2025.11178'!$A$2:$A$38,A4)+COUNTIF('C_jama.2025.15185'!$A$2:$A$13,A4)+COUNTIF('C_jama.2025.15440'!$A$2:$A$3,A4)+COUNTIF('C_jama.2025.16450'!$A$2:$A$11,A4)+COUNTIF('C_jama.2025.19563'!$A$2:$A$8,A4)+COUNTIF('C_jama.2025.19843'!$A$2:$A$2,A4)+COUNTIF('C_jama.2025.20765'!$A$2:$A$14,A4)+COUNTIF('C_jama.2025.24175'!$A$2:$A$15,A4)+COUNTIF('C_jama.2025.4390'!$A$2:$A$4,A4)+COUNTIF('C_jama.2025.7583'!$A$2:$A$4,A4)+COUNTIF('C_jama.2025.7710'!$A$2:$A$5,A4)+COUNTIF('C_jama.2025.9110'!$A$2:$A$7,A4)+COUNTIF('C_jama.2025.9663'!$A$2:$A$4,A4))<>1,COUNTIFS(Candidates!$G$2:$G$132,A4,Candidates!$K$2:$K$132,"jama.2025.19563")<>1),"CHECK KEY",IF(OR(AND(NOT(AND(D4="retain",E4="statistical_results")),H4<>"",H4<>"not_applicable"),AND(NOT(AND(D4="retain",E4="statistical_results")),I4<>"",I4<>"not_applicable"),AND(NOT(AND(D4="retain",E4="statistical_results")),J4<>"",J4<>"not_applicable"),AND(NOT(AND(D4="retain",OR(E4="report_internal_inconsistency",E4="plan_material"))),K4<>"",K4<>"not_applicable"),AND(NOT(AND(D4="retain",E4="protocol_report")),L4<>"",L4<>"not_applicable")),"CLEAR INACTIVE VALUES",IF(OR(NOT(OR(D4="retain",D4="exclude",D4="discuss")),NOT(OR(E4="statistical_results",E4="report_internal_inconsistency",E4="plan_material",E4="protocol_report")),AND(AND(D4="retain",E4="statistical_results"),NOT(OR(H4="confirmed_issue",H4="probable_issue",H4="not_issue",H4="indeterminate"))),AND(AND(D4="retain",E4="statistical_results"),NOT(OR(I4="substantive",I4="minor_presentation",I4="indeterminate"))),AND(AND(D4="retain",E4="statistical_results"),J4<>"",NOT(OR(J4="direct",J4="possible",J4="unlikely",J4="unknown"))),AND(AND(D4="retain",OR(E4="report_internal_inconsistency",E4="plan_material")),NOT(OR(K4="substantive_inconsistency",K4="minor_presentation",K4="non_inconsistency",K4="indeterminate"))),AND(AND(D4="retain",E4="protocol_report"),L4<>"",NOT(OR(L4="substantive_difference",L4="minor_presentation",L4="version_timing",L4="non_inconsistency",L4="indeterminate")))),"CHECK FIELDS",IF(AND(F4<>"",NOT(OR(F4="no",F4="primary_done"))),"CHECK COMPLETE",IF(F4="primary_done","PRIMARY READY","PRIMARY DRAFT")))))),"CHECK INPUT / KEY") -> PRIMARY READY | K4: substantive_inconsistency | R4: TEST 2025::jama.2025.19563::C003
A5: 2025::jama.2025.19563::C004 | B5: eTables 5-7 leave the comparator scope of a repeated age P value ambiguous | C5: DOC-003 supplement — PDF p. 39; DOC-003 supplement — PDF p. 43; DOC-003 supplement — PDF p. 45; DOC-003 supplement — PDF p. 47; DOC-001 main article — PDF p. 6. | D5: retain | E5: report_internal_inconsistency | F5: primary_done | G5: =IFERROR(IF(LEN(TRIM(CLEAN(SUBSTITUTE(Setup!$B$2,CHAR(160)," "))))=0,"CHECK REVIEWER ID",IF(OR(A5="",(COUNTIF('C_jama.2024.24764'!$A$2:$A$9,A5)+COUNTIF('C_jama.2024.27643'!$A$2:$A$9,A5)+COUNTIF('C_jama.2025.11178'!$A$2:$A$38,A5)+COUNTIF('C_jama.2025.15185'!$A$2:$A$13,A5)+COUNTIF('C_jama.2025.15440'!$A$2:$A$3,A5)+COUNTIF('C_jama.2025.16450'!$A$2:$A$11,A5)+COUNTIF('C_jama.2025.19563'!$A$2:$A$8,A5)+COUNTIF('C_jama.2025.19843'!$A$2:$A$2,A5)+COUNTIF('C_jama.2025.20765'!$A$2:$A$14,A5)+COUNTIF('C_jama.2025.24175'!$A$2:$A$15,A5)+COUNTIF('C_jama.2025.4390'!$A$2:$A$4,A5)+COUNTIF('C_jama.2025.7583'!$A$2:$A$4,A5)+COUNTIF('C_jama.2025.7710'!$A$2:$A$5,A5)+COUNTIF('C_jama.2025.9110'!$A$2:$A$7,A5)+COUNTIF('C_jama.2025.9663'!$A$2:$A$4,A5))<>1,COUNTIFS(Candidates!$G$2:$G$132,A5,Candidates!$K$2:$K$132,"jama.2025.19563")<>1),"CHECK KEY",IF(OR(AND(NOT(AND(D5="retain",E5="statistical_results")),H5<>"",H5<>"not_applicable"),AND(NOT(AND(D5="retain",E5="statistical_results")),I5<>"",I5<>"not_applicable"),AND(NOT(AND(D5="retain",E5="statistical_results")),J5<>"",J5<>"not_applicable"),AND(NOT(AND(D5="retain",OR(E5="report_internal_inconsistency",E5="plan_material"))),K5<>"",K5<>"not_applicable"),AND(NOT(AND(D5="retain",E5="protocol_report")),L5<>"",L5<>"not_applicable")),"CLEAR INACTIVE VALUES",IF(OR(NOT(OR(D5="retain",D5="exclude",D5="discuss")),NOT(OR(E5="statistical_results",E5="report_internal_inconsistency",E5="plan_material",E5="protocol_report")),AND(AND(D5="retain",E5="statistical_results"),NOT(OR(H5="confirmed_issue",H5="probable_issue",H5="not_issue",H5="indeterminate"))),AND(AND(D5="retain",E5="statistical_results"),NOT(OR(I5="substantive",I5="minor_presentation",I5="indeterminate"))),AND(AND(D5="retain",E5="statistical_results"),J5<>"",NOT(OR(J5="direct",J5="possible",J5="unlikely",J5="unknown"))),AND(AND(D5="retain",OR(E5="report_internal_inconsistency",E5="plan_material")),NOT(OR(K5="substantive_inconsistency",K5="minor_presentation",K5="non_inconsistency",K5="indeterminate"))),AND(AND(D5="retain",E5="protocol_report"),L5<>"",NOT(OR(L5="substantive_difference",L5="minor_presentation",L5="version_timing",L5="non_inconsistency",L5="indeterminate")))),"CHECK FIELDS",IF(AND(F5<>"",NOT(OR(F5="no",F5="primary_done"))),"CHECK COMPLETE",IF(F5="primary_done","PRIMARY READY","PRIMARY DRAFT")))))),"CHECK INPUT / KEY") -> PRIMARY READY | K5: substantive_inconsistency | R5: TEST 2025::jama.2025.19563::C004
A6: 2025::jama.2025.19563::C005 | B6: eTable 7 pairs “no statistically significant” with p<0.05 | C6: DOC-003 supplement — PDF p. 46; DOC-003 supplement — PDF p. 47. | D6: retain | E6: statistical_results | F6: primary_done | G6: =IFERROR(IF(LEN(TRIM(CLEAN(SUBSTITUTE(Setup!$B$2,CHAR(160)," "))))=0,"CHECK REVIEWER ID",IF(OR(A6="",(COUNTIF('C_jama.2024.24764'!$A$2:$A$9,A6)+COUNTIF('C_jama.2024.27643'!$A$2:$A$9,A6)+COUNTIF('C_jama.2025.11178'!$A$2:$A$38,A6)+COUNTIF('C_jama.2025.15185'!$A$2:$A$13,A6)+COUNTIF('C_jama.2025.15440'!$A$2:$A$3,A6)+COUNTIF('C_jama.2025.16450'!$A$2:$A$11,A6)+COUNTIF('C_jama.2025.19563'!$A$2:$A$8,A6)+COUNTIF('C_jama.2025.19843'!$A$2:$A$2,A6)+COUNTIF('C_jama.2025.20765'!$A$2:$A$14,A6)+COUNTIF('C_jama.2025.24175'!$A$2:$A$15,A6)+COUNTIF('C_jama.2025.4390'!$A$2:$A$4,A6)+COUNTIF('C_jama.2025.7583'!$A$2:$A$4,A6)+COUNTIF('C_jama.2025.7710'!$A$2:$A$5,A6)+COUNTIF('C_jama.2025.9110'!$A$2:$A$7,A6)+COUNTIF('C_jama.2025.9663'!$A$2:$A$4,A6))<>1,COUNTIFS(Candidates!$G$2:$G$132,A6,Candidates!$K$2:$K$132,"jama.2025.19563")<>1),"CHECK KEY",IF(OR(AND(NOT(AND(D6="retain",E6="statistical_results")),H6<>"",H6<>"not_applicable"),AND(NOT(AND(D6="retain",E6="statistical_results")),I6<>"",I6<>"not_applicable"),AND(NOT(AND(D6="retain",E6="statistical_results")),J6<>"",J6<>"not_applicable"),AND(NOT(AND(D6="retain",OR(E6="report_internal_inconsistency",E6="plan_material"))),K6<>"",K6<>"not_applicable"),AND(NOT(AND(D6="retain",E6="protocol_report")),L6<>"",L6<>"not_applicable")),"CLEAR INACTIVE VALUES",IF(OR(NOT(OR(D6="retain",D6="exclude",D6="discuss")),NOT(OR(E6="statistical_results",E6="report_internal_inconsistency",E6="plan_material",E6="protocol_report")),AND(AND(D6="retain",E6="statistical_results"),NOT(OR(H6="confirmed_issue",H6="probable_issue",H6="not_issue",H6="indeterminate"))),AND(AND(D6="retain",E6="statistical_results"),NOT(OR(I6="substantive",I6="minor_presentation",I6="indeterminate"))),AND(AND(D6="retain",E6="statistical_results"),J6<>"",NOT(OR(J6="direct",J6="possible",J6="unlikely",J6="unknown"))),AND(AND(D6="retain",OR(E6="report_internal_inconsistency",E6="plan_material")),NOT(OR(K6="substantive_inconsistency",K6="minor_presentation",K6="non_inconsistency",K6="indeterminate"))),AND(AND(D6="retain",E6="protocol_report"),L6<>"",NOT(OR(L6="substantive_difference",L6="minor_presentation",L6="version_timing",L6="non_inconsistency",L6="indeterminate")))),"CHECK FIELDS",IF(AND(F6<>"",NOT(OR(F6="no",F6="primary_done"))),"CHECK COMPLETE",IF(F6="primary_done","PRIMARY READY","PRIMARY DRAFT")))))),"CHECK INPUT / KEY") -> PRIMARY READY | H6: confirmed_issue | I6: substantive | R6: TEST 2025::jama.2025.19563::C005
A7: 2025::jama.2025.19563::C006 | B7: eTable 10b labels one comparison as both chi-squared and Wilcoxon rank-sum | C7: DOC-003 supplement — PDF p. 29; DOC-003 supplement — PDF p. 52. | D7: retain | E7: statistical_results | F7: primary_done | G7: =IFERROR(IF(LEN(TRIM(CLEAN(SUBSTITUTE(Setup!$B$2,CHAR(160)," "))))=0,"CHECK REVIEWER ID",IF(OR(A7="",(COUNTIF('C_jama.2024.24764'!$A$2:$A$9,A7)+COUNTIF('C_jama.2024.27643'!$A$2:$A$9,A7)+COUNTIF('C_jama.2025.11178'!$A$2:$A$38,A7)+COUNTIF('C_jama.2025.15185'!$A$2:$A$13,A7)+COUNTIF('C_jama.2025.15440'!$A$2:$A$3,A7)+COUNTIF('C_jama.2025.16450'!$A$2:$A$11,A7)+COUNTIF('C_jama.2025.19563'!$A$2:$A$8,A7)+COUNTIF('C_jama.2025.19843'!$A$2:$A$2,A7)+COUNTIF('C_jama.2025.20765'!$A$2:$A$14,A7)+COUNTIF('C_jama.2025.24175'!$A$2:$A$15,A7)+COUNTIF('C_jama.2025.4390'!$A$2:$A$4,A7)+COUNTIF('C_jama.2025.7583'!$A$2:$A$4,A7)+COUNTIF('C_jama.2025.7710'!$A$2:$A$5,A7)+COUNTIF('C_jama.2025.9110'!$A$2:$A$7,A7)+COUNTIF('C_jama.2025.9663'!$A$2:$A$4,A7))<>1,COUNTIFS(Candidates!$G$2:$G$132,A7,Candidates!$K$2:$K$132,"jama.2025.19563")<>1),"CHECK KEY",IF(OR(AND(NOT(AND(D7="retain",E7="statistical_results")),H7<>"",H7<>"not_applicable"),AND(NOT(AND(D7="retain",E7="statistical_results")),I7<>"",I7<>"not_applicable"),AND(NOT(AND(D7="retain",E7="statistical_results")),J7<>"",J7<>"not_applicable"),AND(NOT(AND(D7="retain",OR(E7="report_internal_inconsistency",E7="plan_material"))),K7<>"",K7<>"not_applicable"),AND(NOT(AND(D7="retain",E7="protocol_report")),L7<>"",L7<>"not_applicable")),"CLEAR INACTIVE VALUES",IF(OR(NOT(OR(D7="retain",D7="exclude",D7="discuss")),NOT(OR(E7="statistical_results",E7="report_internal_inconsistency",E7="plan_material",E7="protocol_report")),AND(AND(D7="retain",E7="statistical_results"),NOT(OR(H7="confirmed_issue",H7="probable_issue",H7="not_issue",H7="indeterminate"))),AND(AND(D7="retain",E7="statistical_results"),NOT(OR(I7="substantive",I7="minor_presentation",I7="indeterminate"))),AND(AND(D7="retain",E7="statistical_results"),J7<>"",NOT(OR(J7="direct",J7="possible",J7="unlikely",J7="unknown"))),AND(AND(D7="retain",OR(E7="report_internal_inconsistency",E7="plan_material")),NOT(OR(K7="substantive_inconsistency",K7="minor_presentation",K7="non_inconsistency",K7="indeterminate"))),AND(AND(D7="retain",E7="protocol_report"),L7<>"",NOT(OR(L7="substantive_difference",L7="minor_presentation",L7="version_timing",L7="non_inconsistency",L7="indeterminate")))),"CHECK FIELDS",IF(AND(F7<>"",NOT(OR(F7="no",F7="primary_done"))),"CHECK COMPLETE",IF(F7="primary_done","PRIMARY READY","PRIMARY DRAFT")))))),"CHECK INPUT / KEY") -> PRIMARY READY | H7: confirmed_issue | I7: substantive | R7: TEST 2025::jama.2025.19563::C006
